Workbook

Sheet CONTRATOS VIGENTES
A1: =TODAY() -> 46167
C2: TÉRMINO DA VIGÊNCIA | D2: CONTRATO | E2: ADITIVO | F2: FORNECEDOR | G2: SECRETARIA | H2: SECRETÁRIO | I2: GESTOR | J2: FISCAL | K2: OBJETO | L2: VIGÊNCIA | M2: DATA DA OS | N2: PERÍODO | O2: PROCESSO ADMINISTRATIVO | P2: PROCESSO EXECUÇÃO | Q2: AUDESP LICITAÇÃO | R2: AUDESP AJUSTE | S2: MODALIDADE LICITAÇÃO | T2: VALOR TOTAL CONTRATO | U2: ASSINATURA | V2: DATA DE PUBLICAÇÃO | W2: OBSERVAÇÃO
A3: CONTRATOS COM VENCIMENTO: MARÇO 2026
A4: =C4-$A$1 -> 310 | B4: =IF(A4<60,"Vencendo","Em Vigência") -> Em Vigência | C4: 46477 | D4: 12/24 | E4: 1º Aditivo | F4: LECASA PARTICIPAÇÕES E EMPREENDIMENTOS IMOBILIÁRIOS LTDA CNPJ - 21.091.888/0001-95 | G4: SAÚDE | H4: Felipe Vieira de Sá dos Santos CPF: 361.930.868-38 | I4: Alex Sandro Barroso Alves CPF: 303.636.638-51 | J4: Débora Gomes dos Santos CPF: 420.245.978-40 | K4: LOCAÇÃO DE IMÓVEL SITUADO NO MUNÍCIPIO DE RIO GRANDE DA SERRA, NA AVENIDA DOM PEDRO I ESQUINA COM A RUA VENÂNCIO ORSINI, PARA O FIM EXCLUSIVO DA INSTALAÇÃO DO CENTRO MÉDICO DE ESPECIALIDADE (CEME). | L4: 24 MESES | M4: - | N4: 01/04/26 A 31/03/28 | O4: 205/24 | P4: 779/24 | Q4: 2024000000150 | R4: 2024000000196 | S4: INEX 04/24 | T4: 336000 | U4: 46113
A5: CONTRATOS COM VENCIMENTO: MAIO 2026
A6: =C6-$A$1 -> -2 | B6: =IF(A6<60,"Vencendo","Em Vigência") -> Vencendo | C6: 46165 | D6: 18/23 | E6: 2º Aditivo | F6: ESPAÇO 2 TECNOLOGIA E INFORMÁTICA LTDA EPP CNPJ - 09.066.243/0001-05 | G6: ADMINISTRAÇÃO | H6: MILTON DE SOUZA MARTINS - CPF/MF sob o nº. 107.599.858-12 | I6: Elias | J6: Fábio Eduardo Garcia | K6: CONTRATAÇÃO DE EMPRESA ESPECIALIZADA PARA PRESTAÇÃO DE SERVIÇOS DE LOCAÇÃO, POR MEIO DE DISPONIBILIDADE DE EQUIPAMENTOS (MULTIFUNCIONAIS) DESTINADOS À IMPRESSÃO, REPROGRAFIA E DIGITALIZAÇÃO DE DOCUMENTOS NAS DEPENDÊNCIAS DA PREFEITURA MUNICIPAL DE RIO GRANDE DA SERRA | L6: 12 MESES com cláusula resolutiva | N6: 24/05/25 a 23/05/26 | O6: 303/22 | P6: 1130/23 | Q6: 2023000000071 | R6: AJUSTE 2023000000269 1 TERMO ADITIVO 2023000000019 2 TERMO ADITIVO 2024000000039 3 TERMO ADITIVO 2025000000051 | S6: PP 25/23 | T6: 248220 | U6: 45800 | V6: 45810
A7: =C7-$A$1 -> 1 | B7: =IF(A7<60,"Vencendo","Em Vigência") -> Vencendo | C7: 46168 | D7: 16/25 | E7: Contrato | F7: MARIA CAPARROZ SANTINELLI | G7: ESPORTE | H7: Nikson Nonato Nascimento Andrade CPF 337.710.608-18 | I7: Nikson Nonato Nascimento Andrade CPF 337.710.608-18 | J7: Luana Aline dos Santos CPF 350.638.378-75 | K7: LOCAÇÃO DE IMÓVEL PARA ATENDIMENTO DO PROJETO DE ARTES MARCIAIS FAZER VALER | L7: 12 meses | N7: 26/05/2025 a 26/05/2026 | O7: 207/25 | P7: 996/25 | R7: 2025000000401 | S7: INEX 13/25 | T7: 51600 | U7: 45803 | V7: 45810
A8: =C8-$A$1 -> 1 | B8: =IF(A8<60,"Vencendo","Em Vigência") -> Vencendo | C8: 46168 | D8: 48/24 | E8: 1º Aditivo | F8: RENOV PAVIMENTAÇÃO E CONSTRUÇÕES LTDA | G8: OBRAS | H8: Wanderlei Felipe da Silva Junior | I8: Leila Andreassi de Castro | J8: Guilherme Tadeu Aparecido de Oliveira Dias do Prado | K8: CONTRATAÇÃO DE EMPRESA ESPECIALIZADA PARA INTERVENÇÕES URBANÍSTICAS NA RUA ARUJÁ – VILA CONDE SICILIANO, RECAPEAMENTO ASFÁLTICO E CONTENÇÃO NO MUNICÍPIO DE RIO GRANDE DA SERRA / SP | L8: 270 DIAS | M8: 45628 | N8: 29/08/25 A 26/05/2026 | O8: 1114/2024 | P8: 2265/2024 | Q8: 2024000000279 | R8: 2024000000642 1º TERMO ADITIVO 2025000000082 | S8: CO 06/24 | T8: 854235.15 | U8: 45897 | V8: 45898
A9: CONTRATOS COM VENCIMENTO: JUNHO 2026
A10: =C10-$A$1 -> 10 | B10: =IF(A10<60,"Vencendo","Em Vigência") -> Vencendo | C10: 46177 | D10: 17/25 | E10: Contrato | F10: 4F SOLUÇÕES EM TECNOLOGIA LTDA | G10: ADMINISTRAÇÃO | H10: MILTON DE SOUZA MARTINS - CPF/MF sob o nº. 107.599.858-12 | I10: ELIAS RODRIGUES DO PRADO CPF 227.197.288-45 | J10: ARTHUR GALDINO MARQUES CPF 535.998.138-50 | K10: CONTRATAÇÃO DE EMPRESA ESPECIALIZADA NO FORNECIMENTO DE 300 LICENÇAS DE SOFTWARE DE ANTIVÍRUS, ACOMPANHADAS DE SUPORTE TÉCNICO PELO PERÍODO DE 12 MESES | L10: 12 meses | N10: 04/06/25 a 04/06/25 | O10: 663/25 | P10: 1098/25 | Q10: 2025000000155 | R10: 2025000000406 | S10: DP 15/25 | T10: 39999 | U10: 45807 | V10: 45812
A11: =C11-$A$1 -> 11 | B11: =IF(A11<60,"Vencendo","Em Vigência") -> Vencendo | C11: 46178 | D11: 54/24 | E11: Contrato | F11: NELY RODRIGUES CONSTRUÇÕES CIVIS, COMÉRCIO E PRESTAÇÃO DE SERVIÇOS LTDA CNPJ sob o nº 01.969.162/0001-03 | G11: OBRAS | H11: Leandro Dias Florêncio CPF: 335.659.528-81 | I11: Leila Andreassi de Castro CPF: 235.681.298-92 | J11: Guilherme Tadeu Aparecido de Oliveira Dias do Prado CPF: 414.046.498-40 | K11: CONTRATAÇÃO DE EMPRESA ESPECIALIZADA PARA EXECUÇÃO DA PRAÇA ESPORTIVA NA RUA OSASCO - RECANTO DAS FLORES NO MUNICÍPIO DE RIO GRANDE DA SERRA/SP | L11: 210 DIAS | N11: 05/11/25 A 05/06/26 | O11: 1113/2024 | P11: 2239/2025 | Q11: 2024000000291 | R11: AJUSTE 2025000000587 | S11: CP 08/24 | T11: 198900 | U11: 45631 | V11: 45966 | W11: AUTORIZADO O ANDAMENTO DO PROCESSO SOMENTE EM 05/11/2025.
A12: =C12-$A$1 -> 17 | B12: =IF(A12<60,"Vencendo","Em Vigência") -> Vencendo | C12: 46184 | D12: 30/22 | E12: 4º Aditivo | F12: WHITE MARTINS GASES INDUSTRIAIS LTDA CNPJ: 35.820.448/0081-10 | G12: SAÚDE | H12: FELIPE VIEIRA DE SÁ DOS SANTOS CPF sob o nº 361.930.868-38 | I12: Aline Lima da Silva Toledo | J12: Telma Moraes Pires | K12: CONTRATAÇÃO DE EMPRESA ESPECIALIZADA PARA FORNECIMENTO CONTÍNUO E ININTERRUPTO DE OXIGÊNIO GASOSO EM CILINDROS COM LOCAÇÃO DE CILINDROS PARA ATENDER AS UNIDADES DE SAÚDE E UPA - UNIDADE DE PRONTO ATENDIMENTO | L12: 180 dias | M12: 45276 | N12: 13/12/25 A 11/06/26 | O12: 1475/22 | P12: 2451/22 | Q12: 2022000000126 | R12: 2022000000409 2º TERMO ADITIVO 2025000000025 3º TERMO ADITIVO 2025000000065 4º TERMO ADITIVO 2026000000006 | S12: PP 31/22 | T12: 622152 | U12: 45824 | V12: 45853
A13: =C13-$A$1 -> 25 | B13: =IF(A13<60,"Vencendo","Em Vigência") -> Vencendo | C13: 46192 | D13: 07/26 | E13: Contrato | F13: HC COMERCIO E SERVICOS LTDA CNPJ/MF sob o nº 39.346.967/0001-65 | G13: EDUCAÇÃO | H13: VINÍCIUS BRUM DA SILVA CIN sob o nº 406.779.358-89 | I13: Mônica Mara Rodrigues | J13: Greyce Sueli de Miranda Lima Paula | K13: AQUISIÇÃO DE KITS DE UNIFORMES ESCOLARES | L13: 03 meses | M13: - | N13: 19/03/26 a 19/06/26 | O13: 89/26 | P13: - | Q13: 2026000000003 | R13: 2026000000008 | S13: ADESÃO ATA 39/24 TABOÃO DA SERRA | T13: 815510.94 | U13: 46100 | V13: 46101
A14: =C14-$A$1 -> 32 | B14: =IF(A14<60,"Vencendo","Em Vigência") -> Vencendo | C14: 46199 | D14: 19/24 | E14: Contrato | F14: FL CONTROLE DE PRAGAS E SERVIÇO GERAIS LTDA RUA JOÃO THEODORO, 131, CENTRO CIDADE JACAREÍ/SP CEP: 12.308-720 | G14: Cidadania | H14: ELSA DOS ANJOS IWASAKI | I14: FERNANDA STACHOWSKI | J14: CIBELY APARECIDA MIRANDA DOS SANTOS | K14: CONTRATAÇÃO DE EMPRESA PARA PRESTAÇÃO DE SERVIÇOS DE DEDETIZAÇÃO E DESRATIZAÇÃO, SENDO 02 (DUAS) APLICAÇÕES COM INTERVALO DE 06 (SEIS) MESES, COM O EFETIVO CONTROLE DE PRAGAS, DAS ÁREAS INTERNAS E EXTERNAS DAS UNIDADES: CRAS, CREAS, SAICA (SERVIÇO DE ACOLHIMENTO INSTITUCIONAL PARA CRIANÇAS E ADOLESCENTES), CONSELHO TUTELAR, E DA SEDE DA SECRETARIA DA FAMÍLIA E DESENVOLVIMENTO SOCIAL | L14: 12 MESES | N14: 26/06/2025 A 26/06/2026 | O14: 144/2025 | P14: 1242/2025 | Q14: NÃO SE APLICA | R14: NÃO SE APLICA | S14: DP 16/23 | T14: 3000 | U14: 45826 | V14: 45834
A15: =C15-$A$1 -> 33 | B15: =IF(A15<60,"Vencendo","Em Vigência") -> Vencendo | C15: 46200 | D15: 14/22 | E15: 3º Aditivo | F15: CESPRO PROCESSAMENTO DE DADOS LTDA CNPJ - 17.875.435/0001-82 | G15: JURÍDICO | H15: Fábio Nunes Fernandes | I15: Elaine de Souza Pereira | J15: Jairson Virginio dos Santos | K15: SERVIÇOS DE CONSOLIDAÇÃO DA LEGISLAÇÃO MUNICIPAL, DE MODO INFORMATIZADO, PARA UTILIZAÇÃO VIA INTERNET | L15: 12 meses | N15: 27/06/25 a 27/06/26 | O15: 197/22 | P15: 1456/22 | Q15: 2022000000072 | R15: 3º TERMO ADITIVO 2025000000067 | S15: DP 06/22 | T15: 3480 | U15: 45835 | V15: 45841
A16: CONTRATOS COM VENCIMENTO: JULHO 2026
A17: =C17-$A$1 -> 38 | B17: =IF(A17<60,"Vencendo","Em Vigência") -> Vencendo | C17: 46205 | D17: 45/23 | E17: 3º Aditivo | F17: RENOV PAVIMENTAÇÃO E CONSTRUÇÕES LTDA - EPP CNPJ - 2024000000071 | G17: OBRAS | H17: Wanderlei Felipe da Silva Junior | I17: LEILA ANDREASSI DE CASTRO | J17: Guilherme Tadeu Aparecido de Oliveira Dias do Prado | K17: CONTRATAÇÃO DE EMPRESA PARA EXECUÇÃO DE PAVIMENTAÇÃO, DRENAGEM E SINALIZAÇÃO VIÁRIA - RUA CAMPOS SALES E RUA VALINHOS NO MUNICÍPIO DE RIO GRANDE DA SERRA | L17: 450 DIAS | M17: 45215 | N17: 05/10/2025 a 02/07/2026 | O17: 1148/22 | P17: 1986/23 | Q17: 2023000000118 | R17: Ajuste 2023000000388 Aditivo 1 2024000000028 Aditivo 2 2025000000009 Aditivo 3 2025000000091 | S17: CO 08/23 | T17: 2437957.5 | U17: 45935 | V17: 45967 | W17: VIGENCIA A PARTIR DA ORDEM DE INICIO
A18: =C18-$A$1 -> 49 | B18: =IF(A18<60,"Vencendo","Em Vigência") -> Vencendo | C18: 46216 | D18: 56/24 | E18: Contrato | F18: UPC - URBANA PAULISTA CONSTRUTORA LTDA CNPJ: 23.094.219/0001-00 | G18: OBRAS | H18: Leandro Dias Florencio CPF: 335.659.528-81 | I18: Leila Andreassi de Castro CPF: 235.681.298-92 | J18: Guilherme Tadeu Aparecido de Oliveira Dias do Prado CPF: 414.046.498-40 | K18: CONTRATAÇÃO DE EMPRESA ESPECIALIZADA PARA EXECUÇÃO DE RECAPEAMENTO E PAVIMENTAÇÃO ASFÁLTICA COM SINALIZAÇÃO VIÁRIA HORIZONTAL – ÁREA CENTRAL: RUA PREFEITO CARLOS JOSÉ CARLSON, RUA PASTOR AQUILINO SARTORI, RUA VENÂNCIO ORSINI E RUA PEDRO BRACIALLI NO MUNICÍPIO DE RIO GRANDE DA SERRA – SP | L18: 15 MESES | M18: 46126 | N18: 14/04/2024 A 13/07/2026 | O18: 1208/2024 | P18: 301/2025 | Q18: 2024000000301 | R18: 2025000000195 REEVIADO AUDESP VIGÊNCIA A PARTIR DA OS 2026000000072 | S18: CE 11/24 | T18: R$ 654.000,00 | U18: 45639 | V18: 45714
A19: CONTRATOS COM VENCIMENTO: AGOSTO 2026
A20: =C20-$A$1 -> 70 | B20: =IF(A20<60,"Vencendo","Em Vigência") -> Em Vigência | C20: 46237 | D20: 12/20 | E20: 5º Aditivo | F20: MARCIA ANDREA ZUCCO NISHIKAWARA CPF - 251.418.818-06 | G20: SAÚDE | H20: FELIPE VIEIRA DE SÁ DOS SANTOS | I20: Paula Azevedo Lopes | J20: Bianca Dantas Jacob | K20: LOCAÇÃO DE IMÓVEL SITUADO A RUA PREFEITO JOSÉ CARLSON, 07 - CENTRO - PARA ATENDER AS INSTALAÇÕES DO CAPS - CENTRO DE ATENÇÃO PSICOSSOCIAL | L20: 12 meses | N20: 03/08/24 a 03/08/25 | O20: 1987/19 | P20: 1418/20 | R20: 5º TERMO ADITIVO 2025000000075 | S20: DP 9/2020 | T20: 66420 | U20: 45870 | V20: 45904
A21: =C21-$A$1 -> 72 | B21: =IF(A21<60,"Vencendo","Em Vigência") -> Em Vigência | C21: 46239 | D21: 16/22 | E21: 3º Aditivo | F21: MARIA SANTOS SILVA CPF - 097.374.208-96 | G21: CIDADANIA | H21: Elza Dos Anjos Iwasaki | I21: Ilana Rodrigues Mariano | J21: Fernanda Stachowski | K21: LOCAÇÃO DE IMÓVEL SITO A RUA JOSE MARIA DE FIGUEIREDO, 575 - VILA GONÇALVES - RIO GRANDE DA SERRA/SP, ONDE ESTA INSTALADO O CREAS - CENTRO DE REFERENCIA DE ASSISTENCIA SOCIAL | L21: 12 meses | M21: 44778 | N21: 05/08/25 A 05/08/26 | O21: 930/22 | P21: 1583/22 | Q21: 2022000000091 | R21: 2024000000035 3º TERMO ADITIVO 2025000000069 | S21: DP 9/22 | T21: 38738.28 | U21: 45866 | V21: 45867
A22: =C22-$A$1 -> 80 | B22: =IF(A22<60,"Vencendo","Em Vigência") -> Em Vigência | C22: 46247 | D22: 34/24 | E22: 2º Aditivo | F22: RENOV PAVIMENTAÇÃO E CONSTRUÇÕES LTDA - EPP - | G22: OBRAS | H22: Wanderlei Felipe da Silva Junior | I22: LEILA ANDREASSI DE CASTRO | J22: Guilherme Tadeu Aparecido de Oliveira Dias do Prado | K22: CONTRATAÇÃO DE EMPRESA ESPECIALIZADA PARA EXECUÇÃO DE PAVIMENTAÇÃO ASFÁLTICA, DRENAGEM E SINALIZAÇÃO VIÁRIA – RUA JOAQUIM LOPES – BAIRRO VILA LOPES, NO MUNICÍPIO DE RIO GRANDE DA SERRA/SP | L22: 360 | M22: 45614 | N22: 18/08/2025 A 13/08/2026 | O22: 638/2024 | P22: 1612/2024 | Q22: 2024000000232 | R22: 2024000000602 1º aditivo 2025000000083 2º aditivo | S22: CP 04/24 | T22: 1996000 | U22: 45960 | V22: 45967
A23: =C23-$A$1 -> 81 | B23: =IF(A23<60,"Vencendo","Em Vigência") -> Em Vigência | C23: 46248 | D23: 32/23 | E23: 1º Aditivo | F23: N.K. FIBER LINK LTDA CNPJ - 29.845.988/0001-71 | G23: ADMINISTRAÇÃO | H23: Alex Sandro | I23: Elias Rodrigues do Prado | J23: Fabio Eduardo Garcia | K23: LOCAÇÃO DE CIRCUITO DE VÍDEO-MONITORAMENTO NAS DEPENDÊNCIAS DA PREFEITURA MUNICIPAL DE RIO GRANDE DA SERRA | L23: 12 meses | N23: 14/08/24 A 14/08/25 | O23: 680/23 | P23: 1805/23 | Q23: 2023000000106 | R23: 2023000000361 | S23: CD 161/23 | T23: 17280 | U23: 45511 | V23: 45156
E24: 2º Aditivo | H24: Milton de Souza Martins | I24: Elias Rodrigues do Prado | J24: Fabio Eduardo Garcia | L24: 12 meses | N24: 14/08/25 A 14/08/26 | R24: 2025000000079 | T24: 17280 | U24: 45883 | V24: 45910
A25: =C25-$A$1 -> 95 | B25: =IF(A25<60,"Vencendo","Em Vigência") -> Em Vigência | C25: 46262 | D25: 36/23 | E25: 2º Aditivo | F25: NARCISIO CALASANS VIEIRA CPF - 124.629.878-35 | G25: SAÚDE | H25: Felipe Vieira de Sá dos Santos | I25: Maria Olivia Paulino Torres Portugal | J25: Sandra Emidio da Silva Calheiros | K25: LOCAÇÃO DE IMÓVEL SITO À RUA CEARÁ, 261 - VILA SÃO JOÃO, ONDE ESTÁ INSTALADO A UNIDADE BÁSICA DE SAÚDE - VILA SÃO JOÃO | L25: 12 meses | M25: 45166 | N25: 28/08/25 A 28/08/26 | O25: 751/20 | P25: 1776/23 | R25: 2º TERMO ADITIVO 2025000000073 | S25: DP 16/23 | T25: 18145.56 | U25: 45896 | V25: 45905
A26: =C26-$A$1 -> 96 | B26: =IF(A26<60,"Vencendo","Em Vigência") -> Em Vigência | C26: 46263 | D26: 30/24 | E26: 1º Aditivo | F26: INNOVAMED MANUTENÇÃO DE EQUIPAMENTOS MÉDICOS LTDA CNPJ - 59.055.921/0001-02 | G26: SAÚDE | H26: FELIPE VIEIRA DE SÁ DOS SANTOS | I26: Silvana Moraes Branco Conceição | J26: UBS CENTRO FISCAL DO CONTRATO: Laize Aparecida Mendes UBS VILA NIWA FISCAL DO CONTRATO: Ana Paula de Matos Merlos Pompeo UBS SÃO JOÃO FISCAL DO CONTRATO: Maria Olivia Paulino Torres Portugal UBS SITIO MARIA JOANA FISCAL DO CONTRATO: Nathalia Pimentel Felintro UBS VILA CONDE FISCAL DO CONTRATO: Giselda Souza Batista Pereira UBS VILA LOPES FISCAL DO CONTRATO: Celia Barbosa Lima UBS SANTA TEREZA FISCAL DO CONTRATO: Aparecida Patrícia Pereira de Abreu Vieira UBS PARQUE AMÉRICA FISCAL DO CONTRATO: Odalia de Souza Cruz da Silva UPA FISCAL DO CONTRATO: Drielly Rodrigues Faustino Santos CAPS FISCAL DO CONTRATO: Paula Azevedo Lopes | K26: CONTRATAÇÃO DE EMPRESA ESPECIALIZADA PARA MANUTENÇÃO PREVENTIVA E CORRETIVA DE EQUIPAMENTOS ODONTOLÓGICOS E MÉDICO-HOSPITALARES BEM COMO A INSTALAÇÃO DE NOVOS EQUIPAMENTOS QUE SEJAM ADQUIRIDOS E INCORPORADOS A COBERTURA CONTRATUAL, NA REDE DE SAÚDE DE RIO GRANDE DA SERRA, PARA ATENDER A SECRETARIA MUNICIPAL DE SAÚDE | L26: 12 MESES | M26: 45533 | N26: 29/08/25 A 29/08/26 | O26: 324/24 | P26: 1670/24 | Q26: 2024000000224 | R26: 2024000000486 ADITIVO 1 2025000000077 | S26: PE - 13/24 | T26: 235500 | U26: 45898 | V26: 45931 | W26: PRORROGAÇÃO E ACRÉSCIMO DE 25%
A27: =C27-$A$1 -> 97 | B27: =IF(A27<60,"Vencendo","Em Vigência") -> Em Vigência | C27: 46264 | D27: 38/23 | E27: 2º Aditivo | F27: REDE SOL FUEL DISTRIBUIDORA S/A CNPJ - 02.913.444/0001-43 | G27: S. URBANOS | H27: Jefferson Crispim de Souza | I27: Michele Aparecida de Sousa Carneiro CPF: 457.917.218-38 | J27: Guilherme Leandro Bernardo CPF: 335.305.768-40 | K27: CONTRATAÇÃO DE EMPRESA PARA FORNECIMENTO PARCELADO DE COMBUSTÍVEIS DO TIPO GASOLINA COMUM E ÓLEO DIESEL BS10, COM MAIOR PERCENTUAL DE DESCONTO SOBRE O PREÇO MÉDIO MENSAL DIVULGADO PELA ANP (AGÊNCIA NACIONAL DO PETRÓLEO) PRATICADOS NO ESTADO DE SÃO PAULO, TENDO COMO REFERÊNCIA O PREÇO MÉDIO DA REGIÃO DO ABC OS MUNICÍPIOS DE RIBEIRÃO PIRES, MAUÁ E SANTO ANDRÉ PARA ABASTECIMENTO NO TANQUE DE COMBUSTÍVEL INSTALADO NA GARAGEM MUNICIPAL DA PREFEITURA MUNICIPAL DE RIO GRANDE DA SERRA | L27: 12 meses | N27: 30/08/25 a 30/08/26 | O27: 977/23 | P27: 1768/23 | Q27: 2023000000103 | R27: 2023000000358 1º TERMO ADITIVO 2024000000037 2º TERMO ADITIVO 2025000000086 | S27: PP 36/23 | T27: 277300 | U27: 45898 | V27: 45915 | W27: 1% DE DESCONTO NEGOCIAÇÃO
T28: 532400
T29: =SUM(T27:T28) -> 809700
A30: CONTRATOS COM VENCIMENTO: SETEMBRO 2026
A31: =C31-$A$1 -> 102 | B31: =IF(A31<60,"Vencendo","Em Vigência") -> Em Vigência | C31: 46269 | D31: 37/23 | E31: 1º Aditivo | F31: P&P COLIBRI – CONSULTORIA E SOLUÇÕES S/S LTDA CNPJ - 15.417.725/0001-57 | G31: COMUNICAÇÃO | H31: JULIANA | I31: Ualisson Henrique de Oliveira Monteiro | J31: Juciane da Penha Silva | K31: CONTRATAÇÃO DE EMPRESA PARA FORNECIMENTO DE SOFTWARE PARA ESTRUTURAÇÃO DE IMPRENSA OFICIAL DO MUNICÍPIO | L31: 12 MESES | N31: 04/09/24 A 04/09/25 | O31: 1549/23 | P31: 1893/23 | R31: 2023000000371 1º ADITIVO 2024000000040 | S31: CD 192/23 | T31: 7800 | U31: 45533 | V31: 45187
E32: 2 º Aditivo | H32: DANILO SILVEIRA DE LIMA CPF: 415.016.588-24 | I32: Douglas Ferreira Bombana CPF: 296.491.178-90 | J32: Jéssica Cristine Alves Pereira CPF: 385.599.468-45 | L32: 12 MESES | N32: 04/09/25 A 04/09/26 | T32: 7800 | U32: 45904 | V32: 45904
A33: =C33-$A$1 -> 109 | B33: =IF(A33<60,"Vencendo","Em Vigência") -> Em Vigência | C33: 46276 | D33: 32/25 | E33: Contrato | F33: RIOMEDICA SAÚDE E NUTRIÇÃO COMÉRCIO DE SUPLEMENTOS LTDA ME CNPJ/MF sob o nº 35.578.077/0001-28 | G33: SAÚDE | H33: FELIPE VIEIRA DE SÁ DOS SANTOS CPF sob o nº 361.930.868-38 | I33: Heloísa Pereira da Silva CPF: 434.113.338-12 | J33: Sara de Melo Silva Fernandes CPF: 448.006.058-81 | K33: AQUISIÇÃO DE SUPLEMENTO ALIMENTAR PARA ATENDIMENTO DE PACIENTE DA FARMÁCIA DE DEMANDA JUDICIAL DA SECRETARIA DE SAÚDE DE RIO GRANDE DA SERRA | L33: 12 meses | N33: 11/09/25 a 11/09/26 | O33: 1455/25 | P33: 1897/2025 | Q33: 2025000000187 | R33: 2025000000604 | S33: Dispensa nº 30/2025 | T33: 9360 | U33: 45909 | V33: 45911 | W33: VIGENCIA A PARTIR DA PUBLICAÇÃO
A34: =C34-$A$1 -> 109 | B34: =IF(A34<60,"Vencendo","Em Vigência") -> Em Vigência | C34: 46276 | D34: 36/25 | E34: Contrato | F34: FORTALEZA REAL COMERCIAL DE MATERIAIS E MANUTENÇÃO EM GERAL LTDA - ME CNPJ/MF sob o nº. 20.661.647/0001-71 | G34: SAÚDE | H34: FELIPE VIEIRA DE SÁ DOS SANTOS CPF sob o nº 361.930.868-38 | I34: Silvana Moraes Branco Conceição CPF: 140.431.098-30 | J34: Telma Moraes Pires CPF: 263.971.178-47 | K34: AQUISIÇÃO DE KITS ODONTOLÓGICOS – PROGRAMA SAÚDE NA ESCOLA | L34: 12 meses | N34: 11/09/25 a 11/09/26 | O34: 707/25 | P34: 2017/2025 | Q34: 2025000000189 | R34: 2025000000605 | S34: Dispensa nº 08/2025 | T34: 27400 | U34: 45909 | V34: 45911 | W34: VIGENCIA A PARTIR DA PUBLICAÇÃO
A35: =C35-$A$1 -> 110 | B35: =IF(A35<60,"Vencendo","Em Vigência") -> Em Vigência | C35: 46277 | D35: 01/23 | E35: 4º Aditivo | F35: VIAPRECISA TERRAPLENAGEM E PAVIMENTAÇÃO LTDA CNPJ - 31.133.672/0001-07 | G35: OBRAS | H35: WANDERLEI FELIPE DA SILVA JUNIOR CPF 179.165.208-50 | I35: LEILA ANDREASSI DE CASTRO CPF 235.681.298-92 | J35: SAMUEL PEREIRA MATOS SILVA CPF 382.138.398-46 | K35: CONTRATAÇÃO DE EMPRESA PARA EXECUÇÃO DE PAVIMENTAÇÃO, DRENAGEM E SINALIZAÇÃO VIÁRIA DAS RUAS: XAVANTES, PRESIDENTE PRUDENTE E COTIA – BAIRRO PARQUE AMÉRICA NO MUNICÍPIO DE RIO GRANDE DA SERRA | L35: 8 MESES | M35: 44970 | N35: 13/01/2026 À 12/09/2026 | O35: 1147/22 | P35: 309/23 | Q35: 2023000000012 | R35: 2023000000099 2º TERMO ADITIVO 2024000000056 3º TERMO ADITIVO 2025000000056 4º TERMO ADITIVO 2026000000019 | S35: CO 01/22 | T35: 712236.09 | U35: 45790 | V35: 45834 | W35: ORDEM DE INÍCIO 13/02/2023
A36: =C36-$A$1 -> 111 | B36: Em Vigência | C36: 46278 | D36: 31/25 | E36: 1º Aditivo | F36: MARIA DOS REMEDIOS DE SOUSA ALVES | G36: CIDADANIA | H36: Kátia Néris da Silva CPF 161.660.908-21 | I36: Fernanda Stachowski CPF 336.725.538-67 | J36: Rodrigo do Carmo Santos CPF 477.987.948-59 | K36: LOCAÇÃO DO IMÓVEL PARA INSTALAÇÃO DA CASA DE ACOLHIMENTO TEMPORÁRIA PARA PESSOAS EM SITUAÇÃO DE RUA | L36: 07 MESES | N36: 14/02/2026 À 13/09/2026 | O36: 357/2025 | P36: 1616/2025 | Q36: 2025000000183 | R36: 2025000000559 ADITIVO 1 2026000000012 | S36: INEX 15/2025 | T36: 28000 | U36: 46067 | V36: 46278
A37: =C37-$A$1 -> 123 | B37: =IF(A37<60,"Vencendo","Em Vigência") -> Em Vigência | C37: 46290 | D37: *** | E37: *** | F37: SINDICATO DOS SERVIDORES PÚBLICOS RIO GRANDE DA SERRA CNPJ: 53.721.247/0001-63 | G37: ADMINISTRAÇÃO | H37: MILTON DE SOUZA MARTINS CPF: 107.599.858-12 | K37: TERMO DE COOPERAÇÃO TÉCNICA - FORNECIMENTO E A ADMINISTRAÇÃO DO PLANO DE ASSISTÊNCIA MÉDICA - REPASSE AO SINDICATO REFERENTE AO CONVÊNIO MÉDICO - AUXILIO PATRONAL + AUXILIO PATRONAL FUNPREV | L37: 12 MESES | M37: *** | N37: 12/09/2025 A 11/09/2026 | O37: 1324/2023 | P37: 2015/2023 | Q37: NÃO SE APLICA | R37: NÃO SE APLICA | S37: **** | T37: 840000 | U37: 45912 | V37: 45932 | W37: CONVENIO COM SINDICATO
H38: ALEX SANDRO BARROSO ALVES | L38: 12 MESES | M38: *** | N38: 11/09/2024 À 11/09/2025 | T38: 840000 | U38: 45546 | V38: 45610 | W38: CONVENIO COM SINDICATO
H39: ALEXSANDRA SILVA AGUIAR | I39: IASMIN MARIA DA SILVA | J39: IASMIN MARIA DA SILVA | L39: 12 MESES | M39: *** | N39: 11/09/2023 A 11/09/2024 | T39: 800000 | U39: 45180 | V39: *** | W39: CONVENIO COM SINDICATO
A40: =C40-$A$1 -> 123 | B40: =IF(A40<60,"Vencendo","Em Vigência") -> Em Vigência | C40: 46290 | D40: 42/23 | E40: 3º Aditivo | F40: ANGELUS COMERCIAL E CONSULTORIA EM TECNOLOGIA EIRELI CNPJ - 31.260.520/0001-67 | G40: CIDADANIA | H40: Elza Dos Anjos Iwasaki CPF: 124.538.988-25 | I40: Fernanda Stachowski CPF: 336.725.538-67 | J40: Cibely Aparecida Miranda dos Santos CPF: 462.455.488-45 | K40: FORNECIMENTO DE GÊNEROS ALIMENTÍCIOS, COM ENTREGA FRACIONADA, VISANDO ATENDER ÀS NECESSIDADES DO SAICA – SERVIÇO DE ACOLHIMENTO INSTITUCIONAL PARA CRIANÇAS E ADOLESCENTES | L40: 12 MESES | N40: 25/09/25 À 25/09/26 | O40: 1104/23 | P40: 1937/23 | Q40: 2023000000112 | R40: ADITIVO 1 2024000000051 ADITIVO 2 2024000000058 ADITIVO 3 2025000000087 | S40: PP 39/23 | T40: 92896.16 | U40: 45925 | V40: 45944
A41: =C41-$A$1 -> 124 | B41: =IF(A41<60,"Vencendo","Em Vigência") -> Em Vigência | C41: 46291 | D41: 57/10 | E41: 8° ADITIVO | F41: VIAÇÃO TALISMÃ LTDA CNPJ - 04.150.152/0001-21 | G41: SEGURANÇA URBANA, TRANSITO E DEFESA CIVIL | H41: JOSÉ LUÍS MARTINS NAVARRO CPF: 041.652.548-27 | I41: MAURO MUNHOZ MARTINS FERNANDES CPF 343.796.018-02 | J41: Alexandre de Lima Campos CPF: 182.863.398-43 | K41: TARIFA ZERO - CONCESSÃO ONEROSA PARA EXPLORAÇÃO E EXECUÇÃO DOS SERVIÇOS DO TRANSPORTE PÚBLICO COLETIVO URBANO DE PASSAGEIROS DE RIO GRANDE DA SERRA | L41: 06 MESES | N41: 26/09/2024 A 26/03/2025 26/03/2025 A 26/09/2025 26/09/2025 A 25/03/2026 26/03/2026 A 25/09/2026 | O41: 1402/2005 1844/2022 1791/2024 | P41: 2189/2022 | Q41: 2022000000019 | R41: 2022000000104 | S41: CO 03/10 | T41: 510000 | U41: 46107 | V41: 06/04/2026 E 07/04/2026 | W41: LEI MUNICIPAL N° 1.856 DE 28/06/2010 E DECRETO MUNICIPAL N° 1.934 DE 06/07/2010 - Por igual período - Repasse ao município de 2,5% = PRAZO DE 15 ANOS
A42: CONTRATOS COM VENCIMENTO: OUTUBRO 2026
A43: =C43-$A$1 -> 134 | B43: =IF(A43<60,"Vencendo","Em Vigência") -> Em Vigência | C43: 46301 | D43: 21/22 | E43: 3º Aditivo | F43: CAIO CESAR SIQUEIRA XAVIER CPF - 385.859.888.78 | G43: CIDADANIA | H43: Elza dos Anjos Iwasaki | I43: Fernanda Stachowski | J43: Cibely Aparecida Miranda dos Santos | K43: LOCAÇÃO DE IMÓVEL LOCALIZADO NA RUA AURÉLIO FIGUEIREDO, Nº 195 VILA FIGUEIREDO, RIO GRANDE DA SERRA/SP, PARA INSTALAÇÃO DO SAICA – SERVIÇO DE ACOLHIMENTO INSTITUCIONAL PARA CRIANÇAS E ADOLESCENTES MUNICIPAL DA SECRETARIA DE CIDADANIA E INCLUSÃO SOCIAL | L43: 12 meses | N43: 06/10/25 A 06/10/26 | O43: 1783/22 | P43: 2074/22 | Q43: 2022000000102 | R43: 2024000000065 Aditivo 3 2025000000089 | S43: DP 25/22 | T43: 93180.36 | U43: 45936 | V43: 45959
A44: =C44-$A$1 -> 136 | B44: =IF(A44<60,"Vencendo","Em Vigência") -> Em Vigência | C44: 46303 | D44: PD251594 | E44: Contrato | F44: COMPANHIA DE PROCESSAMENTO DE DADOS DO ESTADO DE SÃO PAULO - PRODESP - CNPJ - 62.577.929/0001-35 | G44: SEGURANÇA | H44: Elias de Lima Meneses | I44: Guilherme Bernardo de Azevedo | J44: Alexandre de Lima Campos | K44: CONTRATAÇÃO DA PRODESP PARA PRESTAÇÃO DE SERVIÇO DE PROCESSAMENTO DE MULTAS E BANCO DE DADOS DO DETRAN | L44: 12 meses | N44: 09/10/25 A 08/10/26 | O44: 1840/2025 | P44: 2289/25 | Q44: 2025000000204 | R44: 2025000000728 | S44: DP 39/25 | T44: 45108 | U44: 45950 | V44: 45973
A45: =C45-$A$1 -> 136 | B45: =IF(A45<60,"Vencendo","Em Vigência") -> Em Vigência | C45: 46303 | D45: 20/21 | E45: Contrato | F45: SCHIMBERGUI COX ADVOGADOS ASSOCIADOS CNPJ - 24.632.410/0001-13 | G45: FINANÇAS | K45: CONTRATAÇÃO DE ESCRITÓRIO ADVOCATÍCIO, PARA PRESTAÇÃO DE SERVIÇOS ESPECIALIZADOS A FIM DE PROPICIAR EXTRAJUDICIALMENTE E JUDICIALMENTE OS INTERESSES DESTA PREFEITURA MUNICIPAL, EM FACE DA AGÊNCIA NACIONAL DO PETRÓLEO, GÁS NATURAL E BIOCOMBUSTÍVEIS – ANP, VISANDO A CORREÇÃO DOS CRITÉRIOS LEGAIS APLICADOS NA DISTRIBUIÇÃO DOS ROYALTIES HAJA VISTA QUE NÃO ESTÃO SENDO CONSIDERADAS EM SUA INTEGRIDADE PARA EFEITO DE PAGAMENTO OS EQUIPAMENTOS EM FUNCIONAMENTO LIGADOS AO PROCESSO DE ESCOAMENTO DO PETRÓLEO PRODUZIDO NO ESTADO DE SÃO PAULO | L45: renovado automaticamente até o limite de 60 meses | N45: 08/10/21 a 08/10/26 | O45: 1023/21 | P45: 2032/21 | Q45: *** | R45: *** | S45: Inexigibilidade nº 01/2021 | T45: 1800000 | U45: 44477 | V45: 45252
A46: =C46-$A$1 -> 141 | B46: =IF(A46<60,"Vencendo","Em Vigência") -> Em Vigência | C46: 46308 | D46: 43/2025 | E46: Contrato | F46: SKY SERVIÇOS DE BANDA LARGA LTDA CNPJ: 72.820.822/0001-20 | G46: CIDADANIA | H46: ELZA DOS ANJOS IWAZAKI CPF: 124.538.988-25 | I46: Cibely Aparecida Miranda dos Santos | K46: PROC 953/2025 - CONTRATAÇÃO DE SERVIÇO DE TV DIGITAL POR ASSINATURA, SENDO UM PACOTE INCLUINDO 03 (TRÊS) PONTOS DE ACESSO COM CONTROLE REMOTO E ACESSO A CANAIS BÁSICOS E INFANTIS, PARA ATENDER ÀS NECESSIDADES DO SERVIÇO DE ACOLHIMENTO INSTITUCIONAL PARA CRIANÇAS E ADOLESCENTES – SAICA. | L46: 12 MESES | N46: 14/10/25 A 13/10/26 | O46: 953/25 | P46: - | Q46: NÃO SE APLICA | R46: NÃO SE APLICA | S46: DISP 38/25 | T46: 2799.24 | U46: 45944
A47: =C47-$A$1 -> 144 | B47: =IF(A47<60,"Vencendo","Em Vigência") -> Em Vigência | C47: 46311 | D47: 40/25 | E47: Contrato | F47: MAQ POTÊNCIA LTDA CNPJ/MF sob o nº 18.488.016/0001-50 | G47: SAÚDE | H47: FELIPE VIEIRA DE SÁ DOS SANTOS CPF sob o nº 361.930.868-38 | I47: Alessandro dos Santos Possidônio Silva CPF: 192.252.648-79 | J47: Telma Moraes Pires CPF: 263.971.178-47 | K47: CONTRATAÇÃO DE EMPRESA ESPECIALIZADA PARA PRESTAÇÃO DE SERVIÇOS DE MANUTENÇÃO PREVENTIVA E CORRETIVA PARA O GRUPO DE GERADORES DE ENERGIA DA UNIDADE DE PRONTO ATENDIMENTO (UPA) DA SECRETARIA MUNICIPAL DE SAÚDE DE RIO GRANDE DA SERRA | L47: 12 MESES A PARTIR DA PUBLICAÇÃO | N47: 16/10/25 a 16/10/26 | O47: 1551/25 | P47: 2075/25 | Q47: 2025000000194 | R47: AJUSTE 2025000000701 | S47: DISP 33/25 | T47: 5400 | U47: 45940 | V47: 45946
A48: =C48-$A$1 -> 150 | B48: =IF(A48<60,"Vencendo","Em Vigência") -> Em Vigência | C48: 46317 | D48: 41/25 | E48: Contrato | F48: TECBLIN LTDA CNPJ/MF sob o nº 48.575.558/0001-21 | G48: SEGURANÇA | H48: Elias de Lima Meneses CPF: 304.013.528-70 | I48: Alexandre de Lima Campos CPF: 182.863.398-43 | J48: Fabiano Gomes Duarte CPF: 365.558.428-81 | K48: AQUISIÇÃO DE COLETE DE PROTEÇÃO BALISTICA E CAPA MODULAR PARA A GUARDA CIVIL MUNICIPAL DE RIO GRANDE DA SERRA | L48: 12 MESES A PARTIR DA PUBLICAÇÃO | N48: 22/10/25 a 22/10/26 | O48: 25/25 | P48: 2157/2025 | Q48: 2025000000197 | R48: AJUSTE 2025000000704 | S48: PE Nº 21/2025 | T48: 48000 | U48: 45947 | V48: 45952
A49: =C49-$A$1 -> 151 | B49: =IF(A49<60,"Vencendo","Em Vigência") -> Em Vigência | C49: 46318 | D49: 42/250 | E49: Contrato | F49: COESMA - COMÉRCIO E SERVIÇOS PARA O TRÂNSITO E MEIO AMBIENTE LTDA CNPJ/MF sob o nº 13.815.614/0001-09 | G49: SEGURANÇA | H49: ELIAS DE LIMA MENESES CPF: 304.013.528-70 | I49: Mauro Munhoz Martins Fernandes CPF: 343.796.018-03 | J49: Alexandre de Lima Campos CPF: 182.863.398-43 | K49: CONTRATAÇÃO DE SERVIÇOS MENSAL DE SISTEMA PARA PROCESSAMENTO DE MULTAS DE TRÂNSITO E TALONÁRIO ELETRÔNICO COM IMPRESSORA TÉRMICA PORTÁTIL E INSUMOS PARA O MUNICÍPIO DE RIO GRANDE DA SERRA | L49: 12 MESES | N49: 23/10/2025 A 23/10/2026 | O49: 1044/2025 | P49: 2148/2025 | Q49: LICTAÇÃO 2025000000199 | R49: AJUSTE 2025000000717 | S49: PE 26/2025 | T49: 63720 | U49: 45947 | V49: 45953
A50: CONTRATOS COM VENCIMENTO: NOVEMBRO DE 2026
A51: =C51-$A$1 -> 171 | B51: Em Vigência | C51: 46338 | D51: 14/2026 | E51: Contrato | F51: KONICA MINOLTA HEALTHCARE DO BRASIL INDUSTRIA DE EQUIPAMENTOS MEDICOS LTDA CNPJ/MF SOB O Nº 71.256.283/0001-85 | G51: SAÚDE | H51: FELIPE VIEIRA DE SÁ DOS SANTOS | I51: Alex Sandro Barroso Alves CPF: 303.636.638-51 | J51: Telma Moraes Pires CPF: 263.971.178-47 | K51: MANUTENÇÃO CORRETIVA PARA MAMÓGRAFO DELICATA DR Km T0025 | L51: 06 MESES | N51: 13/05/2026 A 12/11/2026 | O51: 482/2026 | P51: 835/2026 | Q51: 2026000000139 | R51: AJUSTE 2026000000227 | S51: INEX 04/2026 | T51: R$ 36.967,20 | U51: 46155 | V51: 46157
A52: =C52-$A$1 -> 175 | B52: =IF(A52<60,"Vencendo","Em Vigência") -> Em Vigência | C52: 46342 | D52: 22/21 | E52: 4º Aditivo | F52: GLOBALNET SERVIÇOS E INFORMÁTICA LTDA (INTERNET) CNPJ 19.421.083/0001-10 | G52: ADMINISTRAÇÃO | H52: MILTON | I52: Elias Rodrigues do Prado - CPF: | J52: Arthur Galdino Marques - CPF: 535.998.138-50 | K52: CONTRATAÇÃO DE EMPRESA ESPECIALIZADA PARA PRESTAÇÃO DE SERVIÇOS DE ACESSO À INTERNET ATRAVÉS DE LINK DE DADOS COM IP DEDICADO COM VELOCIDADES FORNECIDA VIA FIBRA ÓPTICA FIM A FIM, COM REDUNDÂNCIA NA INFRAESTRUTURA (COM DOIS CAMINHOS DISTINTOS ENTRE PROVEDOR E O LOCAL DE INSTALAÇÃO) INCORPORANDO A REDE DA PREFEITURA MUNICIPAL DE RIO GRANDE DA SERRA À UMA REDE DE DADOS ATRAVÉS DE LINKS DE FIBRA ÓPTICA ATÉ A CENTRAL DA EMPRESA RESPONSÁVEL PELO PROVIMENTO DA INTERNET, EM CONFORMIDADE COM AS CONDIÇÕES E ESPECIFICAÇÕES ESTABELECIDAS NESTE EDITAL E EM TODOS OS SEUS ANEXOS | L52: 12 MESES | M52: CLAUSULA RESOLUTIVA | N52: 16/11/2025 A 16/11/2026 | O52: 252/21 | P52: 1943/21 | Q52: LICITAÇÃO 202200000048 | R52: AJUSTE 2022000000410 ADITIVO 2024000000005 ADITIVO 3 202400000041 ADITIVO 4 2026000000008 | S52: PP 14/2021 | T52: 571480.2 | U52: 45977 | V52: 46052
A53: =C53-$A$1 -> 175 | B53: =IF(A53<60,"Vencendo","Em Vigência") -> Em Vigência | C53: 46342 | D53: 24/21 | E53: 5º Aditivo | F53: GLOBALNET SERVIÇOS E INFORMÁTICA LTDA (TELEFONIA) CNPJ 19.421.083/0001-10 | G53: ADMINISTRAÇÃO | H53: MILTON | I53: Elias Rodrigues do Prado - CPF: | J53: Arthur Galdino Marques - CPF: 535.998.138-50 | K53: CONTRATAÇÃO DE EMPRESA ESPECIALIZADA PARA PRESTAÇÃO DE SERVIÇOS DE SOLUÇÃO CORPORATIVA DE TELEFONIA, CONTEMPLANDO FORNECIMENTO DE PABX IP, APARELHOS TELEFÔNICOS IP, SOFTFONES, SERVIÇO DE INSTALAÇÃO, GARANTIA ON-SITE DE 12 MESES, SERVIÇOS DE TREINAMENTO, SOFTWARE DE TARIFAÇÃO E CABOS DE REDE UTP, PARA ATENDER ÀS NECESSIDADES DA PREFEITURA MUNICIPAL DE RIO GRANDE DA SERRA | L53: 12 MESES | M53: CLAUSULA RESOLUTIVA | N53: 16/11/2025 A 16/11/2026 | O53: 252/21 | P53: 1945/21 | Q53: LICITAÇÃO 202200000048 | R53: AJUSTE 2022000000411 ADITIVO 2024000000004 ADITIVO 4 202400000042 ADITIVO 5 2026000000009 | S53: PP 14/2021 | T53: 136203.96 | U53: 45977 | V53: 46052
A54: =C54-$A$1 -> 186 | B54: =IF(A54<60,"Vencendo","Em Vigência") -> Em Vigência | C54: 46353 | D54: 47/25 | E54: contrato | F54: VANDERLEI JESUS DOS SANTOS CPF/MF sob nº 645.312.608-72 | G54: CIDADANIA | H54: ELZA DOS ANJOS IWASAKI CPF 124.538.988-25 | I54: Fernanda Stachowski CPF: 336.725.538-67 | J54: Maria Aparecida da Costa CPF: 157.803.918-58 | K54: LOCAÇÃO DE IMÓVEL DE INSTALAÇÃO CRAS – CENTRO DE REFÊRENCIA DE ASSISTÊNCIA SOCIAL | L54: 12 MESES | N54: 27/11/2025 A 27/11/2026 | O54: 497/2025 | P54: 2211/2025 | Q54: 2025000000209 | R54: AJUSTE 2025000000784 | S54: INEX 19/2025 | T54: 96000 | U54: 45987 | V54: 45988
A55: CONTRATOS COM VENCIMENTO: DEZEMBRO DE 2026
A56: =C56-$A$1 -> 199 | B56: =IF(A56<60,"Vencendo","Em Vigência") -> Em Vigência | C56: 46366 | D56: 49/24 | E56: 1º Aditivo | F56: 3 ALT´S X EDUCAÇÃO LTDA | G56: EDUCAÇÃO E CULTURA | H56: Vinícius Brum da Silva CPF: 406.779.358 89 | I56: Mônica Mara Rodrigues CPF: 257.494.078 45 | J56: Marisa Cristina Rodrigues CPF: 257.489.958 08 | K56: CONTRATAÇÃO DE EMPRESA PARA AQUISIÇÃO DE SOLUÇÃO PEDAGÓGICA E TECNOLÓGICA PARA ENSINO DA LÍNGUA INGLESA, POR MEIO DE UM PROJETO QUE APRESENTA UMA ESTRUTURA BASEADA NOS NOVOS CONCEITOS EDUCACIONAIS QUE FACILITEM O ENSINO-APRENDIZADO, CONTENDO: MATERIAL IMPRESSO PARA ALUNO E PARA O PROFESSOR; MATERIAL DIGITAL E ASSESSORIA PEDAGÓGICA E TECNOLÓGICA COM ACESSO A PLATAFORMA | L56: 12 MESES | N56: 11/12/25 a 10/12/26 | O56: 347/24 | P56: execução no processo administrativo | Q56: 2024000000282 | R56: AJUSTE 2024000000669 ADITIVO 2026000000032 | S56: PE 24/24 | T56: R$ 291.994,56 | U56: 45637 | V56: 46002
A57: =C57-$A$1 -> 205 | B57: =IF(A57<60,"Vencendo","Em Vigência") -> Em Vigência | C57: 46372 | D57: 58/24 | E57: 1º aditivo | F57: CAIXA ECONOMICA FEDERAL | G57: FINANÇAS | H57: RICARDO ABÍLIO ROSSI CARDOSO CPF: 246.424.778-29 | I57: LAURA CRISTINA PEREIRA CPF 066.005.058-77 | J57: MARLENE NUNES DOS SANTOS OLIVEIRA CPF 080.198.068-22 | K57: PROCESSO ADMINISTRATIVO Nº 1246/2024 - CONTRATAÇÃO DE INSTITUIÇÕES FINANCEIRAS E INSTITUIÇÕES DE PAGAMENTOS, PARA PRESTAÇÃO DE SERVIÇOS BANCÁRIOS DE ARRECADAÇÃO DE TRIBUTOS MUNICIPAIS E DEMAIS RECEITAS DE TITULARIDADE DA PREFEITURA DO MUNICÍPIO DE RIO GRANDE DA SERRA. | L57: 12 MESES | N57: 16/12/2024 A 16/12/2025 17/12/2025 A 16/12/2026 | O57: 1246/2024 | P57: 2372/2024 | Q57: 2025000000117 | R57: 2025000000007 ADITIVO 2026000000003 | S57: INEX Nº 17/24 | T57: 66034 | U57: 46372 | V57: 46010 | W57: Chamamento Público 01/2024 - Credenciamento
A58: =C58-$A$1 -> 205 | B58: =IF(A58<60,"Vencendo","Em Vigência") -> Em Vigência | C58: 46372 | D58: 57/24 | E58: 1º aditivo | F58: BANCO SANTANDER S/A | G58: FINANÇAS | H58: RICARDO ABÍLIO ROSSI CARDOSO CPF: 246.424.778-29 | I58: LAURA CRISTINA PEREIRA CPF 066.005.058-77 | J58: MARLENE NUNES DOS SANTOS OLIVEIRA CPF 080.198.068-22 | K58: PROCESSO ADMINISTRATIVO Nº 1246/2024 - CONTRATAÇÃO DE INSTITUIÇÕES FINANCEIRAS E INSTITUIÇÕES DE PAGAMENTOS, PARA PRESTAÇÃO DE SERVIÇOS BANCÁRIOS DE ARRECADAÇÃO DE TRIBUTOS MUNICIPAIS E DEMAIS RECEITAS DE TITULARIDADE DA PREFEITURA DO MUNICÍPIO DE RIO GRANDE DA SERRA. | L58: 12 MESES | N58: 16/12/2024 A 16/12/2025 17/12/2025 a 16/12/2026 | O58: 1246/2024 | P58: 2371/2024 | Q58: 2025000000117 | R58: 2025000000006 ADITIVO 2026000000002 | S58: INEX Nº 17/24 | T58: 66033.95 | U58: 46007 | V58: 46010 | W58: Chamamento Público 01/2024 - Credenciamento
A59: =C59-$A$1 -> 205 | B59: =IF(A59<60,"Vencendo","Em Vigência") -> Em Vigência | C59: 46372 | D59: 55/24 | E59: 1º aditivo | F59: BANCO BRADESCO S.A | G59: FINANÇAS | H59: RICARDO ABÍLIO ROSSI CARDOSO CPF: 246.424.778-29 | I59: LAURA CRISTINA PEREIRA CPF 066.005.058-77 | J59: MARLENE NUNES DOS SANTOS OLIVEIRA CPF 080.198.068-22 | K59: PROCESSO ADMINISTRATIVO Nº 1246/2024 - CONTRATAÇÃO DE INSTITUIÇÕES FINANCEIRAS E INSTITUIÇÕES DE PAGAMENTOS, PARA PRESTAÇÃO DE SERVIÇOS BANCÁRIOS DE ARRECADAÇÃO DE TRIBUTOS MUNICIPAIS E DEMAIS RECEITAS DE TITULARIDADE DA PREFEITURA DO MUNICÍPIO DE RIO GRANDE DA SERRA. | L59: 12 MESES | N59: 16/12/2024 A 16/12/2025 17/12/2025 a 16/12/2025 | O59: 1246/2024 | P59: 2300/2024 | Q59: 2025000000117 | R59: AJUSTE 2025000000005 ADITIVO 2026000000001 | S59: INEX Nº 17/24 | T59: 66018.4 | U59: 46003 | V59: 46007 | W59: Chamamento Público 01/2024 - Credenciamento
A60: =C60-$A$1 -> 208 | B60: =IF(A60<60,"Vencendo","Em Vigência") -> Em Vigência | C60: 46375 | D60: 59/24 | E60: 1º aditivo | F60: ITAU UNIBANCO S/A | G60: FINANÇAS | H60: RICARDO ABÍLIO ROSSI CARDOSO CPF: 246.424.778-29 | I60: LAURA CRISTINA PEREIRA CPF 066.005.058-77 | J60: MARLENE NUNES DOS SANTOS OLIVEIRA CPF 080.198.068-22 | K60: PROCESSO ADMINISTRATIVO Nº 1246/2024 - CONTRATAÇÃO DE INSTITUIÇÕES FINANCEIRAS E INSTITUIÇÕES DE PAGAMENTOS, PARA PRESTAÇÃO DE SERVIÇOS BANCÁRIOS DE ARRECADAÇÃO DE TRIBUTOS MUNICIPAIS E DEMAIS RECEITAS DE TITULARIDADE DA PREFEITURA DO MUNICÍPIO DE RIO GRANDE DA SERRA. | L60: 12 MESES | N60: 19/12/2024 A 19/12/2025 20/12/2025 a19/12/2026 | O60: 1246/2024 | P60: 2373/24 | Q60: 2025000000117 | R60: 2025000000004 ADITIVO 2026000000001 | S60: INEX Nº 17/24 | T60: 66019.5 | U60: 46003 | V60: 46007 | W60: Chamamento Público 01/2024 - Credenciamento
A61: =C61-$A$1 -> 210 | B61: =IF(A61<60,"Vencendo","Em Vigência") -> Em Vigência | C61: 46377 | D61: 22/22 | E61: 3º Aditivo | F61: MARCIA APARECIDA ALBANO CPF - 560.567.298-34 CONCHETA ALBANO SIQUEIRA CPF - 080.178.428-05 | G61: CIDADANIA | H61: ELZA DOS ANJOS IWASAKI 124.538.988-25 | I61: Fernanda Stachowski | J61: Maria Aparecida da Costa | K61: LOCAÇÃO DE IMÓVEL SITO À RUA PREFEITO CARLOS JOSÉ CARLSON, 347 - VL. ALBANO, ONDE ESTÁ INSTALADO O CONSELHO TUTELAR | L61: 12 MESES | N61: 21/12/25 A 21/12/26 | O61: 1916/22 | P61: 17/23 | Q61: LICITAÇÃO 2023000000002 | R61: AJUSTE 2023000000006 1º ADITIVO 2024000000001 2º ADITIVO 2024000000074 3º ADITIVO 2026000000005 | S61: DP 27/22 | T61: 45631.32 | U61: 46010 | V61: 45664
A62: CONTRATOS COM VENCIMENTO: JANEIRO 2027
A63: =C63-$A$1 -> 225 | B63: =IF(A63<60,"Vencendo","Em Vigência") -> Em Vigência | C63: 46392 | D63: 01/25 | E63: COMODATO | F63: FÁCIL SOLUÇÕES TECNOLÓGICAS EM INFORMÁTICA S/A | G63: ADMINISTRAÇÃO | H63: MILTON DE SOUZA MARTINS | I63: - | J63: - | K63: licenciamento de uso do programa de computador CONSIGFÁCIL (“SISTEMA”) – Sistema Eletrônico, via internet, de reserva de margem e controle de consignações, com desconto em folha de pagamento, e outras avenças, de propriedade do COMODANTE para uso no âmbito da PREFEITURA MUNICIPAL DE RIO GRANDE DA SERRA/SP | L63: 12 MESES | N63: 705/01/26 A 05/01/27 | O63: 2387/25 | S63: INEX 25/2025 | U63: 46014 | V63: 46027
A64: =C64-$A$1 -> 226 | B64: =IF(A64<60,"Vencendo","Em Vigência") -> Em Vigência | C64: 46393 | D64: 46/25 | E64: CONTRATO | F64: FABIO LEMOS NAKAMURA | G64: CIDADANIA | H64: Elza dos Anjos Iwasaki CPF: 124.538.988-25 | I64: Fernanda Stachowski | J64: Maria Aparecida da Costa | K64: CONTRATAÇÃO EMERGENCIAL DE VAGA EM INSTITUIÇÃO DE LONGA PERMANÊNCIA PARA IDOSOS (ILPI) GRAU I, EM ATENDIMENTO AO SR. JOSÉ DA SILVA, CONFORME MEMORANDO Nº 138/2025 ENCAMINHADO PELO CREAS E DETERMINAÇÃO DO MINISTÉRIO PÚBLICO DO ESTADO DE SÃO PAULO, VISANDO GARANTIR ACOLHIMENTO INSTITUCIONAL E CUIDADOS INTEGRAIS | L64: 12 MESES | N64: 06/01/26 À 06/01/2027 | O64: 2042/25 | P64: 20/2026 | Q64: 2025000000206 | R64: 2026000000001 | S64: DE 40/25 | T64: 33600 | U64: 46014 | V64: 46028 | W64: VIGENCIA DA PUBLICAÇÃO
A65: =C65-$A$1 -> 237 | B65: =IF(A65<60,"Vencendo","Em Vigência") -> Em Vigência | C65: 46404 | D65: 9912593829/23 | E65: 4º Aditivo | F65: EMPRESA BRASILEIRA DE CORREIOS E TELÉGRAFOS CNPJ: 34.028.316/0031-29 | G65: ADMINISTRAÇÃO | H65: MILTON DE SOUZA MARTINS CPF: 107.599.858-12 | I65: Israel da Silva Junior | J65: José Inácio (Zezinho) | K65: CONTRATAÇÃO DE EMPRESA PARA PRESTAÇÃO DE SERVIÇOS POSTAIS, INCLUINDO TELEGRAMA, CARTA COMERCIAL, MALA DIRETA BÁSICA E ENCOMENDAS NACIONAIS, COM SERVIÇO DE REMESSA EXPRESSA DE DOCUMENTOS PARA ATENDER OS DEPARTAMENTOS ADMINISTRATIVOS PELA PREFEITURA MUNICIPAL DE RIO GRANDE DA SERRA. | L65: 12 MESES | N65: 17/01/26 A 17/01/27 | O65: 2404/2022 | P65: 288/2023 | Q65: LICITAÇÃO 2023000000010 | R65: AJUSTE 2023000000092 3 ADITIVO 2025000000015 4 ADITIVO 2026000000007 | S65: DP 33/22 | T65: 100000 | U65: 45666 | V65: 46049 | W65: CONTATO 3003-0800
A66: CONTRATOS COM VENCIMENTO: FEVEREIRO 2027
A67: =C67-$A$1 -> 252 | B67: =IF(A67<60,"Vencendo","Em Vigência") -> Em Vigência | C67: 46419 | D67: 04/24 | E67: 2º Aditivo | F67: CONSÓRCIO RIO GRANDE DA SERRA PERALTA - COMPOSTA PELA PERALTA AMBIENTAL IMP. E EXP. LTDA CNPJ: 05.960.053/0001-78 LARA CENTRAL DE TRATAMENTO DE RESIDUOS LTDA CNPJ: 57.543.001/0001-08 | G67: SERVIÇOS URBANOS | H67: JEFFERSON CRISPIM DE SOUZA - CPF: 362.010.008-01 | I67: DANIEL SOARES DA SILVA - CPF: 232.046.348-84 | J67: GUILHERME LEANDRO BERNARDO - CPF: 335.305.768-40 | K67: CONTRATAÇÃO DE EMPRESA ESPECIALIZADA EM SERVIÇOS DE COLETA E TRANSPORTE DE RESÍDUOS DOMICILIARES, COMERCIAIS E FEIRAS LIVRES; LIMPEZA DE FEIRAS LIVRES; DISPOSIÇÃO FINAL DE RESÍDUOS SÓLIDOS CLASSE II A DOMICILIARES, COMERCIAIS, REJEITOS/INSERVIVEIS E FEIRA LIVRES EM ATERRO SANITÁRIO DEVIDAMENTE LICENCIADO, INCLUINDO TAMBÉM SERVIÇOS DE COLETA, TRANSPORTE E TRATAMENTO DE RESÍDUOS SÓLIDOS DOS SERVIÇOS DE SAÚDE | L67: 12 MESES | M67: 45324 | N67: 02/02/2026 A 01/02/2027 | O67: 2442/2022 | P67: 479/2024 | Q67: 2024000000127 | R67: AJUSTE 2024000000008 ADITIVO 2025000000020 ADITIVO 2026000000013 | S67: CP 15/2023 | T67: 5728225.8 | U67: 46055 | V67: 19/02/2025 06/03/2026
D68: 05/24 | E68: 3º Aditivo | F68: LARA CENTRAL DE TRATAMENTO DE RESIDUOS LTDA CNPJ: 57.543.001/0001-08 | P68: 480/2024 | Q68: 2024000000127 | R68: AJUSTE 2024000000009 ADITIVO 2025000000021 ADITIVO 2026000000014 ADITIVO 2026000000025 | T68: 264091.68 | U68: 46097 | V68: 19/02/2025 06/03/2026 18/03/2026 | W68: ADITIVO 3 REFERE-SE A DIFERENÇA DE VALOR AO ADITIVO 2º
A69: =C69-$A$1 -> 252 | B69: =IF(A69<60,"Vencendo","Em Vigência") -> Em Vigência | C69: 46419 | D69: 06/24 | E69: 2º Aditivo | F69: QUALI INOV SERVIÇOS EMPRESARIAIS LTDA CNPJ - 50.999.258/0001-11 | G69: SAÚDE | H69: Felipe Vieira Sa dos Santos | I69: Gerlice Brasil da Silva CPF: 270.446.548-78 | J69: Aline Lima da Silva Toledo CPF: 442.965.068-38 | K69: CONTRATAÇÃO DE EMPRESA ESPECIALIZADA PARA PRESTAÇÃO DE SERVIÇOS DE LIMPEZA TÉCNICA E CONSERVAÇÃO PREDIAL DE AMBIENTES ASSISTENCIAIS E ADMINISTRATIVOS, ALÉM DE ÁREAS EXTERNAS, INCLUINDO O FORNECIMENTO DE MÃO DE OBRA, MATERIAIS DE HIGIENE E LIMPEZA, UTENSÍLIOS, EQUIPAMENTOS E DEMAIS INSUMOS NECESSÁRIOS EM UNIDADES DE SAÚDE NO MUNICÍPIO DE RIO GRANDE DA SERRA | L69: 12 MESES | M69: 45324 | N69: 02/02/2025 a 02/02/2026 02/02/2026 a 01/02/2027 | O69: 268/2023 | P69: 530/2024 | Q69: 2024000000123 | R69: 2024000000144 ADITIVO 2025000000014 ADITIVO 2026000000011 | S69: PP 53/2023 | T69: 3.153.355,44 3.276.265,08 | U69: 31/01/2025 02/02/2026 | V69: 25/02/2025 05/05/2026
A70: =C70-$A$1 -> 257 | B70: =IF(A70<60,"Vencendo","Em Vigência") -> Em Vigência | C70: 46424 | D70: 01/26 | E70: CONTRATO | F70: BONIZZONI & BONIZZONI LTDA CNPJ sob nº 03.345.887/0001-48 | G70: SECRETARIA DE EDUCAÇÃO, INOVAÇÃO E CULTURA | H70: VINÍCIUS BRUM DA SILVA CPF: 406.779.358-89 | I70: Talita Kumy Goes Silva CPF: 056.833.884-73 | J70: Viviane Aparecida dos Santos Almeida CPF: 285.196.758-40 | K70: CONTRATAÇÃO DE EMPRESA ESPECIALIZADA PARA A EXECUÇÃO CONTÍNUA DOS SERVIÇOS DE PREPARO E DISTRIBUIÇÃO DE REFEIÇÕES DESTINADAS À ALIMENTAÇÃO ESCOLAR DOS ALUNOS REGULARMENTE MATRICULADOS NA REDE PÚBLICA DE ENSINO DO MUNICÍPIO DE RIO GRANDE DA SERRA/SP | L70: 12MESES | N70: 06/02/26 A 06/02/2027 | O70: 1434/25 | P70: 252/26 | Q70: 2026000000115 | R70: 2026000000059 | S70: PE 43/25 | T70: 5800546 | U70: 46059 | V70: 46078
A71: =C71-$A$1 -> 258 | B71: =IF(A71<60,"Vencendo","Em Vigência") -> Em Vigência | C71: 46425 | D71: 31/23 | E71: 1º Aditivo | F71: VIAPRECISA TERRAPLANAGEM E PAVIMENTAÇÃO LTDA CNPJ - 31.133.672/0001-07 | G71: OBRAS | H71: Leandro Dias Florencio | I71: Leila Andreassi de Castro | J71: Leandro Dias Florencio | K71: CONTRATAÇÃO DE EMPRESA PARA EXECUÇÃO DE PAVIMENTAÇÃO, DRENAGEM E SINALIZAÇÃO VIÁRIA NAS RUAS AMPARO E BOTUCATU - PARQUE AMÉRICA, ESTRADA DO CARACU – CHÁCARA SÃO PAULO, RUAS DAS AVENCAS E DAS ORQUÍDEAS – JARDIM ESPERANÇA NO MUNICÍPIO DE RIO GRANDE DA SERRA | L71: 630 DIAS | M71: 45163 | N71: 16/05/25 A 07/02/2027 | O71: 1149/22 | P71: 1551/23 | Q71: 2023000000336 | R71: 2023000000092 ADITIVO 2025000000054 | S71: CO 01/23 | T71: 2684674.9 | U71: 45793 | V71: 45834
A72: =C72-$A$1 -> 260 | B72: =IF(A72<60,"Vencendo","Em Vigência") -> Em Vigência | C72: 46427 | D72: 46/23 | E72: Contrato | F72: ENEL - ELETROPAULO METROPOLITANA ELETRICIDADE DE SP S.A. CNPJ: 61.695.227/0001-93 | G72: OBRAS | H72: WANDERLEI FELIPE DA SILVA JUNIOR | I72: - | J72: - | K72: CONVÊNIO DE ARRECADAÇÃO DA CONTRIBUIÇÃO DE ILUMINAÇÃO PÚBLICA – CIP, INSTITUÍDA PELA LEI MUNICIPAL N° 1.464 | L72: INDETERMINADO | N72: 09/02/26 A 09/02/27 | O72: 1565/21 | P72: 827/24 | Q72: 2024000000175 | R72: 2024000000235 | S72: INEX N° 1/23 | U72: 45331 | V72: 45411 | W72: RENOVAÇÃO AUTOMÁTICA
A73: =C73-$A$1 -> 271 | B73: =IF(A73<60,"Vencendo","Em Vigência") -> Em Vigência | C73: 46438 | D73: 02/25 | E73: 1º Aditivo | F73: PHABRICA DE PRODUÇÕES SERVIÇOS DE PROPAGANDA E PUBLICIDADE LTDA EPP CNPJ - 00.662.315/0001-02 | G73: ADMINISTRAÇÃO | H73: MILTON DE SOUZA MARTINS CPF: 107.599.858-12 | I73: ADOLFO LOPES ALONSO CPF: 140.541.618-12 | J73: JULIANA OLIVEIRA DA SILVA CPF: 368.150.938-75 | K73: CONTRATAÇÃO DE SERVIÇO DE PUBLICAÇÃO DE LICITAÇÕES EM JORNAL IMPRESSO E/OU ELETRÔNICO DE GRANDE CIRCULAÇÃO, DENTRO DO ESTADO DE SÃO PAULO, EM OBSERVÂNCIA AO ART. 54, § 1º, DA LEI DE LICITAÇÕES Nº 14.133/2021 | L73: 12 MESES | N73: 21/02/2025 a 21/02/2026 21/02/2026 a 20/02/2027 | O73: 62/2025 | P73: 369/25 | Q73: 2025000000124 | R73: Ajuste 2025000000187 Aditivo 2026000000015 | S73: DP 03/25 | T73: 33794.4 | U73: 21/02/2025 21/02/2026 | V73: 21/02/2025 16/03/2026
A74: =C74-$A$1 -> 279 | B74: =IF(A74<60,"Vencendo","Em Vigência") -> Em Vigência | C74: 46446 | D74: 04/25 | E74: CONTRATO | F74: DOM PEDRITO PARTICIPAÇÕES E EMPREENDIMENTOS IMOBILIÁRIOS LTDA - ME CNPJ: 20.591.702/0001-02 | G74: SECRETARIA DE EDUCAÇÃO, INOVAÇÃO E CULTURA | H74: VINÍCIUS BRUM DA SILVA CPF: 406.779.358-89 | I74: MÔNICA MARA RODRIGUES CPF: 257.494.078-45 | J74: MARCOS ANTÔNIO DE SÁ TELES SOARES CPF: 107.599.358-07 | K74: LOCAÇÃO DE IMÓVEL PARA INSTALAÇÃO DA SECRETARIA DE EDUCAÇÃO, INOVAÇÃO E CULTURA | L74: 48 MESES | N74: 1º Período 01/03/25 A 28/02/27 2º Período 01/03/27 a 28/02/29 | O74: 121/25 | P74: 430/25 | Q74: 2025000000128 | R74: 2025000000247 | S74: INEX 06/25 | T74: R$ 234,000,00 | U74: 45716 | V74: 45728
A75: CONTRATOS COM VENCIMENTO: MARÇO 2027
A76: =C76-$A$1 -> 291 | B76: =IF(A76<60,"Vencendo","Em Vigência") -> Em Vigência | C76: 46458 | D76: 05/25 | E76: 1º Aditivo | F76: BANCO DO BRASIL S.A - CNPJ - 00.000.000/0001-91 | G76: FINANÇAS | H76: RICARDO ABILIO ROSSI CARDOSO CPF sob o nº 246.424.778-29 | I76: MARLENE NUNES DOS SANTOS OLIVEIRA CPF: 080.198.068-22 | J76: LAURA CRISTINA PEREIRA CPF: 066.005.058-77 | K76: CONTRATAÇÃO DA INSTITUIÇÃO FINANCEIRA ACIMA QUALIFICADA PARA PRESTAÇÃO DE SERVIÇOS BANCÁRIOS DE ARRECADAÇÃO DE TRIBUTOS E DEMAIS RECEITAS PÚBLICAS DO MUNICÍPIO DE RIO GRANDE DA SERRA/SP, CONFORME CONDIÇÕES E EXIGÊNCIAS ESTABELECIDAS NESTE INSTRUMENTO, NO ESTUDO TÉCNICO PRELIMINAR E NO TERMO DE REFERÊNCIA CONSTANTES DO PROCEDIMENTO AUXILIAR DE CREDENCIAMENTO Nº 01/2024 | L76: 12 MESES | N76: 12/03/2026 A 12/03/2027 | O76: 1246/2024 | P76: 438/25 | Q76: 2025000000116 | R76: 2025000000106 | S76: INEX 17/24 | T76: - | U76: 46093 | V76: 46105
A77: =C77-$A$1 -> 292 | B77: =IF(A77<60,"Vencendo","Em Vigência") -> Em Vigência | C77: 46459 | D77: 10/24 | E77: Contrato | F77: DAVI ALVES DE OLIVEIRA LTDA CNPJ - 00.700.428/0001-47 | G77: SERVIÇOS URBANOS | H77: WILSON DE SOUZA | I77: Rawany Nathyely Souza Bedia | J77: Daniel Soares da Silva | K77: PRESTAÇÃO DE SERVIÇO DE LOCAÇÃO DE MÁQUINAS E EQUIPAMENTOS PESADOS, ENGLOBANDO O FORNECIMENTO DE MÃO-DE-OBRA E MANUTENÇÃO PREVENTIVA/CORRETIVA, ALÉM DO PROVIMENTO DE MATERIAIS DE CONSUMO NECESSÁRIOS AO COMPLETO DESEMPENHO DOS TRABALHOS DE LIMPEZAS NAS VIAS, FOSSAS, RIOS, CÓRREGOS E LOGRADOUROS PÚBLICOS, DESASSOREAMENTO DE GALERIAS DE ÁGUAS PLUVIAIS, ASSOREAMENTO DE CÓRREGOS, ENTRE OUTROS SERVIÇOS | L77: 12 MESES | N77: 13/03/24 A 13/03/25 | O77: 1074/2023 | P77: 546/2024 | Q77: 2023000000094 | R77: 2024000000162 | S77: DECORRENTE DA ATA N° 12/2023 - PREGÃO PRESENCIAL Nº 35/2023 | T77: 4552141 | U77: 45364 | V77: 45373
E78: 1 º Aditivo | H78: JEFFERSON CRISPIM DE SOUZA | I78: DANIEL SOARES DA SILVA | J78: GUILHERME LEANDRO BERNARDO | L78: 12 MESES | N78: 13/03/25 A 13/03/26 | O78: 1074/2023 | P78: 546/2024 | R78: 2025000000029 | T78: 4759652.3 | U78: 45729 | V78: 45736
E79: 2º Aditivo | H79: JEFFERSON CRISPIM DE SOUZA | I79: DANIEL SOARES DA SILVA | J79: Michele Aparecida de Sousa Carneiro CPF 457.917.218-38 | L79: 12 MESES | N79: 13/03/26 A 12/03/26 | O79: 1074/2023 | P79: 546/2024 | R79: 2026000000027 | T79: 5589457.3 | U79: 46094 | V79: 46106
A80: =C80-$A$1 -> 294 | B80: =IF(A80<60,"Vencendo","Em Vigência") -> Em Vigência | C80: 46461 | D80: 03/2026 | E80: CONTRATO | F80: BIOLIFE MANUTENÇÃO DE EQUIPAMENTOS HOSPITALARES LTDA 57.367.453/0001-78 | G80: SAÚDE | H80: FELIPE VIEIRA DE SÁ DOS SANTOS CPF: 361.930.868-38 | I80: Alessandro dos Santos Possidônio Silva CPF: 192.252.648-79 | J80: Telma Moraes Pires CPF: 263.971.178-47 | K80: CONTRATAÇÃO DE EMPRESA ESPECIALIZADA PARA A PRESTAÇÃO DE SERVIÇOS DE MANUTENÇÃO PREVENTIVA E CORRETIVA PARA OS VENTILADORES PULMONARES DA UNIDADE DE PRONTO ATENDIMENTO (UPA) DE RIO GRANDE DA SERRA | L80: 12 MESES | N80: 16/03/2026 A 15/03/2027 | O80: 44/2026 | P80: 456/26 | Q80: 2026000000119 | R80: 2026000000092 | S80: INEX 01/26 | T80: 33000 | U80: 46086 | V80: 46097
A81: =C81-$A$1 -> 296 | B81: =IF(A81<60,"Vencendo","Em Vigência") -> Em Vigência | C81: 46463 | D81: 08/23 | E81: 3º Aditivo | F81: JML 3 SOLUÇÕES E TRANSPORTES LTDA CNPJ - 05.411.610/0001-00 | G81: EDUCAÇÃO E CULTURA | H81: VINICIUS BRUM DA SILVA CPF: 406.779.358-89 | I81: Alexandre Bueno Alves CPF: 119.560.408-46 | J81: Ivete Freire Santos CPF: 124.425.518-10 | K81: CONTRATAÇÃO DE EMPRESA ESPECIALIZADA PARA PRESTAÇÃO DE SERVIÇOS DE TRANSPORTE ESCOLAR PARA ALUNOS DO ENSINO FUNDAMENTAL MATRICULADOS NA REDE MUNICIPAL DE ENSINO DE RIO GRANDE DA SERRA | L81: 12 MESES | M81: OS 17/03/2023 | N81: 17/03/26 A 17/03/27 | O81: 1969/22 | P81: 684/23 | Q81: 2023000000032 | R81: 2023000000163 | S81: PP 03/23 | T81: 1332576 | U81: 46098 | V81: 46146
A82: =C82-$A$1 -> 300 | B82: =IF(A82<60,"Vencendo","Em Vigência") -> Em Vigência | C82: 46467 | D82: 06/25 | E82: 1º Aditivo | F82: AVOIP TELECON LTDA-ME CNPJ: 53.109.113/0001-96 | G82: SECRETARIA DA FAMÍLIA E DESENVOLVIMENTO SOCIAL | H82: Katia Neris da Silva CPF: 161.660.908-70 | I82: Fernanda Stachowski CPF: 336.725.538-67 | J82: Rodrigo do Carmo Santos CPF: 477.987.948-59 | K82: CONTRATAÇÃO DE PLANO ANUAL DE 04 (QUATRO) LINHAS TELEFÔNICAS MÓVEIS CORPORATIVAS COM ACESSO AO WHATSAPP, PARA ATENDER AS NECESSIDADES DOS SERVIÇOS PERTENCENTES À SECRETARIA DA FAMÍLIA E DESENVOLVIMENTO SOCIAL, PELO PERÍODO DE 12 (DOZE) MESES, CONFORME CONDIÇÕES E EXIGÊNCIAS ESTABELECIDAS NESTE INSTRUMENTO | L82: 12 MESES | N82: 21/03/26 A 21/03/27 | O82: 1780/24 | P82: 530/25 | Q82: - - - | R82: - - - | S82: DP 05/25 | T82: 1995.36 | U82: 46101 | V82: 46146
A83: =C83-$A$1 -> 309 | B83: =IF(A83<60,"Vencendo","Em Vigência") -> Em Vigência | C83: 46476 | D83: 09/26 | E83: CONTRATO | F83: 2P2L ENGENHARIA LTDA CNPJ/MF sob o nº 26.875.439/0001-51 | G83: SAÚDE | H83: FELIPE VIEIRA DE SÁ DOS SANTOS CPF sob o nº 361.930.868-38 | I83: Alex Sandro Barroso Alves CPF: 303.636.638-51 | J83: Alexandro Aparecido dos Santos Costa CPF: 192.281.958-19 | K83: CONTRATAÇÃO DE EMPRESA ESPECIALIZADA PARA REFORMA DA COBERTURA DA UBS CENTRO, LOCALIZADA NA RUA PREFEITO CIDO FRANCO, Nº 500, VILA ARNOUD, RIO GRANDE DA SERRA/SP | L83: 12 MESES | N83: 01/04/2026 A 31/03/2027 | O83: 188/2025 | P83: 608/2026 | Q83: 2026000000131 | R83: AJUSTE 2026000000135 | S83: PE 01/26 | T83: 354000 | U83: 46111 | V83: 46113
A84: CONTRATOS COM VENCIMENTO: ABRIL 2027
A85: =C85-$A$1 -> 311 | B85: =IF(A85<60,"Vencendo","Em Vigência") -> Em Vigência | C85: 46478 | D85: 11/24 | E85: Contrato | F85: CARLA DA SILVA MOREIRA CARLOS PSICOLOGIA LTDA CNPJ - 38.322.528/0001-50 | G85: SEGURANÇA | H85: Charles David Faustino Fumagalli | I85: João Vitor Rocha Amado | J85: Alan Juliez de Souza | K85: CONTRATAÇÃO DE EMPRESA ESPECIALIZADA PARA REALIZAÇÃO DE 50 (CINQUENTA) EXAMES PSICOLÓGICOS COM LAUDO DESTINADOS A ATENDER A GUARDA CIVIL MUNICIPAL DE RIO GRANDE | L85: 12 MESES | M85: OS | N85: 02/04/24 A 02/04/25 | O85: 18/24 | P85: 780/24 | Q85: 2024000000146 | R85: 2024000000194 | S85: DP 06/24 | T85: 9020 | U85: 45384 | V85: 45401
E86: Aditivo | H86: Elias de Lima Meneses CPF 304.013.528-70 | I86: João Vitor Rocha Amado CPF 130.010.486-46 | J86: Alan Juliez de Souza CPF 331.353.138-59 | L86: 12 MESES | N86: 02/04/25 A 02/04/26 | R86: 2025000000034 | T86: 10500 | U86: 45749 | V86: 45810
E87: 2º Aditivo | H87: José Luís Martins Navarro | I87: Fabiano Gomes Duarte CPF 365.558.428-81 | J87: Alan Juliez de Souza CPF 331.353.138-59 | L87: 12 MESES | N87: 02/04/2026 A 01/04/2027 | R87: 2026000000031 | T87: R$ 3.600,00 | U87: 46114 | V87: 46136
A88: =C88-$A$1 -> 324 | B88: =IF(A88<60,"Vencendo","Em Vigência") -> Em Vigência | C88: 46491 | D88: 04/26 | E88: CONTRATO | F88: QUALI INOV SERVIÇOS EMPRESARIAIS LTDA CNPJ/MF sob o nº. 50.999.258/0001-11 | G88: ADMINISTRAÇÃO | H88: MILTON DE SOUZA MARTINS CPF sob o nº 107.599.858-12 | I88: Patricia Flores Xavier | J88: Anderson Aparecido da Silva | K88: PRESTAÇÃO DE SERVIÇOS DE GUARDA E CUSTÓDIA SEGURA DO ACERVO DOCUMENTAL DA PREFEITURA MUNICIPAL DE RIO GRANDE DA SERRA, INCLUINDO TRANSPORTE, ORGANIZAÇÃO, ARMAZENAMENTO, GESTÃO VIA SISTEMA ELETRÔNICO E ATENDIMENTO A SOLICITAÇÕES DE DOCUMENTOS | L88: 12 MESES | N88: 15/04/2026 A 14/04/2027 | O88: 1379/25 | P88: 683/2026 | Q88: 2026000000120 | R88: 2026000000155 | S88: PE 40/25 | U88: 46113 | V88: 46127 | W88: VIGENCIA A PARTIR DA PUBLICAÇÃO
A89: =C89-$A$1 -> 331 | B89: =IF(A89<60,"Vencendo","Em Vigência") -> Em Vigência | C89: 46498 | D89: 15/24 | E89: 2º Aditivo | F89: MÉRITO CONSULTORIA ASSESSORIA OCUPACIONAL E SERVIÇOS LTDA CNPJ - 14.117.450/0001-73 | G89: ADMINISTRAÇÃO | H89: Milton de Souza Martins CPF: 107.599.858-12 | I89: Bruna Gabrielle Ribeiro Reis de Paula CPF: 433.593.348-76 | J89: Natália Virginia Calefe Pereira CPF: 339.741.248-0 | K89: CONTRATAÇÃO DE SERVIÇOS ESPECIALIZADOS DE SEGURANÇA E MEDICINA DO TRABALHO, COM VISTAS À ELABORAÇÃO, IMPLEMENTAÇÃO, ACOMPANHAMENTO E COORDENAÇÃO DO PROGRAMA DE CONTROLE MÉDICO DE SAÚDE E OCUPACIONAL (PCMSO), DO PROGRAMA DE GESTÃO DE RISCOS (PGR) DO PERFIL PROFISSIOGRÁFICO PREVIDENCIÁRIO (PPP) E DA EMISSÃO DE LAUDO TÉCNICO DE CONDIÇÕES AMBIENTAIS DO TRABALHO (LTCAT), PARA OS SERVIDORES DA PREFEITURA MUNICIPAL DE RIO GRANDE DA SERRA, DE ACORDO COM O MANUAL DE ORIENTAÇÃO DO ESOCIAL | L89: 12 MESES | N89: 22/04/26 A 21/04/27 | O89: 152/2023 | P89: 978/24 | Q89: 2024000000158 | R89: 2025000000042 2 ADITIVO 2026000000040 | S89: PE 02/24 | T89: 60151.55 | U89: 46134 | V89: 46142
A90: =C90-$A$1 -> 332 | B90: =IF(A90<60,"Vencendo","Em Vigência") -> Em Vigência | C90: 46499 | D90: 13/24 | E90: 2º Aditivo | F90: QUALI INOV SERVIÇOS EMPRESARIAIS LTDA CNPJ - 50.999.258/0001-11 | G90: EDUCAÇÃO | H90: VINICIUS BRUM DA SILVA CIN sob o nº. 406.779.358-89 | I90: Paula Neves Bernardo Garcia CPF: 163.539.478-36 | J90: José Benedito da Silva CPF: 037.917.436-78 | K90: CONTRATAÇÃO DE EMPRESA ESPECIALIZADA PARA PRESTAÇÃO DE SERVIÇOS DE LIMPEZA TÉCNICA E CONSERVAÇÃO PREDIAL DE AMBIENTES ASSISTENCIAIS E ADMINISTRATIVOS, ALÉM DE ÁREAS EXTERNAS, INCLUINDO O FORNECIMENTO DE MÃO DE OBRA, MATERIAIS DE HIGIENE E LIMPEZA, UTENSÍLIOS, EQUIPAMENTOS E DEMAIS INSUMOS NECESSÁRIOS EM UNIDADES ESCOLARES DO MUNICÍPIO DE RIO GRANDE DA SERRA | L90: 12 MESES com cláusula resolutiva | N90: 23/04/26 A 22/04/27 | O90: 2199/22 | P90: 814/24 | Q90: 2024000000161 | R90: 2024000000234 1º TERMO ADITIVO 2025000000041 2º TERMO ADITIVO 2026000000036 | S90: PP 60/23 | T90: 1274299.9 | U90: 46135 | V90: 46149
A91: =C91-$A$1 -> 333 | B91: =IF(A91<60,"Vencendo","Em Vigência") -> Em Vigência | C91: 46500 | D91: 17/24 | E91: 2º Aditivo | F91: GARLOC TRANSPORTES, LOGISTICA E LOCAÇÕES LTDA CNPJ - 69.205.789/0001-13 | G91: EDUCAÇÃO | H91: VINICIUS BRUM DA SILVA | I91: Alex Bueno Alves | J91: José Benedito Pereira Lopes | K91: CONTRATAÇÃO DE EMPRESA ESPECIALIZADA PARA PRESTAÇÃO DE SERVIÇOS DE TRANSPORTE ESCOLAR PARA ALUNOS DO ENSINO FUNDAMENTAL MATRICULADOS NA REDE MUNICIPAL DE ENSINO DE RIO GRANDE DA SERRA | L91: 12 MESES | N91: 24/04/26 A 23/04/27 | O91: 2413/23 | P91: 596/24 | S91: pp 54/23 | T91: 5424000 | U91: 45771 | V91: 46142
A92: CONTRATOS COM VENCIMENTO: MAIO 2027
A93: =C93-$A$1 -> 358 | B93: =IF(A93<60,"Vencendo","Em Vigência") -> Em Vigência | C93: 46525 | D93: 13/25 | E93: 2º Aditivo | F93: ALEX REPARAÇÃO DE MÁQUINAS LTDA CNPJ/MF sob o nº 05.820.499/0001-05 | G93: SAÚDE | H93: Felipe Vieira de Sá dos Santos CPF: 361.930.868-38 | I93: Alex Sandro Barroso Alves CPF: 303.636.638-51 | J93: Lucas Pereira Marques CPF: 415.829.618-83 | K93: CONTRATAÇÃO DE EMPRESA ESPECIALIZADA PARA INSTALAÇÃO E MANUTENÇÃO DE APARELHOS CONDICIONADORES DE AR, NAS UNIDADES DE SAÚDE DO MUNICÍPIO DE RIO GRANDE DA SERRA | L93: 12 MESES | N93: 19/05/25 A 19/05/26 19/05/26 A 18/05/27 | O93: 733/24 | P93: 950/25 | Q93: 2025000000139 | R93: AJUSTE 2025000000361 ADITIVO 2026000000038 | S93: PE 04/25 | T93: 140365.32 | U93: 03/12/2025 14/05/2026 | V93: 11/12/2025 18/05/2026 | W93: ACRÉSCIMO 15.2% REAJUSTE 4,14%
A94: =C93-$A$1 -> 358 | B94: Em Vigência | C94: 46526 | D94: 15/26 | E94: Contrato | F94: EBD BIOTECH IMPORTAÇÃO E COMERCIO DE PRODUTOS MÉDICOS HOSPITALARES LTDA CNPJ Nº 13.977.106/0001-91 | G94: SAÚDE | H94: Felipe Vieira de Sá dos Santos CPF: 361.930.868-38 | I94: Renata Cassimiro dos Reis CPF: 411.978.028-78 | J94: Leonardo de Oliveira CPF: 387.442.738-27 | K94: AQUISIÇÃO DE TESTE RÁPIDO PARA DETECÇÃO DE ANTÍGENO NS1 PARA O VÍRUS DA DENGUE | L94: 12 MESES | N94: 20/05/2026 A 19/05/2027 | O94: 19/26 | P94: 836/26 | R94: 2026000000233 | S94: PE 17/26 | T94: R$ 8.400,00 | U94: 46160 | V94: 46162
A95: CONTRATOS COM VENCIMENTO: JULHO 2027
A96: =C96-$A$1 -> 403 | B96: =IF(A96<60,"Vencendo","Em Vigência") -> Em Vigência | C96: 46570 | D96: 29/25 | E96: Contrato | F96: NOROESTE COMERCIAL DE SUPRIMENTOS LTDA CNPJ/MF sob o nº 01.148.472/0001-59 | G96: SAÚDE | H96: FABIANA BÉDIA DA SILVA LOPES CPF/MF sob o nº. 270.620.848-16 | I96: Bruno Henrique Rioichi Uchiyama CPF: 390.183.978-06 | J96: Alexandre Petrokas Meskele CPF: 285.077.288-71 | K96: CONTRATAÇÃO DE EMPRESA PARA PRESTAÇÃO DE SERVIÇOS DE DEDETIZAÇÃO E DESRATIZAÇÃO, SENDO 02 (DUAS) APLICAÇÕES COM INTERVALO DE 06 (SEIS) MESES, COM O EFETIVO CONTROLE DE PRAGAS, DAS ÁREAS INTERNAS E EXTERNAS DAS UNIDADES: CRAS, CREAS, SAICA (SERVIÇO DE ACOLHIMENTO INSTITUCIONAL PARA CRIANÇAS E ADOLESCENTES), CONSELHO TUTELAR, E DA SEDE DA SECRETARIA DA FAMÍLIA E DESENVOLVIMENTO SOCIAL | L96: 12 MESES | M96: - | N96: 02/07/25 A 02/07/26 | O96: 490/2025 | P96: 1272/2025 | Q96: NÃO PRECISA VALOR MÍNIMO | R96: NÃO PRECISA VALOR MÍNIMO | S96: DISP 23/25 | T96: 3609 | U96: 45835 | V96: 45840
A97: =C97-$A$1 -> 405 | B97: =IF(A97<60,"Vencendo","Em Vigência") -> Em Vigência | C97: 46572 | D97: 28/24 | E97: Contrato | F97: NATALIA MIRANDA DE ALMEIDA YAMADA CPF - 255.360.898-54 GILMAR MIRANDA DE ALMEIDA YAMADA CPF - 280.472.208-29 | G97: MEIO AMBIENTE | H97: VINICIUS CARVALHO AMANTE | I97: VINICIUS CARVALHO AMANTE | J97: GUSTAVO SOARES GOMES | K97: LOCAÇÃO DE IMÓVEL PARA INSTALAÇÃO DE CLINICA VETERINÁRIA E CRIAÇÃO DO DEPARTAMENTO DE BEM ESTAR ANIMAL VINCULADA A SECRETARIA DE VERDE E MEIO AMBIENTE | L97: 36 MESES | M97: - | N97: 04/07/24 A 04/07/27 | O97: 1078/24 | P97: 1379/2024 | Q97: 2024000000215 | R97: 2024000000403 | S97: INEX 08/24 | T97: 180000 | U97: 45477
A98: CONTRATOS COM VENCIMENTO: SETEMBRO 2027
A99: =C99-$A$1 -> 479 | B99: =IF(A99<60,"Vencendo","Em Vigência") -> Em Vigência | C99: 46646 | D99: 38/24 | E99: Contrato | F99: COOPERATIVA DOS RECICLADORES DO BRASIL - RECIBRAS CNPJ - 13.439.287/0001-00 | G99: MEIO AMBIENTE | H99: VINICIUS CARVALHO AMANTE | I99: VINICIUS CARVALHO AMANTE | J99: GUSTAVO SOARES GOMES | K99: COOPERATIVA OU ASSOCIAÇÃO DE CATADORES DE MATERIAIS RECICLÁVEIS APTA A TRIAR, BENEFICIAR E COMERCIALIZAR RESÍDUOS POTENCIALMENTE RECICLÁVEIS PROVENIENTES DO MUNICÍPIO DE RIO GRANDE DA SERRA, BEM COMO GESTÃO DOS PONTOS DE ENTREGA VOLUNTÁRIA (PEV'S), ECOPONTOS E ESTRUTURAS DE APOIO (UNIDADE DE TRIAGEM), ATRAVÉS DA ASSINATURA DE TERMO DE COLABORAÇÃO PRÓPRIO | L99: 37 MESES | N99: 16/09/24 a 16/09/27 | O99: 999/23 | P99: 1768/2024 | Q99: - | R99: - | S99: CHAMAMENTO 35/24 | T99: 748800 | U99: 45551
A100: CONTRATOS COM VENCIMENTO: OUTUBRO 2027
...

Sheet CONTRATOS ENCERRADOS
A1: =TODAY() -> 46167
A2: TÉRMINO DA VIGÊNCIA | B2: CONTRATO | C2: ADITIVO | D2: FORNECEDOR | E2: SECRETARIA | F2: SECRETÁRIO | G2: GESTOR | H2: FISCAL | I2: OBJETO | J2: VIGÊNCIA MESES | K2: PERÍODO | L2: PROCESSO ADMINISTRATIVO | M2: PROCESSO EXECUÇÃO | N2: AUDESP LICITAÇÃO | O2: AUDESP AJUSTE | P2: MODALIDADE LICITAÇÃO | Q2: VALOR TOTAL CONTRATO | R2: ASSINATURA ATUAL | S2: DATA DE PUBLICAÇÃO | T2: OBSERVAÇÃO
A3: 46161 | B3: 14/25 | C3: Contrato | D3: ATN CAMPOS COMÉRCIO, PRESTAÇÃO DE SERVIÇOS, IMPORTAÇÃO E EXPORTAÇÃO LTDA CNPJ/MF sob o nº 54.682.221/0001-16 | E3: CIDADANIA | F3: Elza dos Anjos Iwasaki | G3: Fernanda Stachowski | H3: Cibely Aparecida Miranda dos Santos | I3: CONTRATAÇÃO DE EMPRESA PARA CONFECÇÃO DE 03 (TRÊS) UNIDADES DE PLACAS DE IDENTIFICAÇÃO, INCLUINDO O DESENVOLVIMENTO DE ARTE E INSTALAÇÃO, PARA ATENDER ÀS NECESSIDADES DA SECRETARIA DA FAMÍLIA E DESENVOLVIMENTO SOCIAL | J3: 12 MESES | L3: 19/05/25 A 19/05/26 | M3: 547/25 | N3: - | O3: - | P3: - | Q3: DP 08/25 | R3: 3368.43 | S3: 45789 | T3: 45796
A4: 46155 | B4: 02/2026 | C4: CONTRATO | D4: SIMONI INDUSTRIA GRAFICA LTDA CNPJ/MF Sob o nº 37.652.289/0001-33 | E4: FAMÍLIA | F4: KÁTIA NÉRIS DA SILVA | G4: Fernanda Stachowski | H4: Rodrigo do Carmo Santos | I4: AQUISIÇÃO DE PLACAS DE IDENTIFICAÇÃO, BANNER, FOLDERS E DEMAIS MATERIAIS, COM A FINALIDADE DE ESTRUTURAR OS AMBIENTES DA SECRETARIA E SEUS EQUIPAMENTOS INCLUINDO O NOVO ESPAÇO DO CENTRO DE REFERÊNCIA DE ASSISTÊNCIA SOCIAL (CRAS) E FACILITAR O ACESSO DA POPULAÇÃO AOS SERVIÇOS OFERECIDOS | J4: 30 DIAS | L4: 14/04/2026 A 13/05/2026 | M4: 1901/2025 | N4: - | O4: 2026000000116 | P4: 2026000000158 | Q4: PE 39/2025 | R4: R$ 15.000,00 | S4: 46126 | T4: 46128
A5: 46170 | B5: 15/25 | C5: Contrato | D5: ATN CAMPOS COMÉRCIO, PRESTAÇÃO DE SERVIÇOS, IMPORTAÇÃO E EXPORTAÇÃO LTDA | E5: DESENVOLVIMENTO | F5: André Martins Caparroz CPF 292.921.258-69 | G5: Cristopher Ferraz Araujo CPF 228.469.558-24 | H5: Isabella Favero Fazani CPF 450.711.818-27 | I5: AQUISIÇÃO DE 02 (DOIS) TOTENS DE INFORMAÇÃO TURÍSTICA, A SEREM ALOCADOS EM ESPAÇOS ESTRATÉGICOS E DE GRANDE CIRCULAÇÃO NO MUNICÍPIO DE RIO GRANDE DA SERRA | J5: 12 meses | L5: 28/05/25 a 28/05/25 | M5: 386/25 | N5: 1164/2025 | O5: 2025000000149 | P5: 2025000000407 | Q5: DP 14/25 | R5: 11200 | S5: 45805 | T5: 45819 | U5: DESINTERESSE MANIFESTO POR E-MAIL EM 22/04/2026, ÀS 10:43 - QUARTA-FEIRA
A6: 46094 | B6: 09/24 | C6: Contrato | D6: ZENITE PROJETOS E CONSTRUÇÕES LTDA CNPJ: 46.294.771/0001-30 | E6: OBRAS | F6: KLEBER AVELINO DE OLIVEIRA CPF: 373.855.598-67 | G6: KLEBER AVELINO DE OLIVEIRA CPF: 373.855.598-67 | H6: JOÃO VICTOR SILVA CPF: 484.664.358-16 | I6: CONTRATAÇÃO DE EMPRESA PARA PRESTAÇÃO DE SERVIÇOS DE ELABORAÇÃO DE ESTUDO PRELIMINAR, PROJETOS BÁSICOS/EXECUTIVOS MULTIDISCIPLINARES PARA IMPLANTAÇÃO DO CONJUNTO HABITACIONAL E URBANIZAÇÃO, BEM COMO A ELABORAÇÃO DA DOCUMENTAÇÃO LEGAL E SERVIÇOS DE APROVAÇÃO EM TODOS OS ÓRGÃOS PÚBLICOS COMPETENTES PARA IMPLANTAÇÃO DO EMPREENDIMENTO RIO GRANDE DA SERRA | J6: 11 MESES | K6: 45425 | L6: 13/05/2024 A 13/04/2025 | M6: 1708/2023 | N6: 622/24 | O6: 2024000000138 | P6: 2024000000188 | Q6: CO 16/23 | R6: 210000 | S6: 45371 | T6: 45400
C7: 1º aditivo | F7: LEANDRO DIAS FLORÊNCIO CPF: 335.659.528-81 | G7: LEILA ANDREASSI DE CASTRO CPF: 235.681.298-92 | H7: GUILHERME TADEU APARECIDO DE OLIVEIRA DIAS DO PRADO CPF: 414.046.498-40 | J7: 11 MESES | L7: 13/04/2025 A 13/03/2026 | O7: 2024000000138 | Q7: CO 16/23 | S7: 45760 | T7: 45793 | U7: PRORROCAÇÃO SOMENTE DE PRAZO
A8: 46082 | B8: 48/25 | C8: Contrato | D8: PROJESOL ENGENHARIA LTDA CNPJ/MF sob o nº 38.517.835/0001 96 | E8: GOVERNO | F8: Maciel Manoel de Oliveira CPF: 131.613.048 70 | G8: Aline Macruz CPF: 379.914.218 56 | H8: Karine Roque Nascimento CPF: 389.766.778 97 | I8: CONTRATAÇÃO DE EMPRESA(S) ESPECIALIZADA(S) NA PRESTAÇÃO DE SERVIÇOS DE TOPOGRAFIA E SONDAGEM PARA IMPLANTAÇÃO DE UNIDADES HABITACIONAIS MINHA CASA, MINHA VIDA FHNIS SUB 50 | J8: 03 MESES | L8: 01/12/2025 A 01/03/2025 | M8: 2241/2025 | N8: 2212/2025 | P8: AJUSTE 2025000000809 | Q8: DP Nº 41/25 | R8: 24888.88 | S8: 45992 | T8: 45992
A9: 46073 | B9: 33/23 | C9: 2º Aditivo | D9: VIAPRECISA TERRAPLANAGEM E PAVIMENTAÇÃO LTDA CNPJ - 31.133.672/0001-07 | E9: OBRAS | F9: Leandro Dias Florencio | G9: Leila Andreassi de Castro | H9: Leandro Dias Florencio | I9: CONTRATAÇÃO DE EMPRESA PARA EXECUÇÃO DE PAVIMENTAÇÃO, DRENAGEM E SINALIZAÇÃO DE VIA URBANA – CHÁCARA SÃO PAULO | J9: 270 DIAS | K9: 45173 | L9: 26/05/25 A 20/02/26 | M9: 1864/22 | N9: 1552/23 | O9: 2023000000099 | P9: AJUSTE 2023000000344 1º ADITIVO 2024000000032 2º ADITIVO 2025000000055 | Q9: CO 9/23 | R9: 743798.67 | S9: 45803 | T9: 45834
A10: 46066 | B10: 01/25 | C10: Contrato | D10: ATIVA HEALTH SERVIÇOS MÉDICOS LTDA CNPJ: 35.697.111/0001-83 | E10: SAÚDE | F10: Felipe Vieira de Sá dos Santos CPF: 361.930.868-38 | G10: Alessandro dos Santos Possidônio Silva CPF: 192.252.648-79 | H10: Telma Moraes Pires CPF: 263.971.178-47 | I10: CONTRATAÇÃO EMERGENCIAL DE EMPRESA PARA PRESTAÇÃO DE SERVIÇOS DE ASSISTÊNCIA À SAÚDE, COMPOSTOS POR ATIVIDADES MÉDICAS ASSISTENCIAIS, SERVIÇOS DE DIAGNÓSTICOS: RAIO-X, ULTRASSONOGRAFIA, MAMOGRAFIA E EXAMES LABORATORIAIS, COM FORNECIMENTO DE EQUIPAMENTOS E MÃO DE OBRA, EXCETO APARELHO DE USG E MAMÓGRAFO QUE PERTENCEM A PREFEITURA MUNICIPAL DE RIO GRANDE DA SERRA, DESTINADOS À COMPLEMENTAR E ATENDER ÀS NECESSIDADES DAS UNIDADES BÁSICA DE SAÚDE, UPA – UNIDADE DE PRONTO ATENDIMENTO E CEME – CENTRO DE ESPECIALIDADES MÉDICAS DA SECRETARIA MUNICIPAL DE SAÚDE DE RIO GRANDE DA SERRA | J10: 06 meses | K10: 45701 | L10: 13/08/25 a 13/02/26 | M10: 212/2025 | N10: 346/2025 | O10: 2025000000122 | P10: 2025000000179 | Q10: DP 02/25 | R10: 8317509.3 | S10: 45882 | T10: 45895
A11: 46064 | B11: 32/24 | C11: 1º Aditivo | D11: LMM ENGENHARIA E SERVIÇOS LTDA CNPJ - 44.626.011/0001-57 | E11: OBRAS | F11: Wanderlei Felipe da Silva Junior | G11: Leila Andreassi de Castro | H11: Adriano de Sousa Pereira | I11: CONTRATAÇÃO DE EMPRESA ESPECIALIZADA EM ENGENHARIA OU ARQUITETURA PARA A ADAPTAÇÃO DE IMÓVEL DESTINADO AO CENTRO DE ESPECIALIDADES MÉDICAS (CEME) | J11: 360 DIAS | L11: 15/08/25 A 11/02/26 | M11: 531/24 | N11: 1602/24 | O11: 2024000000234 | P11: 2024000000461 1º aditivo 2025000000081 | Q11: CO 05/24 | R11: 814885 | S11: 45884
A12: 46272 | B12: 19/22 | C12: 3º Aditivo | D12: TULIO CASSAROTTI JUNIOR CPF - 155.335.868-65 | E12: CIDADANIA | F12: ELZA DOS ANJOS IWASAKI | G12: Fernanda Stachowski | H12: Cibely Aparecida Miranda dos Santos | I12: LOCAÇÃO DE IMÓVEL LOCALIZADO NA RUA SANTA BRANCA, Nº 24, JARDIM SANTA TEREZA, RIO GRANDE DA SERRA/SP, ONDE ESTÁ INSTALADO O CENTRO DE REFERENCIA DE ASSISTÊNCIA SOCIAL - CRAS, PARA ATENDER A SECRETARIA DE CIDADANIA E INCLUSÃO SOCIAL | J12: 12 meses | K12: CLÁUSULA RESOLUTIVA CONTRATO ENCERRADO | L12: 07/09/25 À 07/09/26 | M12: 1034/2022 | N12: 1675/2022 | P12: ADITIVO 3 2025000000084 | Q12: DP 15/22 | R12: 72000 | S12: 45905 | T12: 45930 | U12: CLÁUSULA RESOLUTIVA
A13: 46018 | B13: 45/24 | C13: 1º Aditivo | D13: VITÓRIA SERVIÇOS OPERACIONAIS LTDA CNPJ - 10.354.733/0001-88 | E13: OBRAS | F13: Leandro Dias Florêncio CPF: 335.659.528-81 | G13: João Victor Silva CPF: 484.664.358-16 | H13: Leandro Dias Florêncio CPF: 335.659.528-81 | I13: CONTRATAÇÃO DE EMPRESA ESPECIALIZADA EM ENGENHARIA PARA CONSTRUÇÃO DO TERMINAL RODOVIÁRIO MUNICIPAL NO MUNICÍPIO DE RIO GRANDE DA SERRA – ETAPA 07 | J13: 15 MESES | K13: 45572 | L13: 30/09/2024 A 30/12/2025 | M13: 343/24 | N13: 1867/2024 | O13: 2024000000258 | P13: 2024000000071 | Q13: CO 03/24 | R13: 3959514.2 | S13: 45632 | T13: 45632
A14: 46023 | B14: 39/25 | C14: CONTRATO sem renovação | D14: BIOLIFE MANUTENÇÃO DE EQUIPAMENTOS HOSPITALARES CNPJ:57.367.453/0001-78 | E14: SAÚDE | F14: Felipe Vieira de Sá dos Santos CPF: 361.930.868-38 | G14: Alessandro dos Santos Possidônio Silva CPF: 192.252.648-79 | H14: Telma Moraes Pires CPF: 263.971.178-47 | I14: CONTRATAÇÃO DE EMPRESA ESPECIALIZADA PARA A PRESTAÇÃO DE SERVIÇOS DE MANUTENÇÃO PREVENTIVA E CORRETIVA DOS VENTILADORES PULMONARES DA UNIDADE DE PRONTO ATENDIMENTO (UPA) DE RIO GRANDE DA SERRA | J14: 90 DIAS | L14: 03/10/2025 A 01/01/2026 | M14: 1246/25 | N14: 2018/2025 | O14: 2025000000201 | P14: AJUSTE 2025000000684 | Q14: INEX 17/25 | R14: 23050 | S14: 45658 | T14: 45933 | U14: VIGÊNCIA A PARTIR DA PUBLICAÇÃO
A15: 46011 | B15: 34/2022 | C15: 2º ADITIVO | D15: IGEVE - INSTITUTO DE GESTÃO EDUCACIONAL E VALORIZAÇÃO DO ENSINO CNPJ: 28.413.401/0001-92 | E15: EDUCAÇÃO E CULTURA | F15: ALESSANDRA AMORA BARCHINI | G15: LAMARTINE DOURADO CAVALCANTE | H15: COMISSÃO DE AVALIAÇÃO E MONITORAMENTO - PORTARIA 717/22 | I15: TERMO DE COLABORAÇÃO PARA O ATENDIMENTO DOS ALUNOS MATRICULADOS NA EDUCAÇÃO INFANTIL, BEM COMO A GESTÃO OPERACIONAL (NÃO PEDAGÓGICA) DAS UNIDADES ESCOLARES DE EJA (EDUCAÇÃO DE JOVENS E ADULTOS) E AEE (ATENDIMENTO EDUCACIONAL ESPECIALIZADO) E DE ENSINO FUNDAMENTAL 1. | J15: 12 MESES | K15: 44915 | L15: 20/12/2024 A 20/12/2025 | M15: 1881/2022 | N15: 2479/2022 | O15: NÃO SE TRATA DE PROCESSO LICITATÓRIO | P15: NÃO SE TRATA DE PROCESSO LICITATÓRIO | Q15: CHAMAMENTO PÚBLICO N° 02/22 - SEC | R15: 11201921
A16: 46009 | B16: 53/24 | C16: Contrato | D16: KONICA MINOLTA HEALTHCARE DO BRASIL INDÚSTRIA DE EQUIPAMENTOS MÉDICOS LTDA | E16: SAÚDE | F16: Luís Fernando Pinotti Silva | G16: VALQUIRIA HELENA DOS SANTOS GONÇALVES | H16: NADJA MARIA SANTOS SILVA | I16: AQUISIÇÃO DE MAMÓGRAFO VISANDO ATENDER A SECRETARIA MUNICIPAL DE SAÚDE | J16: 12 MESES | L16: 18/12/2024 A 18/12/2025 | M16: 487/2024 | O16: 2024000000297 | P16: 2025000000003 | Q16: PE 33/24 | R16: 849000 | S16: 45644 | T16: 45645
A17: 45983 | B17: 46/24 | C17: Contrato | D17: EDUARDO NELSON CANIL LTDA | E17: ADMINISTRAÇÃO/FINANÇAS | F17: Alex Sandro barroso Alves e Cassio Roberto de Souza Pegoraro | G17: Gilmar Santana dos Santos | H17: José Uiliam Loiola da Silva | I17: CONTRATAÇÃO DE ESCRITÓRIO DE ADVOCACIA ESPECIALIZADO NA PRESTAÇÃO DE ASSESSORIA E CONSULTORIA JURÍDICA A SECRETARIA ADMINISTRATIVA E DE FINANÇAS, COM O FIM ESPECÍFICO DE IMPOSTO DE RENDA, O QUAL FOI REPASSADO INDEVIDAMENTE E RECEITA FEDERAL | J17: 22/11/2024 A 22/11/2025 | L17: 22/11/2024 A 22/11/2025 | M17: 1993/2024 | N17: 2243/2024 | O17: - - - | P17: - - - | Q17: INEX N° 16/24 | R17: O valor equivalente a 20% (vinte por cento) do valor restituído. | S17: 45618
A18: 45978 | B18: 25/22 | C18: Contrato | D18: FUNDAÇÃO DE APOIO À UNIVERSIDADE MUNICIPAL DE SÃO CAETANO DO SUL CNPJ - 13.166.456/0001-78 | E18: ADMINISTRAÇÃO | F18: Alexsandra Silva Aguiar - CPF: 180.290.728-99 | G18: Suzana Lopes Quintão Silva - CPF: 277.740.328-78 | H18: Iasmin Maria da Silva - CPF: 390.280.658-30 | I18: CONTRATAÇÃO DE EMPRESA ESPECIALIZADA PARA PRESTAÇÃO DE SERVIÇOS DE REVISÃO DA ESTRUTURA ADMINISTRATIVA ORGANIZACIONAL DA PREFEITURA DE RIO GRANDE DA SERRA | J18: 12 Meses | K18: 44882 | L18: 17/11/22 a 17/11/23 | M18: 1660/22 | N18: 2358/22 | O18: LICITAÇÃO 2022000000118 | P18: 2022000000391 | Q18: DP 30/22 | R18: 300000 | S18: 44882 | T18: 44900
C19: 1º Aditivo | F19: Alexsandra Silva Aguiar - CPF: 180.290.728-99 | G19: Suzana Lopes Quintão Silva - CPF: 277.740.328-78 | H19: Marcela Barbosa Porto - CPF: 365.896.138-42 | J19: 12 Meses | L19: 17/11/23 a 17/11/24 | P19: 2024000000002 | S19: 45245 | T19: 45301 | U19: PRORROGAÇÃO DE VIGÊNCIA
C20: 2º Aditivo | F20: Alex Barroso Alves - CPF: 140.234.958-08 | G20: Alex Barroso Alves - CPF: 140.234.958-08 | H20: Gilmar Santana dos Santos - CPF: 381.836.618-74 | J20: 12 MESES | L20: 17/11/24 A 17/11/25 | P20: 2024000000072 | S20: 45610 | T20: 45629 | U20: PRORROGAÇÃO DE VIGÊNCIA
A21: =#REF!-$A$1 -> #REF! | B21: 47/24 | C21: RESCISÃO | D21: RENOV PAVIMENTAÇÃO E CONSTRUÇÕES LTDA | E21: OBRAS | F21: WANDERLEI | G21: - | H21: - | I21: CONTRATAÇÃO DE EMPRESA ESPECIALIZADA PARA EXECUÇÃO DE RECAPEAMENTO E PAVIMENTAÇÃO ASFÁLTICA COM SINALIZAÇÃO VIÁRIA HORIZONTAL – ÁREA CENTRAL LOCALIZADA NA AVENIDA DOM PEDRO I – CENTRO – RIO GRANDE DA SERRA/SP | J21: 300 DIAS | K21: FALTA OS | L21: OS | M21: 1155/2024 | N21: 2253/2024 | O21: 2024000000272 | P21: 2024000000628 | Q21: CO 07/24 | R21: 813280 | S21: 45980
A22: 45939 | B22: 40/23 | C22: 1º Aditivo | D22: PRODESP - COMPANHIA DE PROCESSAMENTO DE DADOS DO ESTADO DE SÃO PAULO - CNPJ: 62.577.929/0001-35 | E22: SEGURANÇA URBANA, TRANSITO E DEFESA CIVIL | F22: Izaias Fernandes | G22: Mauro Munhoz Martins Fernandes | H22: Alexandre de Lima Campos | I22: PRESTAÇÃO DE SERVIÇOS TECNICOS DE INFORMATICA REALTIVO A CESSÃO DE INFORMAÇÕES DO BANCO DE DADOS DO DETRAN PARA O PROCESSAMENTO DE MULTAS DE TRÂNSITO | J22: 12 MESES | K22: OS 09/10/2023 | L22: 09/10/2025 A 09/10/2026 | M22: 1566/2023 | N22: 2534/2023 | O22: ADITIVO 2023000000126 | P22: 2025000000022 | Q22: DP 15/23 | R22: 10310.4 | S22: 45573 | T22: 45744 | U22: PRORROGÁVEL NO LIMITE DE 60 MESES - LEI 8.666/93
A23: 45930 | B23: 41/24 | C23: Contrato | D23: GARLOC TRANSPORTES, LOGISTICA E LOCAÇÕES LTDA CNPJ - 69.205.789/0001-13 | E23: EDUCAÇÃO | F23: ALESSANDRA | G23: Lamartine Dourado Cavalcante | H23: Ari Inácio de Souza | I23: CONTRATAÇÃO DE EMPRESA ESPECIALIZADA PARA PRESTAÇÃO DE SERVIÇOS DE TRANSPORTE ESCOLAR PARA ALUNOS DO ENSINO FUNDAMENTAL MATRICULADOS NA REDE MUNICIPAL DE ENSINO DE RIO GRANDE DA SERRA | J23: 12 MESES | K23: 45566 | L23: 30/09/24 À 30/09/25 | M23: 2413/23 | N23: 1908/2024 | O23: 2024000000140 | P23: AJUSTE 2024000000570 | Q23: PP 54/23 | R23: 480000 | S23: 45565
A24: 45946 | B24: 39/24 | C24: Contrato | D24: COMPANHIA BRASILEIRA DE CARTUCHOS CNPJ - 57.494.031/0001-63 | E24: SEGURANÇA | F24: Yuri Laled Lobato El Malat | G24: João Vitor Rocha Amado | H24: Ariane Fajoli de Souza | I24: AQUISIÇÃO DE MUNIÇÕES CBC 9MM LUGER ETOG 124GR E CBC 9MM LUGER+P EXPO 124GR BONDED A | J24: 16/10/2024 A 16/10/2025 | M24: 1360/2024 | N24: 2001/2024 | O24: 20244000000243 | P24: AJUSTE 2024000000594 | Q24: INEX 12/2024 | R24: 35750 | S24: 45561
A25: 45923 | B25: 18/25 | C25: Contrato | D25: FL CONTROLE DE PRAGAS E SERVIÇO GERAIS LTDA | E25: CIDADANIA | F25: ELSA DOS ANJOS IWASAKI | G25: CIBELY APARECIDA MIRANDA DOS SANTOS CPF: 462.455.488-45 | H25: FERNANDA STACHOWSKI | I25: CONTRATAÇÃO DE EMPRESA PARA PRESTAÇÃO DE SERVIÇOS DE LIMPEZA DE CAIXA D’AGUA DAS UNIDADES: CRAS, CREAS, SAICA, CONSELHO TUTELAR E DA SECRETARIA DA FAMÍLIA E DESENVOLVIMENTO SOCIAL | J25: 90 DIAS | L25: 23/06/2025 A 23/09/2025 | M25: 145/2025 | N25: 1217/2025 | O25: NÃO SE APLICA DEVIDO O VALOR | P25: NÃO SE APLICA DEVIDO O VALOR | Q25: DP 17/25 | R25: 1649.96 | S25: 45821 | T25: 45831
A26: 45913 | B26: 36/24 | C26: Contrato | D26: NP TECNOLOGIA E GESTÃO DE DADOS LTDA CNPJ: 07.797.967/0001-95 | E26: ADMINISTRAÇÃO | F26: Alex Sandro Barroso Alves | G26: Daniela Aparecida Ferreira Magalhães Terra | H26: Conceição Aparecida Trajano da Silva | I26: CONTRATAÇÃO DE EMPRESA ESPECIALIZADA NO FORNECIMENTO DE ASSINATURA DE FERRAMENTA DE PESQUISA E COMPARAÇÃO DE PREÇOS PRATICADOS PELA ADMINISTRAÇÃO PÚBLICA | J26: 12 MESES | K26: 45548 | L26: 13/09/24 À 13/09/2025 | M26: 890/2024 | N26: 1733/2024 | O26: 2024000000240 | P26: 2024000000519 | Q26: INX 10/24 | R26: 14950 | S26: 45545
A27: 45897 | B27: 24/24 | C27: Contrato | D27: FC GERADORES LTDA CNPJ - 27.117.171/0001-51 | E27: SAÚDE | F27: Luís Fernando Pinotti Silva | G27: Telma Moraes Pires | H27: Milton Luiz Rodrigues dos Santos | I27: CONTRATAÇÃO DE EMPRESA ESPECIALIZADA EM PRESTAÇÃO DE SERVIÇO DE MANUTENÇÃO PREVENTIVA E CORRETIVA PARA GRUPO DE GERADORES DA SECRETARIA MUNICIPAL DE SAÚDE – UNIDADE DE PRONTO ATENDIMENTO – UPA | J27: 12 meses | K27: - | L27: 28/08/24 A 28/08/25 | M27: 74/24 | N27: 1711/24 | O27: 2024000000246 | P27: 2024000000490 | Q27: CD 25/24 | R27: 5400 | S27: 45532
A28: 45891 | B28: 33/24 | C28: Contrato | D28: CAIXA ECONÔMICA FEDERAL CNPJ - 00.360.305/0001-04 | E28: OBRAS | F28: LEANDRO | G28: Leandro Dias Florêncio | H28: Gislene Stephanelli | I28: CONTRATAÇÃO DE EMPRESA ESPECIALIZADA PARA CAPACITAÇÃO DE SERVIÇOS TÉCNICOS NA MOBILIDADE OFICINA DE CAPACITAÇÃO COM OS TEMAS: ENGENHARIA DE CUSTOS – MOBILIDADE À DISTÂNCIA | J28: 12 meses | L28: 22/08/2024 A 22/08/2025 | M28: 1454/2024 | Q28: INEXIGIBILIDADE Nº 09/24 | R28: 4370 | S28: 45526
A29: 45874 | B29: 31/24 | C29: 1º Aditivo | D29: TBRT AUDITORES INDEPENDENTES S/S CNPJ - 03.566.241/0001-90 | E29: ADMINISTRAÇÃO | F29: MILTON DE SOUZA MARTINS - CPF/MF sob o nº. 107.599.858-12 | G29: ERIKA TIEMI SEKITANI - CPF: 127.071.258-65 | H29: BRUNA GABRIELLE RIBEIRO DE PAULA - CPF: 433.593.348-76 | I29: CONTRATAÇÃO DE EMPRESA ESPECIALIZADA NA CAPACITAÇÃO TÉCNICA COMPLETA DOS SERVIDORES PÚBLICOS NA ÁREA DE RECURSOS HUMANOS (DEPARTAMENTO PESSOAL) E NA EXECUÇÃO DO E-SOCIAL E DCTFWEB JUNTO AO DEPARTAMENTO DE PESSOAL, VISANDO CORRIGIR TODAS AS DEFICIÊNCIAS E REGULARIZAR OS LANÇAMENTOS, CUMPRINDO OS PRAZOS LEGAIS PREVISTOS. | J29: 06 meses | L29: 05/02/24 A 05/08/25 | M29: 410/24 | N29: 1556/24 | O29: 2024000000223 | P29: 2025000000069 | Q29: PE 19/2024 | R29: 162000 | S29: 45693 | T29: 45728 | U29: DIMINUIÇÃO DE 10% DO VALOR INICIAL DO CONTRATO
A30: 45868 | B30: 06/21 | C30: 5º Aditivo | D30: PEDRO LUIS DE OLIVEIRA CPF - 379.169.808-78 GILDETE PEREIRA DE OLIVEIRA CPF - 839.070.418-87 | E30: SEGURANÇA URBANA, TRANSITO E DEFESA CIVIL | F30: Izaias Fernandes CPF: 155.257.828-39 | G30: Elias de Lima Meneses CPF: 304.013.528-70 | H30: Fabiano Gomes Duarte CPF: 365.558.428-81 | I30: LOCAÇÃO DE IMÓVEL LOCALIZADO NA AV. JEAN LIEUTAUD, 309 -TÉRREO, 1º E 2º PAVIMENTO - JD. SANTA TEREZA - RGS/SP, ONDE SERÁ INSTALADO A SECRETARIA DE SEGURANÇA URBANA, TRANSITO E DEFESA CIVIL E A GUARDA MUNICIPAL | J30: 6 MESES | L30: 30/01/25 à 30/07/25 | M30: 197/2021 | N30: 698/2021 | O30: 2021000000097 | P30: AJUSTE 2022000000056 4 ADITIVO 2025000000003 5 ADITIVO 2025000000012 | Q30: DP 06/21 | R30: 48000 | S30: 45687 | T30: 45694
A31: 45864 | B31: 29/23 | C31: 1º Aditivo | D31: ROCHA E MACHADO SOCIEDADE DE ADVOGADOS CNPJ - 19.851.544/0001-95 | E31: JURÍDICO | F31: Fábio Nunes Fernandes | G31: Elaine de Souza Pereira | H31: Jairson Virginio dos Santos | I31: CONTRATAÇÃO DE EMPRESA ESPECIALIZADA PARA PRESTAÇÃO DE SERVIÇOS ADVOCATÍCIOS DESTINADOS À ASSESSORIA JURÍDICA, BEM COMO DEFESA TÉCNICA DA PREFEITURA DO MUNICÍPIO DE RIO GRANDE DA SERRA NOS PROCESSOS E PROCEDIMENTOS EM TRÂMITE NO EGRÉGIO TRIBUNAL DE CONTAS DO ESTADO DE SÃO PAULO, INCLUINDO O ACOMPANHAMENTO DOS PROCEDIMENTOS ATÉ SEU TRÂNSITO EM JULGADO | J31: 12 MESES | L31: 26/07/24 a 26/07/25 | M31: 493/23 | N31: 1514/23 | O31: 2023000000095 | P31: 1º ADITIVO 2024000000029 AJUSTE 2023000000338 | Q31: CV 06/23 | R31: 170388 | S31: 45133 | T31: 45139
A32: 45857 | B32: 28/23 | C32: 1º Termo Aditivo | D32: PRESCON INFORMÁTICA E ASSESSORIA LTDA CNPJ - 01.221.551/0001-48 | E32: ADMINISTRAÇÃO E FINANÇAS | F32: ALEXSANDRA SILVA AGUIAR E CÁSSIO ROBERTO DE SOUZA PEGORARO | G32: ISRAEL DA SILVA JUNIOR | H32: Sistema de Contabilidade, Orçamento Público e Tesouraria: WILLIAN | I32: CONTRATAÇÃO DE EMPRESA ESPECIALIZADA NA PRESTAÇÃO DE SERVIÇOS DE INFORMÁTICA, PARA O FORNECIMENTO DE LICENÇA DE SOLUÇÃO TECNOLOGICA DE GESTÃO, CONTEMPLANDO OS SERVIÇOS DE IMPLANTAÇÃO (MIGRAÇÃO DE DADOS, CUSTOMIZAÇÃO, TREINAMENTO E CAPACITAÇÃO DE USUARIOS), MANUTENÇÃO (PREVENTIVA, CORRETIVA E DE ORDEM LEGAL) E SUPORTE TÉCNICO. | J32: 24 MESES | K32: 19/07/23 a 19/07/25 | L32: 1364/22 | M32: 1601/23 | N32: 2023000000102 | O32: 2023000000357 | P32: PP 04/23 | Q32: 361000 | R32: 45471 | S32: 45140 | T32: VIGENCIA A PARTIR DA ORDEM DE SERVIÇO OCORRIDA EM 22/08/2023
H33: Sistema de Gestão de Pessoal – RH Sistema de Medicina do Trabalho Sistema de Segurança no Trabalho Sistema de Ponto Eletrônico: IASMIN | M33: 1602/23 | Q33: 193800
H34: Sistema de Administração do Patrimônio Sistema de Administração de Almoxarifados Sistema de Controle de Frota: EDUARDO | M34: 1603/23 | Q34: 142500
H35: Sistema de Administração de Compras, Licitações e Contratos: ISRAEL DA SILVA JUNIOR | M35: 1604/23 | Q35: 486200
H36: Sistema de Administração de Cemitério: Adriana Barbosa da Silva | M36: 1608/23 | Q36: 33250
H37: Sistema de Protocolo e Controle de Processos Administrativos: CARLOS | M37: 1609/23 | Q37: 47500
H38: Sistema Controle de Obras: LEILA | M38: 1582/23 | Q38: 47500
H39: Jurídico Web: Rodrigo Limettre Moreno | M39: 1266/24 | Q39: 60000
H40: Sistema de Controle Interno Portal da Transparência Lei de Acesso a Informação Sistema de Tratamento de Informações Gerenciais (Business Intelligence): EMILY CAMILA DA SILVA SANTOS | M40: 1599/23 | Q40: 128250
Q41: =SUM(Q32:Q40) -> 1500000
A42: 45851 | B42: 23/25 | C42: Contrato | D42: NEXT PRODUÇÃO E EVENTOS LTDA CNPJ/MF sob o nº 54.536.761/0001-91 | E42: DESENVOLVIMENTO ECONÔMICO | F42: ANDRÉ MARTINS CAPARROZ | G42: Suzana Lopes Quintão Silva | H42: Cristopher Ferraz de Araújo | I42: CONTRATAÇÃO DE ARTISTAS PARA SE APRESENTAREM NO 17º FESTIVAL DO CAMBUCI 2025 | J42: 30 DIAS | K42: 13/06/2025 A 13/07/2025 | L42: 1124/2025 | N42: NÃO SE APLICA | O42: NÃO SE APLICA | P42: INEX 14/25 | Q42: 2500 | R42: 45821 | S42: 45845
A43: 45851 | B43: 21/25 | C43: Contrato | D43: EDNA LEITE ALVES FEITOSA 27231460810 | E43: DESENVOLVIMENTO ECONÔMICO | F43: ANDRÉ MARTINS CAPARROZ | G43: Suzana Lopes Quintão Silva | H43: Cristopher Ferraz de Araújo | I43: CONTRATAÇÃO DE ARTISTAS PARA SE APRESENTAREM NO 17º FESTIVAL DO CAMBUCI 2025 | J43: 30 DIAS | K43: 13/06/2025 A 13/07/2025 | L43: 1124/2025 | N43: NÃO SE APLICA | O43: NÃO SE APLICA | P43: INEX 14/25 | Q43: 2500 | R43: 45821 | S43: 45831
A44: 45851 | B44: 22/25 | C44: Contrato | D44: JULIANA APARECIDA ROSA DA SILVA 35113360821 | E44: DESENVOLVIMENTO ECONÔMICO | F44: ANDRÉ MARTINS CAPARROZ | G44: Suzana Lopes Quintão Silva | H44: Cristopher Ferraz de Araújo | I44: CONTRATAÇÃO DE ARTISTAS PARA SE APRESENTAREM NO 17º FESTIVAL DO CAMBUCI 2025 | J44: 30 DIAS | K44: 13/06/2025 A 13/07/2025 | L44: 1124/2025 | N44: NÃO SE APLICA | O44: NÃO SE APLICA | P44: INEX 14/25 | Q44: 1000 | R44: 45821 | S44: 45831
A45: 45851 | B45: 24/25 | C45: Contrato | D45: PULSAR X LTDA | E45: DESENVOLVIMENTO ECONÔMICO | F45: ANDRÉ MARTINS CAPARROZ | G45: Suzana Lopes Quintão Silva | H45: Cristopher Ferraz de Araújo | I45: CONTRATAÇÃO DE ARTISTAS PARA SE APRESENTAREM NO 17º FESTIVAL DO CAMBUCI 2025 | J45: 30 DIAS | K45: 13/06/2025 A 13/07/2025 | L45: 1124/2025 | N45: NÃO SE APLICA | O45: NÃO SE APLICA | P45: INEX 14/25 | Q45: 2500 | R45: 45821 | S45: 45831
A46: 45851 | B46: 25/25 | C46: Contrato | D46: 25.182.192 GIVALDO LOURENCO DAVIO FILHO | E46: DESENVOLVIMENTO ECONÔMICO | F46: ANDRÉ MARTINS CAPARROZ | G46: Suzana Lopes Quintão Silva | H46: Cristopher Ferraz de Araújo | I46: CONTRATAÇÃO DE ARTISTAS PARA SE APRESENTAREM NO 17º FESTIVAL DO CAMBUCI 2025 | J46: 30 DIAS | K46: 13/06/2025 A 13/07/2025 | L46: 1124/2025 | N46: NÃO SE APLICA | O46: NÃO SE APLICA | P46: INEX 14/25 | Q46: 2500 | R46: 45821 | S46: 45831
A47: 45851 | B47: 26/25 | C47: Contrato | D47: 33.818.222 FAGNER OLIVEIRA SILVA | E47: DESENVOLVIMENTO ECONÔMICO | F47: ANDRÉ MARTINS CAPARROZ | G47: Suzana Lopes Quintão Silva | H47: Cristopher Ferraz de Araújo | I47: CONTRATAÇÃO DE ARTISTAS PARA SE APRESENTAREM NO 17º FESTIVAL DO CAMBUCI 2025 | J47: 30 DIAS | K47: 13/06/2025 A 13/07/2025 | L47: 1124/2025 | N47: NÃO SE APLICA | O47: NÃO SE APLICA | P47: INEX 14/25 | Q47: 2500 | R47: 45821 | S47: 45831
A48: 45851 | B48: 27/25 | C48: Contrato | D48: 52.767.739 ELIEZER GONCALVES | E48: DESENVOLVIMENTO ECONÔMICO | F48: ANDRÉ MARTINS CAPARROZ | G48: Suzana Lopes Quintão Silva | H48: Cristopher Ferraz de Araújo | I48: CONTRATAÇÃO DE ARTISTAS PARA SE APRESENTAREM NO 17º FESTIVAL DO CAMBUCI 2025 | J48: 30 DIAS | K48: 13/06/2025 A 13/07/2025 | L48: 1124/2025 | N48: NÃO SE APLICA | O48: NÃO SE APLICA | P48: INEX 14/25 | Q48: 2500 | R48: 45821 | S48: 45831
A49: 45851 | B49: 28/25 | C49: Contrato | D49: 55.415.394 WESLEY BARBOSA QUEIROZ | E49: DESENVOLVIMENTO ECONÔMICO | F49: ANDRÉ MARTINS CAPARROZ | G49: Suzana Lopes Quintão Silva | H49: Cristopher Ferraz de Araújo | I49: CONTRATAÇÃO DE ARTISTAS PARA SE APRESENTAREM NO 17º FESTIVAL DO CAMBUCI 2025 | J49: 30 DIAS | K49: 13/06/2025 A 13/07/2025 | L49: 1124/2025 | N49: NÃO SE APLICA | O49: NÃO SE APLICA | P49: INEX 14/25 | Q49: 2500 | R49: 45821 | S49: 45831
A50: 45828 | B50: 13/22 | C50: 3º Aditivo | D50: GRIFON DIGITAL SERVIÇOS LTDA CNPJ - 21.129.497/0001-12 | E50: JURÍDICO | F50: Fábio Nunes Fernandes | G50: Elaine de Souza Pereira | H50: Jairson Virginio dos Santos | I50: CONTRATAÇÃO DE EMPRESA ESPECIALIZADA EM RECORTES ELETRÔNICOS DOS CADERNOS DO PODER EXECUTIVO E LEGISLATIVO. | J50: 12 meses | K50: 20/06/24 A 20/06/25 | L50: 277/22 | M50: 1358/22 | N50: LICITAÇÃO 202200000074 | O50: AJUSTE 2022000000206 2º ADITIVO 2023000000024 | P50: DP 04/22 | Q50: 1510.68 | R50: 45455 | S50: 45253
A51: 45813 | B51: 16/23 | D51: SAGS FACILITIES SERVIÇOS EMPRESARIAIS LTDA CNPJ - 18.465.479/0001-05 | E51: ADMINISTRAÇÃO | F51: ALEXSANDRA SILVA AGUIAR | G51: Debiran | H51: João Carlos | I51: CONTRATAÇÃO DE EMPRESA ESPECIALIZADA NA PRESTAÇÃO DE SERVIÇOS DE GUARDA E CUSTÓDIA SEGURA PARA O ACERVO DOCUMENTAL DA PREFEITURA DE RIO GRANDE DA SERRA | J51: 12 MESES | K51: 05/06/24 A 05/06/25 | L51: 2072/22 | M51: 1097/23 | P51: CV 02/23 | Q51: 70744.32 | R51: 45448 | S51: 45089
A52: 45804 | B52: 26/24 | C52: Contrato | D52: AAHBRANT ENGENHARIA E CONSTRUÇÕES LTDA CNPJ: 23.837.456/0001-06 | E52: OBRAS | F52: Leandro Dias Florencio | G52: Leila Andreassi de Castro | H52: Gislene Stephanelli | I52: CONTRATAÇÃO DE EMPRESA ESPECIALIZADA PARA EXECUÇÃO DE OBRAS DE CONTENÇÃO DO TALUDE SITUADO NA AVENIDA JOSÉ BELLO NO MUNICÍPIO DE RIO GRANDE DA SERRA | J52: 300 dias | K52: 31/07/2024 A 27/05/2025 | L52: 1980/23 | M52: 1378/24 | N52: 2024000000205 | O52: AJUSTE 2024000000419 | P52: CO 17/23 | Q52: 1237268.2 | R52: 45478
A53: 45803 | B53: 16/24 | C53: Contrato | D53: LLIÈGE SERVIÇOS E SISTEMAS ESPECIALIZADOS LTDA CNPJ - 01.058.305/0001-17 | E53: CIDADANIA | F53: Ricardo Tadeu Caires Silva | G53: Eliza Aparecida Camine Almeida | H53: Fernanda Stachowski | I53: CONTRATAÇÃO DE SERVIÇOS E SOLUÇÃO TECNOLÓGICA, POR MEIO DE PLATAFORMA (SOFTWARE) PARA ATENDIMENTO AOS PROGRAMAS SOCIAIS DO MUNICÍPIO DE RIO GRANDE DA SERRA, INCLUINDO O LICENCIAMENTO DA SOLUÇÃO, UNIFICAÇÃO DE CADASTROS DE PROGRAMAS MUNICIPAIS, APONTAMENTO GEOGRÁFICO DE PROGRAMAS E FAMÍLIAS CONTEMPLANDO A ENTREGA FINAL EM PORTAL CORPORATIVO DE GESTÃO SOCIAL, CONTEMPLANDO TODA A IMPLANTAÇÃO, MIGRAÇÃO DE DADOS, PARAMETRIZAÇÃO, TREINAMENTO, ATUALIZAÇÕES LEGAIS, SUPORTE TÉCNICO E POSSÍVEIS INTEGRAÇÕES DE DADOS ORIUNDOS DOS DEMAIS SISTEMAS EXISTENTES NO MUNICÍPIO | J53: 12 meses a partir da OS | K53: 25/04/24 a 25/04/25 | L53: 1358/23 | M53: 893/24 | N53: 2024000000165 | O53: 2024000000243 | P53: PP 61/23 | Q53: 83000 | R53: 45407 | S53: 45421
A54: 45762 | B54: 45717 | C54: Contrato | D54: ASSOCIAÇÃO VIVA BEM A IDADE QUE TEM CNPJ - 03.289.502/0001-72 | E54: CIDADANIA | F54: ELZA DOS ANJOS IWASAKI CPF: 124.538.988-25 | G54: EMILY CAMILA DA SILVA SANTOS CPF: 401.799.849-88 | H54: FERNANDA STACHOWSKI CPF: 336.725.538-67 | I54: CONTRATAÇÃO DE 01(UMA) VAGA DE INSTITUIÇÃO DE LONGA PERMANÊNCIA PARA IDOSOS (ILPI), CONFORME OFÍCIO Nº 19/2025, REFERENTE À NOTÍCIA DE FATO Nº 2/2025 DO MINISTÉRIO PÚBLICO DO ESTADO DE SÃO PAULO, PELO PERÍODO DE 12 (DOZE) MESES OU ENQUANTO PERDURAR A NECESSIDADE, CONFORME CONDIÇÕES EXIGIDAS ESTABELECIDAS NO TERMO DE REFERÊNCIA | J54: 12 MESES | K54: 06/03/25 A 06/03/26 | L54: 179/25 | M54: 409/25 | N54: 2025000000125 | O54: AJUSTE/EXECUÇÃO (RESCINDIDO) 2025000000239 | P54: DP 01/25 | Q54: R$ 39.600,00 | R54: 45722 | S54: 45726 | T54: IDOSO FALECEU 26/02/2025. CONTRATO RESCINDIDO 15/04/2025
A55: 45691 | B55: 04/23 | C55: Contrato | D55: INSTITUTO MAIS DE GESTÃO E DESENVOLVIMENTO SOCIAL - IMAIS CNPJ - 08.179.183/0001-66 | E55: ADMINISTRAÇÃO | F55: Alexsandra Silva Aguiar | G55: Suzana Lopes Quintão Silva CPF: 277.740.328-78 | H55: COMISSÃO FISCALIZADORA DO CONCURSO PÚBLICO E/OU PROCESSO SELETIVO - PORTARIA | I55: PRESTAÇÃO DE SERVIÇOS TÉCNICOS ESPECIALIZADOS DE PLANEJAMENTO, ORGANIZAÇÃO E EXECUÇÃO DE CONCURSOS PÚBLICOS E/OU PROCESSOS SELETIVOS, DESTINADO AO PROVIMENTO DE VAGAS EM SEU QUADRO DE PESSOAL DA PREFEITURA MUNICIPAL DE RIO GRANDE DA SERRA | J55: 12 MESES | K55: 03/02/23 A 03/02/24 | L55: 2438/22 | M55: 284/23 | N55: NÃO OBRIGATÓRIO | O55: NÃO OBRIGATÓRIO | P55: DP 7/23 | Q55: 0 | R55: 44960 | S55: 44964
C56: 1º Aditivo | F56: Alexsandra Silva Aguiar | G56: Suzana Lopes Quintão Silva CPF: 277.740.328-78 | H56: COMISSÃO FISCALIZADORA DO CONCURSO PÚBLICO E/OU PROCESSO SELETIVO - PORTARIA | K56: 03/02/24 A 03/02/25 | N56: NÃO OBRIGATÓRIO | O56: NÃO OBRIGATÓRIO | R56: 45325 | S56: 45370
A57: 45681 | B57: 13/23 | C57: 2º Aditivo | D57: INTERTEC SOLUÇÕES EM SOFTWARE LDTA EPP CNPJ - 18.351.823/0001-27 | E57: COMUNICAÇÃO | F57: JULIANA CARLA RODRIGUES MENDES CPF: 316.472.928-67 | G57: Juciane da Penha Silva CPF: 408.737.788-12 | H57: Ualisson Henrique de Oliveira Monteiro CPF: 425.454.448-92 | I57: CONTRATAÇÃO DE PESSOA JURÍDICA ESPECIALIZADA NA PRESTAÇÃO DE SERVIÇOS DE INFORMÁTICA, QUE REALIZE A ATUALIZAÇÃO, CUSTOMIZAÇÃO E MANUTENÇÃO DO SITE DA PREFEITURA MUNICIPAL DE RIO GRANDE DA SERRA COM HOSPEDAGEM E SUPORTE TÉCNICO DA PÁGINA E DOS E-MAILS VINCULADOS AO SITE PELO PERÍODO DE 06 MESES, SENDO PAGOS MENSALMENTE | J57: 06 MESES | K57: 24/07/24 a 24/01/25 | L57: 86/2023 | M57: 335/2024 | N57: 2023000000091 | O57: 2023000000335 2º ADITIVO 2024000000030 | P57: DP 11/23 | Q57: 8400 | R57: 45497 | S57: 45337
A58: 45676 | B58: 40/24 | C58: Contrato | D58: EXPRESSO AUTO BUS TRANSPORTES LTDA CNPJ - 13.240.751/0001-27 | E58: ESPORTE | F58: RODRIGO FERNANDES OLIVARES | G58: RODRIGO FERNANDES OLIVARES | H58: ENIO DA FRAGA PIRES | I58: CONTRATAÇÃO DE EMPRESA ESPECIALIZADA EM PRESTAÇÃO DE SERVIÇO DE LOCAÇÃO DE ONIBUS E VAN, EM CARATER EMERGENCIAL, PARA ATENDER AS NECESSIDADES DA SECRETARIA MUNICIPAL DA JUVENTUDE, ESPORTE E LAZER, COM FORNECIMENTO DE COMBUSTÍVEL, PNEUS, MANUTENÇÕES, MOTORISTAS E TRIPULANTES | J58: 04 MESES | K58: 19/09/2024 A 19/01/2025 | L58: 1706/2024 | M58: - - - | N58: 2024000000251 | O58: 2024000000561 | P58: DP 47/24 | Q58: 272000 | R58: 45554
A59: 45661 | B59: 25/24 | C59: Contrato | D59: VENTISOL NORDESTE INDUSTRIA E COMERCIO DE VENTILADORES LTDA CNPJ: 08.934.225/0001-27 | E59: EDUCAÇÃO | F59: Alessandra Amora Barchini | G59: Alessandra Amora Barchini | H59: Alessandra Amora Barchini | I59: PROCESSO ADMINISTRATIVO N° 979/2024 - AQUISIÇÃO DE VENTILADORES PARA ATENDER A SECRETARIA DE EDUCAÇÃO E CULTURA, ATRAVÉS DE ADESÃO DA ATA DE REGISTRO DE PREÇOS N° 1/2024 FNDE/MEC - PREGÃO ELETRÔNICO N° 14/2023 - PROCESSO ADMINISTRATIVO N° 23034.018062/2023-81 - PROCESSO N° 23034.012537/2024-14 - ORGÃO PARTICIPANTE SIGARP N° 99127 | J59: 180 DIAS | K59: 04/07/2024 A 04/01/2025 | L59: 979/2024 | M59: 979/2024 | N59: 2024000000005 | O59: 2024000000036 | P59: PE 14/2023 - FNDE | Q59: 14004 | R59: 45477 | S59: 45202 | T59: VIGENCIA A PARTIR DA ORDEM DE INICIO
A60: 45657 | B60: 44/24 | C60: Contrato | D60: CAM COMÉRCIO E INDÚSTRIA LTDA CNPJ - 34.301.930/0001-05 | E60: ESPORTE | F60: Rodrigo Fernandes Olivares | G60: Rodrigo Fernandes Olivares | H60: Enio da Fraga Pires | I60: CONTRATAÇÃO DE EMPRESA ESPECIALIZADA PARA O FORNECIMENTO E INSTALAÇÃO DE REDE DE PROTEÇÃO PARA QUADRA POLIESPORTIVA DO GINÁSIO MUNICIPAL, DESTINADOS A SECRETARIA DA JUVENTUDE, ESPORTE E LAZER, NO MUNICIPIO DE RIO GRANDE DA SERRA | J60: 3 MESES | L60: 20/09/2024 A 31/12/2024 | M60: 1525/2024 | N60: - - - | O60: 2024000000248 | P60: AJUSTE 2024000000577 | Q60: DP 26/24 | R60: 10147.2 | S60: 45555
A61: 45657 | B61: 04/21 | C61: 2º Aditivo | D61: DOM PEDRITO PARTICIPAÇÕES E EMPREENDIMENTOS IMOBILIARIOS LTDA ME CNPJ - 20.591.702/0001-02 | E61: EDUCAÇÃO E CULTURA | F61: Charles David Faustino Fumagalli | G61: Charles David Faustino Fumagalli | H61: Luana | I61: LOCAÇÃO DE IMÓVEL SITO A AV. DOM PEDRO I, 487 - CENTRO - RIO GRANDE DA SERRA/SP, ONDE ESTÁ INSTALADO A SECRETARIA DE EDUCAÇÃO, BIBLIOTECA E O PROJETO ROBÓTICA | J61: 21 MESES | K61: *** | L61: 12/03/23 À 31/12/24 | M61: 406/19 | N61: 406/19 | Q61: DP 04/21 | R61: 385200 | S61: 44267 | T61: 45021
A62: 45640 | B62: 35/24 | C62: Contrato | D62: SCS ENGENHARIA REFRIGERAÇÃO E CLIMATIZAÇÃO LTDA CNPJ - 24.306.420/0001-69 | E62: FINANÇAS | F62: Cássio Roberto de Souza Pegoraro | G62: Edmir Francisco da Silva | H62: Rosiclei de Lima Meneses | I62: Contratação de empresa especializada em fornecimento e instalação de aparelhos de ar condicionado | J62: 60 dias | K62: 45579 | L62: 45640 | M62: 902/24 | N62: - - - | O62: 2024000000238 | P62: AJUSTE 2024000000554 AJUSTE 2024000000597 | Q62: DP 43/24 | R62: 59980 | S62: 45553
A63: 45618 | B63: 27/22 | C63: Contrato | D63: MARIA CAPARROZ SANTINELLI CPF - 069.120.308-31 | E63: ESPORTE | G63: RODRIGO FERNANDES OLIVARES | H63: GLAUCIR DA COSTA PEREIRA | I63: LOCAÇÃO DE IMÓVEL LOCALIZADO NA RUA JOSÉ MARIA FIGUEIREDO, 53, CENTRO, RIO GRANDE DA SERRA/SP, PARA INSTALAÇÃO DO PROJETO DE ARTES MARCIAIS FAZER VALER | K63: 22/11/2023 A 22/11/2024 | L63: 1968/22 | M63: 2410/22 | N63: LICITACAO 2022000000119 | O63: AJUSTE 2022000000395 ADITIVO 2023000000025 | P63: DISPENSA 31/22 | Q63: 48000 | R63: 44887 | S63: 45264
A64: 45609 | B64: 34/23 | C64: 2º Aditivo | D64: RENOV PAVIMENTAÇÃO E CONSTRUÇÕES LTDA - EPP CNPJ - 10.277.133/0001-63 | E64: OBRAS | F64: Leandro | G64: Leandro | H64: Leandro | I64: CONTRATAÇÃO DE EMPRESA PARA EXECUÇÃO DE PAVIMENTAÇÃO ASFÁLTICA, DRENAGEM E SINALIZAÇÃO VIÁRIA: JARDIM SANTA TEREZA NO MUNICÍPIO DE RIO GRANDE DA SERRA | J64: 450 DIAS | L64: 21/08/23 a 13/11/24 | M64: 1169/22 | N64: 1679/23 | O64: 2023000000097 | P64: 2023000000342 2º ADITIVO 2024000000034 | Q64: CO 10/23 | R64: 4003199.5 | S64: 45474 | T64: 45160
A65: 45606 | B65: 37/24 | C65: Contrato | D65: EVIRTUAL COMPUTACAO LTDA CNPJ - 10.530.398/0001-21 | E65: GOVERNO | F65: LUIS | G65: LUIS | H65: ERIKA | I65: CONTRATAÇÃO DE CONSULTORIA ESPECIALIZADA PARA A ELABORAÇÃO DOS ESTUDOS TECNICOS NECESSÁRIOS PARA A INSTITUIÇÃO E DELEGAÇÃO DO SERVIÇO PÚBLICO LOTÉRICO MUNICIPAL | J65: 45 DIAS APÓS PUBLICAÇÃO | L65: 26/09/24 A 10/11/24 | M65: 1268/24 | N65: - | O65: 2024000000247 | P65: 2024000000555 | Q65: CD 44/24 | R65: 57300 | S65: 45551
A66: 45601 | B66: 17/23 | C66: Contrato | D66: REISCON CONSTRUTORA E TERRAPLANAGEM EIRELI CNPJ - 16.804.449/0001-42 | E66: OBRAS | F66: Priscila Ulian de Oliveira | G66: Wilson de Souza | H66: Priscila Ulian de Oliveira | I66: CONTRATAÇÃO DE EMPRESA ESPECIALIZADA PARA EXECUÇÃO DE OBRAS DE PAVIMENTAÇÃO E DRENAGEM NO CEMITÉRIO SÃO SEBASTIÃO – BAIRRO JARDIM SANTA TEREZA | J66: 455 DIAS DA ORDEM DE SERVIÇO | K66: OS 08/08/2023 | L66: 08/08/2023 À 05/11/2024 | M66: 2091/22 | N66: 1207/23 | O66: 2023000000073 | P66: 2023000000283 | Q66: CO 03/23 | R66: 1299310.8 | S66: 45093 | T66: 45098
C67: 1º Aditivo | F67: Kléber Avelino de Oliveira | H67: Kléber Avelino de Oliveira | P67: 2024000000003 | R67: 1398349.9 | S67: 45341 | T67: 45350
A68: 45595 | B68: 44/23 | C68: Contrato | D68: BYE INSECT CONTROLADORA DE PRAGAS S/S LTDA CNPJ - 02.936.838/0001-17 | E68: CIDADANIA | F68: SANDRO | G68: SANDRO | H68: Fernanda | I68: CONTRATAÇÃO DE EMPRESA PARA PRESTAÇÃO DE SERVIÇOS DE DEDETIZAÇÃO E DESRATIZAÇÃO, SENDO 02 (DUAS) APLICAÇÕES COM INTERVALO DE 06 (SEIS) MESES, COM O EFETIVO CONTROLE DE PRAGAS, DAS ÁREAS INTERNAS E EXTERNAS DAS UNIDADES: CRAS, CREAS, ACOLHIMENTO INSTITUCIONAL, CONSELHO TUTELAR E DA SEDE DA SECRETARIA DE CIDADANIA | J68: 12 MESES | L68: 30/10/23 A 30/10/24 | M68: 1790/23 | N68: 2197/23 | O68: - | P68: - | Q68: DP N° 20/23 | R68: 4760 | S68: 45229 | T68: 45243 | U68: SEM ORDEM DE INÍCIO
A69: 45553 | B69: 27/24 | C69: Contrato | D69: GIOVANNI ALVES BORGES E SILVA 87059142134 PILULAS DO ECA CNPJ - 29.735.562-0001-65 | E69: CIDADANIA | F69: Ricardo | G69: Laucimar Pereira da Silva | H69: Lilian Carvalho Pezzo | I69: CONTRATAÇÃO DE EMPRESA PARA REALIZAÇÃO DE CAPACITAÇÃO PROFISSIONAIS NA MODALIDADE PRESENCIAL PARA FUNCIONÁRIOS DO SAICA E TÉCNICOS DE REDE SOCIOASSITENCIAL COM OBJETIVO DE APRIMORAMENTO NO ATENDIMENTO | J69: 30 dias | L69: 18/08/24 A 18/09/24 | M69: 2467/23 | N69: - | O69: 2024000000212 | P69: 2024000000402 1º ADITIVO 2024000000036 | Q69: DP 22/24 | R69: 34870 | S69: 45516
A70: 45525 | B70: 21/23 | C70: 2º Aditivo | D70: VIAPRECISA TERRAPLENAGEM E PAVIMENTAÇÃO LTDA CNPJ - 31.133.672/0001-07 | E70: OBRAS | F70: Leandro Dias Florencio | G70: Leila Andreassi de Castro | H70: Lourdes de Campos | I70: CONTRATAÇÃO DE EMPRESA ESPECIALIZADA NA ÁREA DE ENGENHARIA E ARQUITETURA PARA CONTINUAÇÃO DA CONSTRUÇÃO DO TERMINAL RODOVIÁRIO DO MUNICÍPIO DE RIO GRANDE DA SERRA | J70: 210 DIAS | K70: 45106 | L70: 24/01/2024 À 21/08/2024 | M70: 2183/22 | N70: 1216/23 | O70: 2023000000075 | P70: 2023000000290 | Q70: CO 07/23 | R70: 1222854.8 | S70: 45456 | T70: 45328
A71: 45514 | B71: 02/21 | C71: 3º Aditivo | D71: MARIO HIROSHI ISHIHARA CPF - 155.330.198-63 | E71: JURÍDICO | G71: Richard | H71: Richard | I71: LOCAÇÃO DE IMÓVEL SITO A RUA AGOSTINHO CARDOSO, 176 - VILA FIGUEIREDO - RIO GRANDE DA SERRA/SP, ONDE ESTÁ INSTALADO FORO DISTRITAL DE RIO GRANDE DA SERRA | J71: 12 meses | L71: 01/03/23 À 01/03/24 | M71: 588/17 | N71: 231/24 | O71: 2023000000023 | P71: 2023000000124 | Q71: DP 02/21 | R71: 86776.08 | S71: 44256 | T71: 44998
B72: 02/21 | C72: 4º Aditivo | F72: JONATHAN | G72: SANDRA REGINA | H72: RAFAELLA | J72: 12 meses | L72: 01/03/24 a 01/03/25 | P72: 2024000000017 | R72: 90786.12 | S72: 45352 | T72: 45365
A73: 45508 | B73: 20/24 | C73: 1º Aditivo | D73: METALURGICA COMERCIAL NAVBAN – COMÉRCIO E PRESTAÇÃO DE SERVIÇOS LTDA CNPJ - 43.540.241/0001-36 | E73: OBRAS | F73: LEANDRO DIAS FLORENCIO | G73: Leila Andreassi de Castro | H73: Adriano de Sousa Pereira | I73: CONTRATAÇÃO DE EMPRESA ESPECIALIZADA EM SERVIÇOS DE ESTRUTURA PRÉ-MOLDADAS DE CONCRETO E COM COBERTURA EM TELHA EM AÇO GALVANIZADO COMPREENDENDO O FORNECIMENTO DE MATERIAL E MÃO DE OBRA, DESTINADAS PARA A CONSTRUÇÃO DO TERMINAL RODOVIÁRIO MUNICIPAL DE RIO GRANDE DA SERRA | J73: 30 dias | K73: 45446 | L73: 04/07/24 A 04/08/24 | M73: 386/24 | N73: 975/24 | O73: 2024000000178 | P73: 2024000000376 1º ADITIVO 2024000000027 | Q73: CO 01/24 | R73: 583954.55 | S73: 45477 | T73: 45433
A74: 45506 | B74: 22/23 | C74: 1º Aditivo | D74: REISCON CONSTRUTORA E TERRAPLANAGEM EIRELI CNPJ - 16.804.449/0001-42 | E74: OBRAS | F74: Luis Fernando Pinotti Silva | G74: Luis Fernando Pinotti Silva | H74: Priscila Ulian de Oliveira | I74: CONTRATAÇÃO DE EMPRESA ESPECIALIZADA PARA REFORMA DA UNIDADE BÁSICA DE SAÚDE DO PARQUE AMÉRICA NO MUNICÍPIO DE RIO GRANDE DA SERRA | J74: 60 DIAS | L74: 05/01/24 A 05/03/24 | M74: 1643/21 | N74: 1402/23 | Q74: CO 05/23 | R74: 298724.04 | S74: 45127 | T74: 45259 | U74: ORDEM DE INÍCIO 08/08/23
C75: 2º Aditivo | F75: Luis Fernando Pinotti Silva | G75: Luis Fernando Pinotti Silva | H75: KEBER AVELINO DE OLIVEIRA | J75: 150 DIAS | L75: 05/03/24 A 02/08/24 | P75: 2023000000312 2º ADITIVO 2024000000019 | T75: 45369
A76: 45487 | B76: 07/24 | C76: Contrato | D76: LDL COMERCIAL EIRELI CNPJ - 23.284.551/0001-20 | E76: OBRAS | F76: LEANDRO DIAS FLORENCIO | G76: Willian Santos Faria | H76: Kléber Avelino de Oliveira | I76: CONTRATAÇÃO DE EMPRESA PARA SERVIÇOS DE ADEQUAÇÃO DO ESPAÇO PARA MUDANÇA DE USO – SALA DE AUDIOVISUAL NA EMEB PROFª RAQUEL SILVEIRA MONTEIRO – RUA JOSÉ MARIA DE FIGUEIREDO, CENTRO – RIO GRANDE DA SERRA-SP | J76: 90 DIAS | K76: 45397 | L76: 15/04/24 A 14/07/24 | M76: 1744/23 | N76: 623/24 | O76: 2024000000175 | Q76: CV 09/23 | R76: 83211.23 | S76: 45378 | T76: 45385
A77: 45483 | B77: 08/24 | C77: Contrato | D77: GRASIL ENGENHARIA & ARQUITETURA LTDA CNPJ - 50.158.486/0001-69 | E77: OBRAS | F77: LEANDRO DIAS FLORENCIO | G77: Lamartine Dourado Cavalcante | H77: Kleber Avelino de Oliveira | I77: CONTRATAÇÃO DE EMPRESA PARA SERVIÇOS DE INSPEÇÃO PREDIAL E ELABORAÇÃO DO “LAUDO TÉCNICO DE ESTABILIDADE E SEGURANÇA – LTES”, AS BUILT E PROJETO PARA REFORÇO ESTRUTURAL NA ESCOLA MUNICIPAL DE ENSINO BÁSICO – EMEB PRIMEIRA DAMA ZULMIRA JARDIM TEIXEIRA | J77: 90 DIAS | K77: 45393 | L77: 11/04/24 A 10/07/24 | M77: 1177/23 | N77: 624/24 | O77: 2024000000377 | P77: 2024000000174 | Q77: CV 10/23 | R77: 88000 | S77: 45376 | T77: 45379
A78: 45352 | B78: 19/23 | C78: CONTRATO | D78: REISCON CONSTRUTORA E TERRAPLANAGEM EIRELI CNPJ - 16.804.449/0001-42 | E78: OBRAS | F78: Priscila Ulian de Oliveira CPF: 434.008.938-97 | G78: Luis Fernando Pinotti Silva CPF: 291.822.538-03 | H78: Priscila Ulian de Oliveira CPF: 434.008.938-97 | I78: CONTRATAÇÃO DE EMPRESA PARA EXECUÇÃO DE AMPLIAÇÃO DE UNIDADE BÁSICA DE SAÚDE DO CENTRO – UBS VEREADOR AVELINO VALÉRIO SOBRINHO NO MUNICÍPIO DE RIO GRANDE DA SERRA | J78: 180 dias | K78: 05/07/23 À 01/01/24 | L78: 1642/21 | M78: 1098/23 | N78: 2023000000068 | O78: 2023000000265 | P78: CO 04/23 | Q78: 297446.22 | R78: 45077 | S78: 45083 | T78: FOI PARA A EMPRESA ASSINAR E POSTERIOR PUBLICAÇÃO
C79: 1º Aditivo | F79: Priscila Ulian de Oliveira CPF: 434.008.938-97 | G79: Luis Fernando Pinotti Silva CPF: 291.822.538-03 | H79: Priscila Ulian de Oliveira CPF: 434.008.938-97 | J79: 60 dias | K79: 01/01/24 À 01/03/24 | O79: 2023000000026 | S79: 45083
A80: 45641 | B80: 18/20 | C80: 4º Aditivo | D80: MAGSI COMERCIO E PRESTAÇÃO DE SERVIÇOS DE LIMPEZA E CONSERVAÇÃO LTDA CNPJ - 19.630.021/0001-19 | E80: OBRAS | G80: Priscila Ulian de Oliveira | H80: Priscila Ulian de Oliveira | I80: CONTRATAÇÃO DE EMPRESA ESPECIALIZADA PARA PRESTAÇÃO DE SERVIÇOS DE OPERAÇÃO, MANUTENÇÃO CORRETIVA E PREVENTIVA, AMPLIAÇÃO E EFICIENTIZAÇÃO DO SISTEMA DE ILUMINAÇÃO PÚBLICA E SERVIÇOS DE GESTÃO INFORMATIZADA, TELEGESTÃO INTEGRADA NAS VIAS E AREAS PÚBLICAS URBANAS NO MUNICÍPO DE RGS | J80: 12 MESES | K80: 15/12/23 à 15/12/24 | L80: 2454/19 | M80: 1773/20 | N80: NÃO FOI LANÇADO NA AUDESP | P80: TP 03/20 | Q80: 1730983.2 | R80: 44147 | S80: 45274 | T80: ORDEM DE INÍCIO 15/12 RESCISÃO 10/05/24
A81: 45424 | B81: 08/21 | C81: 2º Aditivo | D81: HISAE KURASHIMA IDEHIRA (ADMINISTRADORA C&M INTERMEDIAÇÃO DE NEGÓCIOS LTDA) CNPJ nº 13.191.483/0001-09 | E81: DESENVOLVIMENTO | G81: KARINA | H81: KARINA | I81: LOCAÇÃO DE IMÓVEL SITO A RUA CARLOS JOSÉ CARLSON, 280 - CENTRO - RIO GRANDE DA SERRA/SP, ONDE ESTA INSTALADO A SECRETARIA DE DESENVOLVIMENTO ECONÔMICO E TURÍSTICO | K81: 12/05/23 A 12/05/24 | L81: 314/21 | M81: 758/21 | P81: DP 08/21 | Q81: =#REF!*12 -> #REF! | R81: 44328 | S81: 45072
A82: 45414 | B82: 02/23 | C82: 2º Aditivo | D82: OMASA SERVIÇOS INTELIGENTES LTDA CNPJ - 27.701.958/0001-66 | E82: EDUCAÇÃO E CULTURA | F82: Alessandra Amora Barchini | G82: LAMARTINE | H82: Paula Neves Bernardo Garcia | I82: CONTRATAÇÃO EMERGENCIAL DE EMPRESA ESPECIALIZADA NA PRESTAÇÃO DE SERVIÇOS DE LIMPEZA, CONSERVAÇÃO E HIGIENIZAÇÃO NAS UNIDADES ESCOLARES MUNICIPAIS, COM O FORNECIMENTO DE SANEANTES DOMISSANITÁRIOS, MATERIAIS, EQUIPAMENTOS E MÃO DE OBRA | J82: 3 MESES | K82: 02/02/24 a 02/05/24 | L82: 2355/22 | M82: 2355/22 | N82: 2023000000017 | O82: 2023000000109 | P82: DP 06/23 | Q82: 412731.93 | R82: 44963 | S82: 45366 | T82: ORDEM DE INICIO
A83: 45406 | B83: 26/17 | C83: 7º Aditivo | D83: GARLOC TRANSPORTES, LOGISTICA E LOCAÇÕES LTDA CNPJ - 69.205.789/0001-13 | E83: EDUCAÇÃO E CULTURA | G83: ARI INACIO DE SOUZA 308.320.978-96 | H83: PAULA NEVES BERNARDO GARCIA 163.539.478-36 | I83: CONTRATAÇÃO DE EMPRESA ESPECIALIZADA PARA PRESTAÇÃO DE SERVIÇOS DE LOCAÇÃO DE VEICULOS, COM MOTORISTA E FORNECIMENTO DE COMBUSTIVEL PARA TRANSPORTE ESCOLAR - SECRETARIA DE EDUCAÇÃO E CULTURA | K83: 24/04/23 À 24/04/24 | L83: 741/17 | M83: 2239/17 | N83: NÃO LANÇADO NO SISTEMA AUDESP | P83: PP 17/17 | Q83: 4052843.2 | R83: 43040 | S83: 45044 | T83: LIMITE CONTRATUAL ATINGIU O 60 MESES
A84: 45397 | B84: 03/23 | C84: Contrato | D84: VIAPRECISA TERRAPLENAGEM E PAVIMENTAÇÃO LTDA CNPJ - 31.133.672/0001-07 | E84: OBRAS | F84: Priscila Ulian de Oliveira | G84: Priscila Ulian de Oliveira | H84: Priscila Ulian de Oliveira | I84: CONTRATAÇÃO DE EMPRESA PARA EXECUÇÃO DE PASSEIO PÚBLICO – PROGRAMA CALÇADA ACESSÍVEL NO MUNICÍPIO DE RIO GRANDE DA SERRA | J84: 07 MESES | K84: 15/02/2023 a 15/09/2023 | L84: 1144/22 | M84: 330/23 | N84: 2023000000014 | O84: 2023000000105 | P84: CO 04/22 | Q84: 244285.46 | R84: 44970 | S84: 44971 | T84: ORDEM DE INICIO 15/02/2023
C85: 1º Aditivo | F85: Priscila Ulian de Oliveira | G85: Priscila Ulian de Oliveira | H85: Priscila Ulian de Oliveira | J85: 07 MESES | K85: 15/09/2023 a 15/04/2024 | O85: 2023000000021 | R85: 45184 | S85: 45202
A86: 45360 | B86: 02/20 | C86: 3º Aditivo | D86: JOÃO GILBERTO ORLANDO CPF - 007.112.518-35 | E86: SAÚDE | I86: LOCAÇÃO DE IMÓVEL SITO A RUA DOS SÁBIAS, 60 - VILA NIWA, ONDE ESTA INSTALADA A UNIDADE BASICA DE SAÚDE | K86: 09/03/23 a 09/03/24 | L86: 1517/19 | M86: 1517/19 | P86: DP 01/20 | Q86: 25361.88 | R86: 43899 | S86: 45008
B87: 02/18 | C87: 8º Aditivo | D87: LARA CENTRAL DE TRATAMENTO DE RESÍDUOS LTDA CNPJ - 57.543.001/0001-08 | E87: S. URBANOS | F87: Wilson de Souza | G87: Rawany Nathyely Souza Bedia | H87: Noely Mendes | I87: CONTRATAÇÃO DE EMPRESA ESPECIALIZADA EM SERVIÇOS DE COLETA E TRANSPORTE DE RESIDUOS DOMICILIARES, COMERCIAIS, SAUDE E LIMPEZA DE FEIRAS LIVRES | J87: 4 MESES | K87: 01/10/23 à 01/02/24 | L87: 1892/17 | M87: 383/18 | N87: 2018000189217 | P87: CO 03/17 | Q87: 510898.8 | R87: 43132 | S87: 45209 | T87: PRORROGAÇÃO JÁ NA EXCEPCIONALIDADE
Q88: 76042.4
Q89: =SUM(Q87:Q88) -> 586941.2
D90: PERALTA AMBIENTAL IMPORTAÇÃO E EXPORTAÇÃO LTDA CNPJ - 05.960.053/0001-78 | Q90: 868944.6
Q91: 27720
Q92: =SUM(Q90:Q91) -> 896664.6
Q93: =SUM(Q89,Q92) -> 1483605.8
A94: 45351 | B94: 01/24 | C94: Contrato | D94: ALCÂNTARA MASSONI – SOCIEDADE DE ADVOGADOS CNPJ - 41.090.148/0001-41 | E94: ADMINISTRAÇÃO | F94: Alexsandra Silva Aguiar | G94: Alexsandra Silva Aguiar | H94: Alexsandra Silva Aguiar | I94: CONTRATAÇÃO DE EMPRESA ESPECIALIZADA PARA PRESTAÇÃO DE SERVIÇOS DE CAPACITAÇÃO, ATUALIZAÇÃO, TREINAMENTO TEÓRICO E PRÁTICO DOS SERVIDORES DA PREFEITURA MUNICIPAL DE RIO GRANDE DA SERRA NA NOVA LEI DE LICITAÇÕES (LEI FEDERAL N° 14.133/2021) | J94: 40 HORAS | K94: 45323 | L94: 01/02/24 A 29/02/2024 | M94: 2027/23 | N94: - | O94: LICITAÇÃO 2024000000121 | P94: AJUSTE 2024000000090 | Q94: CONVITE Nº 11/2023 | R94: 85447.12 | S94: 44945 | T94: 45330
A95: 45349 | B95: 48/23 | C95: Contrato | D95: VIVERCON SERVIÇOS DE CONSTRUÇÃO CIVIL LTDA CNPJ - 11.076.813/0001-81 | E95: OBRAS | F95: Priscila Ulian de Oliveira | G95: Priscila Ulian de Oliveira | H95: Priscila Ulian de Oliveira | I95: CONTRATAÇÃO DE EMPRESA ESPECIALIZADA EM SERVIÇOS DE ENGENHARIA PARA CONSULTORIA, ELABORAÇÃO DE ESTUDOS E PROJETOS LUMINOTÉCNICOS, ESTUDO TÉCNICO COM DIAGNÓSTICO E EFICIENTIZAÇÃO ENERGÉTICA, ELABORAÇÃO DE PROJETO BÁSICO, CADERNO TÉCNICO, ORÇAMENTOS PARA MUDANÇA DO PARQUE DE ILUMINAÇÃO PÚBLICA PARA LED | J95: 90 DIAS | L95: 29/11/23 A 27/02/2024 | M95: 2013/23 | N95: - | O95: LICITAÇÃO 2023000000133 | P95: AJUSTE 202300000523 | Q95: DP - COMPRA DIRETA - 224/2023 | R95: 31500 | S95: 45259 | T95: 45265 | U95: FALTA ORDEM DE INÍCIO
A96: 45329 | B96: 49/23 | C96: Contrato | D96: ILUMICON LTDA CNPJ - 36.175.118/0001-06 | E96: ADMINISTRAÇÃO | F96: Alexsandra Silva Aguiar | G96: Kléber Avelino de Oliveira | H96: Kléber Avelino de Oliveira | I96: CONTRATAÇÃO DE EMPRESA DE ENGENHARIA PARA LOCAÇÃO DE DECORAÇÃO NATALINA, INSTALAÇÃO, REMOÇÃO E ACONDICIONAMENTO COM FORNECIMENTO DE MATERIAIS NO MUNICÍPIO DE RIO GRANDE DA SERRA | J96: 2 MESES | L96: 07/12/23 A 07/02/24 | M96: 2272/23 | N96: - | O96: LICITAÇÃO 2023000000141 | P96: AJUSTE 2023000000418 | Q96: DP - COMPRA DIRETA - 235/2023 | R96: 32896 | S96: 45267 | T96: 45278
A97: 45324 | B97: 30/23 | C97: Contrato | D97: 3ALLTECH – SERVIÇOS DE INFORMAÇÃO LTDA CNPJ - 18.367.014/0001-03 | E97: SEGURANÇA URBANA, TRANSITO E DEFESA CIVIL | G97: Izaias Fernandes | H97: Ana Lúcia Capitanio Teles Schiavone | I97: LOCAÇÃO (DISPONIBILIZAÇÃO/INSTALAÇÃO) DE SOFTWARE ESPECIALIZADO EM GESTÃO E REGISTRO DE INFRAÇÕES DE TRÂNSITO (TALONÁRIO) E DE OCORRÊNCIAS DE ACIDENTES DE TRÂNSITO, CONTEMPLANDO TODOS OS RECURSOS NECESSÁRIOS PARA A FINALIDADE DO OBJETO | L97: 02/08/23 a 02/02/24 | M97: 435/23 | N97: 1632/23 | Q97: CV 05/23 | R97: 170400 | S97: 45140 | T97: 45155
A98: 45969 | B98: 18/21 | C98: Contrato | D98: B TUNEL METODO NAO DESTRUTIVO ENGENHARIA EIRELI CNPJ - 34.169.504/0001-51 | E98: OBRAS | I98: CONTRATAÇÃO DE EMPRESA PARA EXECUÇÃO DE SERVIÇOS CIVIS E REPAROS NO VELÓRIO MUNICIPAL DE RIO GRANDE DA SERRA | M98: 44491 | N98: 397/21 | O98: - | R98: DP 14/21 | S98: 20822.11 | T98: 44470 | U98: 44491 | V98: 3 MESES APÓS A ORDEM DE INÍCIO
A99: 45291 | B99: *** | C99: *** | D99: CLARO S.A - CNPJ: 40.432.544/0001-47 | E99: ADMINISTRAÇÃO | G99: NÃO SE APLICA | H99: NÃO SE APLICA | I99: CONTRATAÇÃO DE SERVIÇO RENPAC - SERVIÇO DE COMUNICAÇÃO DE DADOS POR COMUTAÇÃO DE PACOTES, QUE PROPICIA A INTERLIGAÇÃO ENTRE TERMINAIS DE DADOS, MICROCOMPUTADORES E COMPUTADORES DO CIRETRAN DE RIO GRANDE DA SERRA ATRAVÉS DE CONVÊNIO. | M99: 01/01/22 A 31/12/22 | N99: 1067/22 | O99: 1067/2022 | P99: NÃO LANÇADO NA AUDESP | R99: DISPENSA DE LICITAÇÃO | S99: 8500 | T99: *** | U99: *** | V99: SERVIÇO CUSTEADO PELA SECRETARIA DE ADMINISTRAÇÃO DEVIDO CONVÊNIO COM O CIRETRAN
A100: 45289 | B100: 26/23 | C100: 1º Aditivo | D100: FÁBIO LEMOS NAKAMURA CPF - 321.017.798-89 | E100: CIDADANIA | G100: Adriana Alves da Silva Carvalho | H100: Fernanda Stachowski | I100: LOCAÇÃO DO IMÓVEL SITUADO NO MUNÍCIPIO DE RIO GRANDE DA SERRA, NA RUA MESSIAS DA SILVA RAMOS, Nº 220, VILA FIGUEIREDO, RIO GRANDE DA SERRA, PARA O FIM EXCLUSIVO DE INSTALAÇÃO DA CASA DE ACOLHIMENTO TEMPORÁRIA PARA PESSOAS EM SITUAÇÃO DE RUA | M100: 14/11/23 A 29/12/23 | N100: 720/23 | O100: 1366/23 | P100: DP 15/23 | Q100: 4500 | R100: 45121 | S100: 45253
...

Sheet ATAS VIGENTES
A1: =TODAY() -> 46167
C2: ATA | D2: Detentor | E2: Secretaria | F2: Gestor | G2: Fiscal | H2: Objeto | I2: Modalidade | J2: Processo Administrativo | K2: Processo Execução | L2: AUDESP | M2: Valor Total Ata | N2: Assinatura | O2: Data da Publicação | P2: Vigência | S2: OBSERVAÇÃO
A3: =Q3-$A$1 -> -1 | B3: =IF(A3<60,"Vencendo","Em Vigência") -> Vencendo | C3: 12/24 | D3: PILAR ECOTEC AMBIENTAL LTDA EPP CNPJ - 30.667.156/0001-91 | E3: DESENVOLVIMENTO | F3: Tânia Maria de Oliveira Sales | G3: Cristopher Ferraz de Araujo | H3: REGISTRO DE PREÇOS VISANDO EVENTUAIS LOCAÇÃO DE ESTRUTURAS, EQUIPAMENTOS E SERVIÇOS PARA EVENTOS MUNICIPAIS | I3: PE - 08/2024 | J3: 504/2024 | K3: 992/2024 | L3: 2024000000203 | M3: 866000 | N3: 45800 | O3: 45821 | P3: 24/05/2025 A 24/05/2026 | Q3: 46166 | R3: ADITIVO
A4: =Q4-$A$1 -> -1 | B4: =IF(A4<60,"Vencendo","Em Vigência") -> Vencendo | C4: 13/24 | D4: STAGE 360 EVENTOS LTDA - EPP CNPJ - 46.429.701/0001-41 | E4: DESENVOLVIMENTO | F4: Tânia Maria de Oliveira Sales | G4: Cristopher Ferraz de Araujo | H4: REGISTRO DE PREÇOS VISANDO EVENTUAIS LOCAÇÃO DE ESTRUTURAS, EQUIPAMENTOS E SERVIÇOS PARA EVENTOS MUNICIPAIS | I4: PE - 08/2024 | J4: 504/2024 | K4: 990/2024 | L4: 2024000000203 | M4: 4190000 | N4: 45800 | O4: 45821 | P4: 24/05/2025 A 24/05/2026 | Q4: 46166 | R4: ADITIVO
A5: =Q5-$A$1 -> 1 | B5: =IF(A5<60,"Vencendo","Em Vigência") -> Vencendo | C5: 26/25 | D5: DC INFINITY COMERCIALIZADORA LTDA | E5: ADMINISTRAÇÃO | F5: Kauê Rafael Lima Di Santi Pires | G5: Eduardo da Silva Divino | H5: REGISTRO DE PREÇOS PARA FUTURA E EVENTUAL AQUISIÇÃO DE ÁGUA MINERAL NATURAL, VISANDO ATENDER AS NECESSIDADES DAS UNIDADES DA PREFEITURA MUNICIPAL DE RIO GRANDE DA SERRA | I5: PE 06/25 | J5: PE 06/25 | K5: 960/2025 | L5: 2025000000153 | M5: 41090 | N5: 45798 | O5: 45803 | P5: 26/05/2025 A 26/05/2026 | Q5: 46168
A6: =Q6-$A$1 -> 1 | B6: =IF(A6<60,"Vencendo","Em Vigência") -> Vencendo | C6: 27/25 | D6: E.S. ADMINISTRADORA LTDA | E6: ADMINISTRAÇÃO | F6: Kauê Rafael Lima Di Santi Pires | G6: Eduardo da Silva Divino | H6: REGISTRO DE PREÇOS PARA FUTURA E EVENTUAL AQUISIÇÃO DE ÁGUA MINERAL NATURAL, VISANDO ATENDER AS NECESSIDADES DAS UNIDADES DA PREFEITURA MUNICIPAL DE RIO GRANDE DA SERRA | I6: PE 06/25 | J6: PE 06/25 | K6: 961/2025 | L6: 2025000000153 | M6: 2670 | N6: 45799 | O6: 45803 | P6: 26/05/2025 A 26/05/2026 | Q6: 46168
A7: =Q7-$A$1 -> 24 | B7: =IF(A7<60,"Vencendo","Em Vigência") -> Vencendo | C7: 29/25 | D7: WINES REIS COMERCIAL LTDA CNPJ sob o nº 47.282.627/0001-46 | E7: ADMINISTRAÇÃO | F7: Israel da Silva Junior CPF: 131.326.178-57 | G7: Juventude, Esporte e Lazer Nome: José Gilmário Silva Nicolau Cargo: Chefe de Setor CPF: 155.261.668-13 Família e Desenvolvimento Social Nome: Jorge Aparecido da Silva Cargo: Motorista CPF: 061.123.038-09 Segurança Urbana, Trânsito e Defesa Civil Nome: Fabiano Gomes Duarte Cargo: Diretor CPF: 365.558.428-81 Educação e Cultura Nome: Alexandro Calazans Vieira Cargo: Chefe de Setor CPF: 293.761.318-78 Saúde Nome: Celso Paes dos Santos Cargo: Gestor CPF: 054.536.117-17 Jurídico Nome: Ariane Perogini Prestes Cargo: Agente Administrativo CPF: 303.403.088-69 Obras Nome: Guilherme Tadeu Aparecido de Oliveira Dias do Prado Cargo: Engenheiro civil CPF: 414.046.498-40 Clima, Meio ambiente e Bem Estar Animal Nome: Cláudio Fernando Pereira Cargo: Fiscal CPF: 288.291.138-67 Serviços Urbanos Nome: Guilherme Leandro Bernado Cargo: Chefe de Setor CPF: 335.305.768-40 Administração Nome: Eduardo da Silva Divino Cargo: Agente Administrativo CPF: 297.110.268-80 | H7: REGISTRO DE PREÇOS PARA CONTRATAÇÃO DE SERVIÇOS DE MANUTENÇÃO PREVENTIVA, CORRETIVA E PERIÓDICA NOS VEÍCULOS (MOTOCICLETAS, VEÍCULOS LEVES, VEÍCULOS PESADOS E MAQUINÁRIOS/ EQUIPAMENTOS PESADOS) QUE COMPÕEM A FROTA DESTE MUNICÍPIO, FORNECIMENTO OU REPOSIÇÃO DE PEÇAS E AFINS, INCLUINDO MECÂNICA EM GERAL, SERVIÇOS DE FUNILARIA, PINTURA, ELÉTRICA, HIDRÁULICA, SUSPENSÃO, CAPOTARIA, VIDRAÇARIA, BORRACHARIA, BALANCEAMENTO E ALINHAMENTO, AR CONDICIONADO, ACESSÓRIOS DE SOM E INSTALAÇÃO DE ACESSÓRIOS EM GERAL | I7: PE 05/25 | J7: 1638/2024 | K7: 1211/2025 - ADM 1810/2025 - CIDADANIA 1811/2025 - JURIDICO 1812/2025 - ESPORTE 1813/2025 - SAÚDE 1809/2025 - SEGURANÇA 1814/2025 - SSU 1815/2025 - EDUCAÇÃO 1816/2025 - MEIO AMBIENTE 1979/2025 - OBRAS | L7: 2025000000156 | M7: LOTE 01 – MOTOCICLETAS - ME/EPP R$ 16.477,50 - 50% de desconto LOTE 02 – VEÍCULOS DE PASSEIO - ME/EPP R$ 30.070,00 - 55% de desconto LOTE 03 – VEÍCULOS UTILITÁRIOS - AMPLA CONCORRÊNCIA R$ 33.840,00 - 55% de desconto LOTE 04 – VEÍCULOS PESADOS - AMPLA CONCORRÊNCIA R$ 36.597,50 - 59% de desconto LOTE 05 – MAQUINÁRIOS E EQUIPAMENTOS PESADOS - AMPLA CONCORRÊNCIA R$ 135.646,00 - 56% de desconto | N7: 45820 | O7: 45826 | P7: 18/06/2025 A 18/06/2026 | Q7: 46191
A8: =Q8-$A$1 -> 40 | B8: =IF(A8<60,"Vencendo","Em Vigência") -> Vencendo | C8: 30/25 | D8: ASTRA MEDICAL SUPPLY PRODUTOS MEDICOS E HOSPITALARES LTDA CNPJ sob o nº 44.127.150/0001-36 | E8: SAÚDE | F8: Heloisa Pereira da Silva CRF: 107757 | G8: Sara de Melo Silva Fernandes CPF: 448.006.058-81 | H8: REGISTRO DE PREÇOS DE DIETAS, ALIMENTAÇÃO ENTERAL PARA ATENDIMENTO DAS DEMANDAS JUDICIAIS DO MUNICÍPIO DE RIO GRANDE DA SERRA | I8: PE 02/25 | J8: 1886/2024 | K8: 1259/2025 | L8: 2025000000159 | M8: 13802.4 | N8: 45834 | O8: 45842 | P8: 04/07/2025 A 04/07/2026 | Q8: 46207
A9: =Q9-$A$1 -> 40 | B9: =IF(A9<60,"Vencendo","Em Vigência") -> Vencendo | C9: 31/25 | D9: FRAGNARI DISTRIBUIDORA DE MEDICAMENTOS LTDA CNPJ sob o nº 14.271.474/0001-82 | E9: SAÚDE | F9: Heloisa Pereira da Silva CRF: 107757 | G9: Sara de Melo Silva Fernandes CPF: 448.006.058-81 | H9: REGISTRO DE PREÇOS DE DIETAS, ALIMENTAÇÃO ENTERAL PARA ATENDIMENTO DAS DEMANDAS JUDICIAIS DO MUNICÍPIO DE RIO GRANDE DA SERRA | I9: PE 02/25 | J9: 1886/2024 | K9: 1260/2025 | L9: 2025000000159 | M9: 4273.2 | N9: 45826 | O9: 45842 | P9: 04/07/2025 A 04/07/2026 | Q9: 46207
A10: =Q10-$A$1 -> 40 | B10: =IF(A10<60,"Vencendo","Em Vigência") -> Vencendo | C10: 32/25 | D10: LOGGEN PRODUTOS PARA SAÚDE LTDA CNPJ sob o nº 24.980.102/0001-89 | E10: SAÚDE | F10: Heloisa Pereira da Silva CRF: 107757 | G10: Sara de Melo Silva Fernandes CPF: 448.006.058-81 | H10: REGISTRO DE PREÇOS DE DIETAS, ALIMENTAÇÃO ENTERAL PARA ATENDIMENTO DAS DEMANDAS JUDICIAIS DO MUNICÍPIO DE RIO GRANDE DA SERRA | I10: PE 02/25 | J10: 1886/2024 | K10: 1258/2025 | L10: 2025000000159 | M10: 12163.2 | N10: 45825 | O10: 45842 | P10: 04/07/2025 A 04/07/2026 | Q10: 46207
A11: =Q11-$A$1 -> 40 | B11: =IF(A11<60,"Vencendo","Em Vigência") -> Vencendo | C11: 33/25 | D11: RIOMEDICA SAÚDE E NUTRIÇÃO COMÉRCIO DE SUPLEMENTOS LTDA CNPJ sob o nº 35.578.077/0001-28 | E11: SAÚDE | F11: Heloisa Pereira da Silva CRF: 107757 | G11: Sara de Melo Silva Fernandes CPF: 448.006.058-81 | H11: REGISTRO DE PREÇOS DE DIETAS, ALIMENTAÇÃO ENTERAL PARA ATENDIMENTO DAS DEMANDAS JUDICIAIS DO MUNICÍPIO DE RIO GRANDE DA SERRA | I11: PE 02/25 | J11: 1886/2024 | K11: 1257/2025 | L11: 2025000000159 | M11: 4315.2 | N11: 45826 | O11: 45842 | P11: 04/07/2025 A 04/07/2026 | Q11: 46207
A12: =Q12-$A$1 -> 59 | B12: =IF(A12<60,"Vencendo","Em Vigência") -> Vencendo | C12: 37/25 | D12: TREVO PADARIA RESTAURANTE E PIZZARIA LTDA CNPJ sob o nº 60.163.707/000-40 | E12: CIDADANIA | F12: Fernanda Stachowski CPF: 336.725.538-67 | G12: Cibely Aparecida Miranda dos Santos CPF: 462.455.488-45 | H12: REGISTRO DE PREÇOS PARA EVENTUAL FORNECIMENTO DE REFEIÇÕES, SENDO DESJEJUM E JANTAR (MARMITEX), PARA ATENDIMENTO ÀS PESSOAS EM SITUAÇÃO DE RUA, REFERENCIADAS E ACOMPANHADAS PELA EQUIPE DO CREAS | I12: DP 13/25 | J12: 2117/2023 | K12: 1460/2025 | L12: 2025000000166 | M12: 95400 | N12: 45860 | O12: 45861 | P12: 23/07/2025 A 23/07/2026 | Q12: 46226
A13: =Q13-$A$1 -> 68 | B13: =IF(A13<60,"Vencendo","Em Vigência") -> Em Vigência | C13: 38/25 | D13: COMERCIAL PROMOSTORE CONFECCOES LTDA CNPJ sob o nº 32.624.131/0001-36 | E13: EDUCAÇÃO | F13: Mônica Mara Rodrigues CPF: 257.494.078-45 | G13: Paula Neves Bernardo Garcia CPF: 163.539.478-36 | H13: REGISTRO DE PREÇOS VISANDO ADQUIRIR MATERIAL DE APOIO PEDAGÓGICO PARA ATENDER AS DEMANDAS ESCOLARES E DOS ALUNOS DA REDE MUNICIPAL DE ENSINO NO MUNICÍPIO DE RIO GRANDE DA SERRA | I13: PE 01/24 | J13: 1907/2023 | K13: 1408/2025 | L13: 2025000000169 | M13: 105117.4 | N13: 45867 | O13: 45870 | P13: 01/08/2025 A 01/08/2026 | Q13: 46235
A14: =Q14-$A$1 -> 59 | B14: =IF(A14<60,"Vencendo","Em Vigência") -> Vencendo | C14: 39/25 | D14: ESC COMERCIAL LTDA CNPJ sob o nº 42.222.413/0001-60 | E14: EDUCAÇÃO | F14: Mônica Mara Rodrigues CPF: 257.494.078-45 | G14: Paula Neves Bernardo Garcia CPF: 163.539.478-36 | H14: REGISTRO DE PREÇOS VISANDO ADQUIRIR MATERIAL DE APOIO PEDAGÓGICO PARA ATENDER AS DEMANDAS ESCOLARES E DOS ALUNOS DA REDE MUNICIPAL DE ENSINO NO MUNICÍPIO DE RIO GRANDE DA SERRA | I14: PE 01/24 | J14: 1907/2023 | K14: 1409/2025 | L14: 2025000000169 | M14: 1243407.2 | N14: 45856 | O14: 45861 | P14: 23/07/2025 A 23/07/2026 | Q14: 46226
A15: =Q15-$A$1 -> 59 | B15: =IF(A15<60,"Vencendo","Em Vigência") -> Vencendo | C15: 40/25 | D15: S A FREITAS ARTIGOS DE ESCRITORIO LTDA CNPJ sob o nº 48.547.677/0001-70 | E15: EDUCAÇÃO | F15: Mônica Mara Rodrigues CPF: 257.494.078-45 | G15: Paula Neves Bernardo Garcia CPF: 163.539.478-36 | H15: REGISTRO DE PREÇOS VISANDO ADQUIRIR MATERIAL DE APOIO PEDAGÓGICO PARA ATENDER AS DEMANDAS ESCOLARES E DOS ALUNOS DA REDE MUNICIPAL DE ENSINO NO MUNICÍPIO DE RIO GRANDE DA SERRA | I15: PE 01/24 | J15: 1907/2023 | K15: 1410/2025 | L15: 2025000000169 | M15: 285474.43 | N15: 45855 | O15: 45861 | P15: 23/07/2025 A 23/07/2026 | Q15: 46226
A16: =Q16-$A$1 -> 64 | B16: =IF(A16<60,"Vencendo","Em Vigência") -> Em Vigência | C16: 41/25 | D16: SEVEN COMERCIO E SERVIÇOS LTDA CNPJ sob o nº 07.159.856/0001-53 | E16: EDUCAÇÃO | F16: Mônica Mara Rodrigues CPF: 257.494.078-45 | G16: Paula Neves Bernardo Garcia CPF: 163.539.478-36 | H16: REGISTRO DE PREÇOS VISANDO ADQUIRIR MATERIAL DE APOIO PEDAGÓGICO PARA ATENDER AS DEMANDAS ESCOLARES E DOS ALUNOS DA REDE MUNICIPAL DE ENSINO NO MUNICÍPIO DE RIO GRANDE DA SERRA | I16: PE 01/24 | J16: 1907/2023 | K16: 1411/2025 | L16: 2025000000169 | M16: 649690 | N16: 45861 | O16: 45866 | P16: 28/07/2025 A 28/07/2026 | Q16: 46231
A17: =Q17-$A$1 -> 74 | B17: =IF(A17<60,"Vencendo","Em Vigência") -> Em Vigência | C17: 42/25 | D17: ROSICLER CIRURGICA LTDA CNPJ Nº: nº 57.365.116/0001-41 | E17: CIDADANIA | F17: Cibely Aparecida Miranda dos Santos CPF: 462.455.488-45 | G17: Ilana Rodrigues Mariano CPF: 318.605.163-00 | H17: REGISTRO DE PREÇOS, VISANDO A EVENTUAL FÓRMULA LÁCTEA INFANTIL, PARA ATENDER AS DEMANDAS DO SAICA (SERVIÇO DE ACOLHIMENTO INSTITUCIONAL PARA CRIANÇAS E ADOLESCENTES). | I17: PE 20/25 | J17: 162/2025 | K17: 1545/2025 | L17: 2025000000171 | M17: 38334 | N17: 45873 | O17: 45876 | P17: 07/08/2025 A 07/08/2026 | Q17: 46241
A18: =Q18-$A$1 -> 74 | B18: =IF(A18<60,"Vencendo","Em Vigência") -> Em Vigência | C18: 43/25 | D18: BERITH COMERCIO DE PRODUTOS ODONTOLOGICOS LTDA CNPJ sob o nº 57.642.694/0001-88 | E18: CIDADANIA | F18: Gerlice Brasil da Silva CPF: 270.446.548-78 | G18: Silvana Moraes Branco Conceição CPF: 140.431.098-30 | H18: REGISTRO DE PREÇO DE MATERIAIS ODONTOLÓGICOS PARA ATENDER AS NECESSIDADES DAS UNIDADES QUE COMPÕEM A SECRETARIA DE SAÚDE DO MUNICÍPIO DE RIO GRANDE DA SERRA | I18: PE 13/25 | J18: 2003/2024 | K18: 1546/2025 | L18: 2025000000171 | M18: 7948.41 | N18: 45873 | O18: 45876 | P18: 07/08/2025 A 07/08/2026 | Q18: 46241
A19: =Q19-$A$1 -> 74 | B19: =IF(A19<60,"Vencendo","Em Vigência") -> Em Vigência | C19: 44/25 | D19: DENTAL CONCEITO COMERCIO DE PRODUTOS ODONTOLOGICOS MEDICOS E HOSPITALARES LTDA CNPJ Nº: nº 29.084.363/0001-34 | E19: SAÚDE | F19: Gerlice Brasil da Silva CPF: 270.446.548-78 | G19: Silvana Moraes Branco Conceição CPF: 140.431.098-30 | H19: REGISTRO DE PREÇO DE MATERIAIS ODONTOLÓGICOS PARA ATENDER AS NECESSIDADES DAS UNIDADES QUE COMPÕEM A SECRETARIA DE SAÚDE DO MUNICÍPIO DE RIO GRANDE DA SERRA | I19: PE 13/25 | J19: 2003/2024 | K19: 1521/2025 | L19: 2025000000171 | M19: 27807.3 | N19: 45867 | O19: 45876 | P19: 07/08/2025 A 07/08/2026 | Q19: 46241
... A30: =Q30-$A$1 -> 89 | B30: =IF(A30<60,"Vencendo","Em Vigência") -> Em Vigência | C30: 55/25 | D30: ALMEIDA FARMACEUTICA LTDA CNPJ sob o nº 40.455.009/0001-01 | E30: SAÚDE | F30: Heloisa Pereira da Silva CPF: 434.113.338-12 | G30: Demóstenes Dias de Mendonça CPF: 460.198.395-91 | H30: REGISTRO DE PREÇOS PARA AQUISIÇÃO DE MEDICAMENTOS FRACASSADOS/DESERTOS EM PREGÕES ANTERIORES PARA ATENDER AS NECESSIDADES DAS UNIDADES QUE COMPÕEM A SECRETARIA DE SAÚDE DA PREFEITURA MUNICIPAL DE RIO GRANDE DA SERRA | I30: PE 12/25 | J30: 307/2025 | K30: 1691/2025 | L30: 2025000000184 | M30: 158388 | N30: 45888 | O30: 45891 | P30: 22/08/2025 A 22/08/2026 | Q30: 46256
A31: =Q31-$A$1 -> 93 | B31: =IF(A31<60,"Vencendo","Em Vigência") -> Em Vigência | C31: 27/24 | D31: ATMOSFERA GASES ESPECIAIS E EPIS CNPJ - 13.134.213/0001-58 | E31: SAÚDE | F31: FELIPE VIEIRA DE SÁ DOS SANTOS | G31: GERLICE BRASIL DA SILVA | H31: REGISTRO DE PREÇO PARA TROCA E FORNECIMENTO CONTÍNUO ININTERRUPTO DE OXIGÊNIO GASOSO, COM SISTEMA DE COMODATO EM CILINDROS, PARA SUPRIR AS NECESSIDADES DA SECRETARIA DE SAÚDE, COM A ENTREGA SOB DEMANDA, PELO PERÍODO DE 24 (VINTE E QUATRO MESES). | I31: PE - 20/24 | J31: 45444 | K31: 1639/2024 | L31: 2024000000228 | M31: 2025000 | N31: 45530 | O31: 45530 | P31: 26/08/2024 A 26/08/2025 | Q31: 46260
B32: =IF(A32<60,"Vencendo","Em Vigência") -> Vencendo | C32: ADITIVO | F32: TELMA MORAES PIRES | G32: GERLICE BRASIL DA SILVA | M32: 2025000 | N32: 45895 | O32: 45910 | P32: 26/08/2025 a 26/08/2026
A33: =Q33-$A$1 -> 94 | B33: =IF(A33<60,"Vencendo","Em Vigência") -> Em Vigência | C33: 56/25 | D33: APOTEK DISTRIBUIDORA DE MEDICAMENTOS E MATERIAIS HOSPITALARES LTDA CNPJ sob o nº 36.099.392/0001-35 | E33: SAÚDE | F33: Heloisa Pereira da Silva CPF: 434.113.338-12 | G33: Demóstenes Dias de Mendonça CPF: 460.198.395-91 | H33: REGISTRO DE PREÇOS PARA AQUISIÇÃO DE MEDICAMENTOS FRACASSADOS/DESERTOS EM PREGÕES ANTERIORES PARA ATENDER AS NECESSIDADES DAS UNIDADES QUE COMPÕEM A SECRETARIA DE SAÚDE DA PREFEITURA MUNICIPAL DE RIO GRANDE DA SERRA | I33: PE 12/25 | J33: 307/2025 | K33: 1692/2025 | L33: 2025000000184 | M33: 64632 | N33: 45894 | O33: 45896 | P33: 27/08/2025 A 27/08/2026 | Q33: 46261
A34: =Q34-$A$1 -> 114 | B34: =IF(A34<60,"Vencendo","Em Vigência") -> Em Vigência | C34: 57/25 | D34: AZULFARMA DISTRIBUIDORA DE MEDICAMENTOS LTDA CNPJ sob o nº 03.634.617/0001-57 | E34: SAÚDE | F34: Heloisa Pereira da Silva CPF: 434.113.338-12 | G34: Demóstenes Dias de Mendonça CPF: 460.198.395-91 | H34: REGISTRO DE PREÇOS PARA AQUISIÇÃO DE MEDICAMENTOS FRACASSADOS/DESERTOS EM PREGÕES ANTERIORES PARA ATENDER AS NECESSIDADES DAS UNIDADES QUE COMPÕEM A SECRETARIA DE SAÚDE DA PREFEITURA MUNICIPAL DE RIO GRANDE DA SERRA | I34: PE 12/25 | J34: 307/2025 | K34: 1828/2025 | L34: 2025000000184 | M34: 39636 | N34: 45910 | O34: 45916 | P34: 16/09/2025 A 16/09/2026 | Q34: 46281
A35: =Q35-$A$1 -> 102 | B35: =IF(A35<60,"Vencendo","Em Vigência") -> Em Vigência | C35: 58/25 | D35: CIRÚRGICA OLÍMPIO LTDA CNPJ sob o nº 01.140.868/0001-50 | E35: SAÚDE | F35: Heloisa Pereira da Silva CPF: 434.113.338-12 | G35: Demóstenes Dias de Mendonça CPF: 460.198.395-91 | H35: REGISTRO DE PREÇOS PARA AQUISIÇÃO DE MEDICAMENTOS FRACASSADOS/DESERTOS EM PREGÕES ANTERIORES PARA ATENDER AS NECESSIDADES DAS UNIDADES QUE COMPÕEM A SECRETARIA DE SAÚDE DA PREFEITURA MUNICIPAL DE RIO GRANDE DA SERRA | I35: PE 12/25 | J35: 307/2025 | K35: 1693/2025 | L35: 2025000000184 | M35: 27600 | N35: 45887 | O35: 45904 | P35: 04/09/2025 A 04/09/2026 | Q35: 46269
A36: =Q36-$A$1 -> 107 | B36: =IF(A36<60,"Vencendo","Em Vigência") -> Em Vigência | C36: 59/25 | D36: CIRÚRGICA ASSIS DISTRIBUIDORA DE PRODUTOS PARA SAÚDE LTDA CNPJ sob o nº 39.610.184/0001-47 | E36: SAÚDE | F36: Heloisa Pereira da Silva CPF: 434.113.338-12 | G36: Demóstenes Dias de Mendonça CPF: 460.198.395-91 | H36: REGISTRO DE PREÇOS PARA AQUISIÇÃO DE MEDICAMENTOS FRACASSADOS/DESERTOS EM PREGÕES ANTERIORES PARA ATENDER AS NECESSIDADES DAS UNIDADES QUE COMPÕEM A SECRETARIA DE SAÚDE DA PREFEITURA MUNICIPAL DE RIO GRANDE DA SERRA | I36: PE 12/25 | J36: 307/2025 | K36: 1694/2025 | L36: 2025000000184 | M36: 5976 | N36: 45902 | O36: 45909 | P36: 09/09/2025 A 09/09/2026 | Q36: 46274
A37: =Q37-$A$1 -> 94 | B37: =IF(A37<60,"Vencendo","Em Vigência") -> Em Vigência | C37: 60/25 | D37: CIRÚRGICA NOSSA SENHORA LTDA CNPJ sob o nº 24.586.988/0001-80 | E37: SAÚDE | F37: Heloisa Pereira da Silva CPF: 434.113.338-12 | G37: Demóstenes Dias de Mendonça CPF: 460.198.395-91 | H37: REGISTRO DE PREÇOS PARA AQUISIÇÃO DE MEDICAMENTOS FRACASSADOS/DESERTOS EM PREGÕES ANTERIORES PARA ATENDER AS NECESSIDADES DAS UNIDADES QUE COMPÕEM A SECRETARIA DE SAÚDE DA PREFEITURA MUNICIPAL DE RIO GRANDE DA SERRA | I37: PE 12/25 | J37: 307/2025 | K37: 1695/2025 | L37: 2025000000184 | M37: 19557 | N37: 45889 | O37: 45896 | P37: 27/08/2025 A 27/08/2026 | Q37: 46261
A38: =Q38-$A$1 -> 89 | B38: =IF(A38<60,"Vencendo","Em Vigência") -> Em Vigência | C38: 61/25 | D38: COMERCIAL CIRÚRGICA RIOCLARENSE LTDA CNPJ sob o nº 67.729.178/0004-91 | E38: SAÚDE | F38: Heloisa Pereira da Silva CPF: 434.113.338-12 | G38: Demóstenes Dias de Mendonça CPF: 460.198.395-91 | H38: REGISTRO DE PREÇOS PARA AQUISIÇÃO DE MEDICAMENTOS FRACASSADOS/DESERTOS EM PREGÕES ANTERIORES PARA ATENDER AS NECESSIDADES DAS UNIDADES QUE COMPÕEM A SECRETARIA DE SAÚDE DA PREFEITURA MUNICIPAL DE RIO GRANDE DA SERRA | I38: PE 12/25 | J38: 307/2025 | K38: 1696/2025 | L38: 2025000000184 | M38: 156426 | N38: 45888 | O38: 45891 | P38: 22/08/2025 A 22/08/2026 | Q38: 46256
A39: =Q39-$A$1 -> 94 | B39: =IF(A39<60,"Vencendo","Em Vigência") -> Em Vigência | C39: 62/25 | D39: DIMEBRAS COMERCIAL HOSPITALAR LTDA 56.081.482/0001-06 | E39: SAÚDE | F39: Heloisa Pereira da Silva CPF: 434.113.338-12 | G39: Demóstenes Dias de Mendonça CPF: 460.198.395-91 | H39: REGISTRO DE PREÇOS PARA AQUISIÇÃO DE MEDICAMENTOS FRACASSADOS/DESERTOS EM PREGÕES ANTERIORES PARA ATENDER AS NECESSIDADES DAS UNIDADES QUE COMPÕEM A SECRETARIA DE SAÚDE DA PREFEITURA MUNICIPAL DE RIO GRANDE DA SERRA | I39: PE 12/25 | J39: 307/2025 | K39: 1697/2025 | L39: 2025000000184 | M39: 108360 | N39: 45888 | O39: 45896 | P39: 27/08/2025 A 27/08/2026 | Q39: 46261
A40: =Q40-$A$1 -> 94 | B40: =IF(A40<60,"Vencendo","Em Vigência") -> Em Vigência | C40: 63/25 | D40: DISTRIBUIDORA DE MEDICAMENTOS BACKES LTDA CNPJ sob o nº 25.279.552/0001-01 | E40: SAÚDE | F40: Heloisa Pereira da Silva CPF: 434.113.338-12 | G40: Demóstenes Dias de Mendonça CPF: 460.198.395-91 | H40: REGISTRO DE PREÇOS PARA AQUISIÇÃO DE MEDICAMENTOS FRACASSADOS/DESERTOS EM PREGÕES ANTERIORES PARA ATENDER AS NECESSIDADES DAS UNIDADES QUE COMPÕEM A SECRETARIA DE SAÚDE DA PREFEITURA MUNICIPAL DE RIO GRANDE DA SERRA | I40: PE 12/25 | J40: 307/2025 | K40: 1699/2025 | L40: 2025000000184 | M40: 29508.42 | N40: 45891 | O40: 45896 | P40: 27/08/2025 A 27/08/2026 | Q40: 46261
A41: =Q41-$A$1 -> 89 | B41: =IF(A41<60,"Vencendo","Em Vigência") -> Em Vigência | C41: 64/25 | D41: DROGAFONTE LTDA CNPJ sob o nº 08.778.201/0001-26 | E41: SAÚDE | F41: Heloisa Pereira da Silva CPF: 434.113.338-12 | G41: Demóstenes Dias de Mendonça CPF: 460.198.395-91 | H41: REGISTRO DE PREÇOS PARA AQUISIÇÃO DE MEDICAMENTOS FRACASSADOS/DESERTOS EM PREGÕES ANTERIORES PARA ATENDER AS NECESSIDADES DAS UNIDADES QUE COMPÕEM A SECRETARIA DE SAÚDE DA PREFEITURA MUNICIPAL DE RIO GRANDE DA SERRA | I41: PE 12/25 | J41: 307/2025 | K41: 1700/2025 | L41: 2025000000184 | M41: 249124.56 | N41: 45888 | O41: 45891 | P41: 22/08/2025 A 22/08/2026 | Q41: 46256
A42: =Q42-$A$1 -> 94 | B42: =IF(A42<60,"Vencendo","Em Vigência") -> Em Vigência | C42: 65/25 | D42: FERRARI MED. DISTRIBUIDORA DE MEDICAMENTOS LTDA CNPJ sob o nº 28.004.857/0001-07 | E42: SAÚDE | F42: Heloisa Pereira da Silva CPF: 434.113.338-12 | G42: Demóstenes Dias de Mendonça CPF: 460.198.395-91 | H42: REGISTRO DE PREÇOS PARA AQUISIÇÃO DE MEDICAMENTOS FRACASSADOS/DESERTOS EM PREGÕES ANTERIORES PARA ATENDER AS NECESSIDADES DAS UNIDADES QUE COMPÕEM A SECRETARIA DE SAÚDE DA PREFEITURA MUNICIPAL DE RIO GRANDE DA SERRA | I42: PE 12/25 | J42: 307/2025 | K42: 1701/2025 | L42: 2025000000184 | M42: 18120 | N42: 45889 | O42: 45896 | P42: 27/08/2025 A 27/08/2026 | Q42: 46261
A43: =Q43-$A$1 -> 103 | B43: =IF(A43<60,"Vencendo","Em Vigência") -> Em Vigência | C43: 66/25 | D43: GRAMS & GRAMS LTDA | E43: SAÚDE | F43: Heloisa Pereira da Silva CPF: 434.113.338-12 | G43: Demóstenes Dias de Mendonça CPF: 460.198.395-91 | H43: REGISTRO DE PREÇOS PARA AQUISIÇÃO DE MEDICAMENTOS FRACASSADOS/DESERTOS EM PREGÕES ANTERIORES PARA ATENDER AS NECESSIDADES DAS UNIDADES QUE COMPÕEM A SECRETARIA DE SAÚDE DA PREFEITURA MUNICIPAL DE RIO GRANDE DA SERRA, | I43: PE 12/25 | J43: 307/2025 | K43: 1702/2025 | L43: 2025000000184 | M43: 8592 | N43: 45898 | O43: 45905 | P43: 05/09/2025 A 05/09/2026 | Q43: 46270
A44: =Q44-$A$1 -> 89 | B44: =IF(A44<60,"Vencendo","Em Vigência") -> Em Vigência | C44: 67/25 | D44: INDALABOR INDAIÁ LABORATÓRIO FARMACÊUTICO LTDA CNPJ sob o nº 04.654.861/0001-44 | E44: SAÚDE | F44: Heloisa Pereira da Silva CPF: 434.113.338-12 | G44: Demóstenes Dias de Mendonça CPF: 460.198.395-91 | H44: REGISTRO DE PREÇOS PARA AQUISIÇÃO DE MEDICAMENTOS FRACASSADOS/DESERTOS EM PREGÕES ANTERIORES PARA ATENDER AS NECESSIDADES DAS UNIDADES QUE COMPÕEM A SECRETARIA DE SAÚDE DA PREFEITURA MUNICIPAL DE RIO GRANDE DA SERRA | I44: PE 12/25 | J44: 307/2025 | K44: 1704/2025 | L44: 2025000000184 | M44: 51120 | N44: 45887 | O44: 45891 | P44: 22/08/2025 A 22/08/2026 | Q44: 46256
A45: =Q45-$A$1 -> 94 | B45: =IF(A45<60,"Vencendo","Em Vigência") -> Em Vigência | C45: 68/25 | D45: INOVAMED HOSPITALAR LTDA | E45: SAÚDE | F45: Heloisa Pereira da Silva CPF: 434.113.338-12 | G45: Demóstenes Dias de Mendonça CPF: 460.198.395-91 | H45: REGISTRO DE PREÇOS PARA AQUISIÇÃO DE MEDICAMENTOS FRACASSADOS/DESERTOS EM PREGÕES ANTERIORES PARA ATENDER AS NECESSIDADES DAS UNIDADES QUE COMPÕEM A SECRETARIA DE SAÚDE DA PREFEITURA MUNICIPAL DE RIO GRANDE DA SERRA | I45: PE 12/25 | J45: 307/2025 | K45: 1698/2025 | L45: 2025000000184 | M45: 59299.86 | N45: 45894 | O45: 45896 | P45: 27/08/2025 A 27/08/2026 | Q45: 46261
A46: =Q46-$A$1 -> 94 | B46: =IF(A46<60,"Vencendo","Em Vigência") -> Em Vigência | C46: 69/25 | D46: LA DOS SANTOS DISTRIBUIDORA DE MEDICAMENTOS 07.654.936.0001/85 | E46: SAÚDE | F46: Heloisa Pereira da Silva CPF: 434.113.338-12 | G46: Demóstenes Dias de Mendonça CPF: 460.198.395-91 | H46: REGISTRO DE PREÇOS PARA AQUISIÇÃO DE MEDICAMENTOS FRACASSADOS/DESERTOS EM PREGÕES ANTERIORES PARA ATENDER AS NECESSIDADES DAS UNIDADES QUE COMPÕEM A SECRETARIA DE SAÚDE DA PREFEITURA MUNICIPAL DE RIO GRANDE DA SERRA | I46: PE 12/25 | J46: 307/2025 | K46: 45886 | L46: 2025000000184 | M46: 27552 | N46: 45889 | O46: 45896 | P46: 27/08/2025 A 27/08/2026 | Q46: 46261
A47: =Q47-$A$1 -> 89 | B47: =IF(A47<60,"Vencendo","Em Vigência") -> Em Vigência | C47: 70/25 | D47: MEDILAR IMPORTAÇÃO E DISTRIBUIÇÃO DE PRODUTOS MÉDICO HOSPITALARES S/A CNPJ sob o nº 07.752.236/0001-23 | E47: SAÚDE | F47: Heloisa Pereira da Silva CPF: 434.113.338-12 | G47: Demóstenes Dias de Mendonça CPF: 460.198.395-91 | H47: REGISTRO DE PREÇOS PARA AQUISIÇÃO DE MEDICAMENTOS FRACASSADOS/DESERTOS EM PREGÕES ANTERIORES PARA ATENDER AS NECESSIDADES DAS UNIDADES QUE COMPÕEM A SECRETARIA DE SAÚDE DA PREFEITURA MUNICIPAL DE RIO GRANDE DA SERRA | I47: PE 12/25 | J47: 307/2025 | K47: 1705/2025 | L47: 2025000000184 | M47: 64776 | N47: 45888 | O47: 45891 | P47: 22/08/2025 A 22/08/2026 | Q47: 46256
A48: =Q48-$A$1 -> 89 | B48: =IF(A48<60,"Vencendo","Em Vigência") -> Em Vigência | C48: 71/25 | D48: OCTO FARMACO LTDA CNPJ sob o nº 29.404.097/0001-80 | E48: SAÚDE | F48: Heloisa Pereira da Silva CPF: 434.113.338-12 | G48: Demóstenes Dias de Mendonça CPF: 460.198.395-91 | H48: REGISTRO DE PREÇOS PARA AQUISIÇÃO DE MEDICAMENTOS FRACASSADOS/DESERTOS EM PREGÕES ANTERIORES PARA ATENDER AS NECESSIDADES DAS UNIDADES QUE COMPÕEM A SECRETARIA DE SAÚDE DA PREFEITURA MUNICIPAL DE RIO GRANDE DA SERRA | I48: PE 12/25 | J48: 307/2025 | K48: 1706/2025 | L48: 2025000000184 | M48: 16340.4 | N48: 45888 | O48: 45891 | P48: 22/08/2025 A 22/08/2026 | Q48: 46256
A49: =Q49-$A$1 -> 89 | B49: =IF(A49<60,"Vencendo","Em Vigência") -> Em Vigência | C49: 72/25 | D49: PONTAMED FARMACÊUTICA LTDA CNPJ sob o nº 02.816.696/0001-54 | E49: SAÚDE | F49: Heloisa Pereira da Silva CPF: 434.113.338-12 | G49: Demóstenes Dias de Mendonça CPF: 460.198.395-91 | H49: REGISTRO DE PREÇOS PARA AQUISIÇÃO DE MEDICAMENTOS FRACASSADOS/DESERTOS EM PREGÕES ANTERIORES PARA ATENDER AS NECESSIDADES DAS UNIDADES QUE COMPÕEM A SECRETARIA DE SAÚDE DA PREFEITURA MUNICIPAL DE RIO GRANDE DA SERRA | I49: PE 12/25 | J49: 307/2025 | K49: 1707/2025 | L49: 2025000000184 | M49: 98380.8 | N49: 45888 | O49: 45891 | P49: 22/08/2025 A 22/08/2026 | Q49: 46256
A50: =Q50-$A$1 -> 89 | B50: =IF(A50<60,"Vencendo","Em Vigência") -> Em Vigência | C50: 73/25 | D50: XISMED DISTRIBUIDORA LTDA 27.908.285/0001-10 | E50: SAÚDE | F50: Heloisa Pereira da Silva CPF: 434.113.338-12 | G50: Demóstenes Dias de Mendonça CPF: 460.198.395-91 | H50: REGISTRO DE PREÇOS PARA AQUISIÇÃO DE MEDICAMENTOS FRACASSADOS/DESERTOS EM PREGÕES ANTERIORES PARA ATENDER AS NECESSIDADES DAS UNIDADES QUE COMPÕEM A SECRETARIA DE SAÚDE DA PREFEITURA MUNICIPAL DE RIO GRANDE DA SERRA | I50: PE 12/25 | J50: 307/2025 | K50: 1709/2025 | L50: 2025000000184 | M50: 99000 | N50: 45889 | O50: 45896 | P50: 27/08/2025 A 27/08/2026 | Q50: 46256
A51: =Q51-$A$1 -> 87 | B51: =IF(A51<60,"Vencendo","Em Vigência") -> Em Vigência | C51: 74/25 | D51: CROMO COMERCIO E DISTRIBUICAO DE MATERIAIS ODONTO-MEDICO HOSPITALARES LTDA CNPJ sob o nº 30.584.194/0001-80 | E51: SAÚDE | F51: Heloísa Pereira da Silva CPF: 434.113.338-12 | G51: Silvana Moraes Branco Conceição CPF: 140.431.098-30 | H51: REGISTRO DE PREÇOS PARA FUTURA E EVENTUAL AQUISIÇÃO DE TIRAS REAGENTES E LANCETAS PARA AFERIÇÃO DE GLICOSE, DESTINADAS AO REABASTECIMENTO DAS UNIDADES DE SAÚDE DO MUNICÍPIO DE RIO GRANDE DA SERRA | I51: PE 19/25 | J51: 332/2025 | K51: 1686/2025 | L51: 2025000000186 | M51: 90000 | N51: 45889 | O51: 45891 | P51: 20/08/2025 A 20/08/2026 | Q51: 46254
A52: =Q52-$A$1 -> 81 | B52: =IF(A52<60,"Vencendo","Em Vigência") -> Em Vigência | C52: 75/25 | D52: VYTTRA DIAGNÓSTICOS S.A CNPJ sob o nº 00.904.728/0015-43 | E52: SAÚDE | F52: Heloísa Pereira da Silva CPF: 434.113.338-12 | G52: Silvana Moraes Branco Conceição CPF: 140.431.098-30 | H52: REGISTRO DE PREÇOS PARA FUTURA E EVENTUAL AQUISIÇÃO DE TIRAS REAGENTES E LANCETAS PARA AFERIÇÃO DE GLICOSE, DESTINADAS AO REABASTECIMENTO DAS UNIDADES DE SAÚDE DO MUNICÍPIO DE RIO GRANDE DA SERRA | I52: PE 19/25 | J52: 332/2025 | K52: 1687/2025 | L52: 2025000000186 | M52: 200000 | N52: 45883 | O52: 45891 | P52: 14/08/2025 A 14/08/2026 | Q52: 46248 | R52: ADITIVO - TROCA DE CNPJ
A53: =Q53-$A$1 -> 115 | B53: =IF(A53<60,"Vencendo","Em Vigência") -> Em Vigência | C53: 76/25 | D53: ALPHA COMERCIAL HOSPITLAR LTDA CNPJ sob o nº 41.073.251/0001-83 | E53: SAÚDE | F53: Heloísa Pereira da Silva CPF: 434.113.338-12 | G53: Sara de Melo Silva Fernandes CPF: 448.006.058-81 | H53: REGISTRO DE PREÇOS DE MATERIAIS MÉDICOS PARA ATENDIMENTO DE DEMANDA JUDICIAL DO MUNICÍPIO DE RIO GRANDE DA SERRA | I53: PE 08/25 | J53: 1888/2024 | K53: 1710/2025 | L53: 2025000000185 | M53: 28015.2 | N53: 45894 | O53: 45917 | P53: 17/09/2025 A 17/09/2026 | Q53: 46282
A54: =Q54-$A$1 -> 86 | B54: =IF(A54<60,"Vencendo","Em Vigência") -> Em Vigência | C54: 78/25 | D54: NEO MEDICAL COMERCIAL HOSPITALAR LTDA CNPJ sob o nº 20.956.481/0001-10 | E54: SAÚDE | F54: Heloísa Pereira da Silva CPF: 434.113.338-12 | G54: Sara de Melo Silva Fernandes CPF: 448.006.058-81 | H54: REGISTRO DE PREÇOS DE MATERIAIS MÉDICOS PARA ATENDIMENTO DE DEMANDA JUDICIAL DO MUNICÍPIO DE RIO GRANDE DA SERRA | I54: PE 08/25 | J54: 1888/2024 | K54: 1712/2025 | L54: 2025000000185 | M54: 960 | N54: 45891 | O54: 45898 | P54: 29/08/2025 A 29/08/2026 | Q54: 46253
A55: =Q55-$A$1 -> 86 | B55: =IF(A55<60,"Vencendo","Em Vigência") -> Em Vigência | C55: 79/25 | D55: SPECIAL MED COMERCIAL HOSPITALAR LTDA CNPJ sob o nº 47.292.400/0001-81 | E55: SAÚDE | F55: Heloísa Pereira da Silva CPF: 434.113.338-12 | G55: Sara de Melo Silva Fernandes CPF: 448.006.058-81 | H55: REGISTRO DE PREÇOS DE MATERIAIS MÉDICOS PARA ATENDIMENTO DE DEMANDA JUDICIAL DO MUNICÍPIO DE RIO GRANDE DA SERRA | I55: PE 08/25 | J55: 1888/2024 | K55: 1713/2025 | L55: 2025000000185 | M55: 13086.32 | N55: 45891 | O55: 45898 | P55: 29/08/2025 A 29/08/2026 | Q55: 46253
A56: =Q56-$A$1 -> 107 | B56: =IF(A56<60,"Vencendo","Em Vigência") -> Em Vigência | C56: 80/25 | D56: SAMTRONIC INDÚSTRIA E COMÉRCIO LTDA CNPJ sob o nº 58.426.628/0001 33 | E56: SAÚDE | F56: Heloísa Pereira da Silva CPF: 434.113.338-12 | G56: Sara de Melo Silva Fernandes CPF: 448.006.058-81 | H56: REGISTRO DE PREÇOS PARA AQUISIÇÃO DE EQUIPOS DE BOMBA DE INFUSÃO E BOMBAS DE INFUSÃO EM REGIME DE COMODATO PARA A UTILIZAÇÃO NA UNIDADE DE PRONTO ATENDIMENTO (UPA) DO MUNICÍPIO DE RIO GRANDE DA SERRA | I56: PE 23/25 | J56: 826/2025 | K56: 1754/2025 | L56: 2025000000188 | M56: 112000 | N56: 45902 | O56: 45909 | P56: 09/09/25 a 09/09/2026 | Q56: 46274
A57: =Q57-$A$1 -> 120 | B57: =IF(A57<60,"Vencendo","Em Vigência") -> Em Vigência | C57: 81/25 | D57: WAF COMÉRCIO E SERVIÇOS LTDA CNPJ sob o nº 15.065.776/0001-67 | E57: ADMINISTRAÇÃO | F57: Eduardo da Silva Divino CPF: 297.110.268-80 | G57: Kauê Rafael Lima di Santi Pires CPF: 411.882.018-83 | H57: REGISTRO DE PREÇOS PARA FUTURA E EVENTUAL AQUISIÇÃO DE MATERIAIS ELÉTRICOS, DIVIDIDOS EM LOTES, INCLUINDO CABOS E FIOS ELÉTRICOS, DISJUNTORES, TOMADAS E INTERRUPTORES, LÂMPADAS E LUMINÁRIAS, E MATERIAIS DIVERSOS, PARA ATENDER ÀS NECESSIDADES DA PREFEITURA MUNICIPAL DE RIO GRANDE DA SERRA, PELO PERÍODO DE 12 (DOZE) MESES, COM ENTREGA FRACIONADA | I57: PE 16/25 | J57: 1017/2025 | K57: 1846/2025 | L57: 2025000000190 | M57: 938802.79 | N57: 45918 | O57: 45922 | P57: 22/09/2025 A 22/09/2026 | Q57: 46287
A58: =Q58-$A$1 -> 116 | B58: =IF(A58<60,"Vencendo","Em Vigência") -> Em Vigência | C58: 82/25 | D58: FERREIRA & KOHLER ILUMINAÇÃO LTDA CNPJ sob o nº 53.111.090/0001-54 | E58: ADMINISTRAÇÃO | F58: Eduardo da Silva Divino CPF: 297.110.268-80 | G58: Kauê Rafael Lima di Santi Pires CPF: 411.882.018-83 | H58: REGISTRO DE PREÇOS PARA FUTURA E EVENTUAL AQUISIÇÃO DE MATERIAIS ELÉTRICOS, DIVIDIDOS EM LOTES, INCLUINDO CABOS E FIOS ELÉTRICOS, DISJUNTORES, TOMADAS E INTERRUPTORES, LÂMPADAS E LUMINÁRIAS, E MATERIAIS DIVERSOS, PARA ATENDER ÀS NECESSIDADES DA PREFEITURA MUNICIPAL DE RIO GRANDE DA SERRA, PELO PERÍODO DE 12 (DOZE) MESES, COM ENTREGA FRACIONADA | I58: PE 16/25 | J58: 1017/2025 | K58: 1847/2025 | L58: 2025000000190 | M58: 126978.48 | N58: 45912 | O58: 45918 | P58: 18/09/2025 A 18/09/2026 | Q58: 46283
A59: =Q59-$A$1 -> 129 | B59: =IF(A59<60,"Vencendo","Em Vigência") -> Em Vigência | C59: 83/25 | D59: E.S. ADMINISTRADORA LTDA CNPJ sob o nº 51.099.516/0001-76 | E59: CIDADANIA | F59: Cibely Aparecida Miranda dos Santos | G59: Ilana Rodrigues Mariano | H59: REGISTRO DE PREÇO PARA EVENTUAL AQUISIÇÃO DE ALIMENTOS PERECÍVEIS PARA ATENDER AS NECESSIDADES DOS USUÁRIOS DO CRAS (CENTRO DE REFERÊNCIA DE ASSISTÊNCIA SOCIAL), CREAS (CENTRO DE REFERÊNCIA ESPECIALIZADO DE ASSISTÊNCIA SOCIAL), E CONSELHO TUTELAR | I59: PE 24/25 | J59: 849/2025 | K59: 1972/2025 | L59: 2025000000191 | M59: 99761.7 | N59: 45918 | O59: 46296 | P59: 01/10/2025 A 01/10/2026 | Q59: 46296
A60: =Q60-$A$1 -> 129 | B60: =IF(A60<60,"Vencendo","Em Vigência") -> Em Vigência | C60: 84/25 | D60: GAMBA CONEXOES COMERCIO ATACADISTA DE ALIMENTOS LTDA CNPJ sob o nº 40.738.368/0001-76 | E60: CIDADANIA | F60: Cibely Aparecida Miranda dos Santos | G60: Ilana Rodrigues Mariano | H60: REGISTRO DE PREÇO PARA EVENTUAL AQUISIÇÃO DE ALIMENTOS PERECÍVEIS PARA ATENDER AS NECESSIDADES DOS USUÁRIOS DO CRAS (CENTRO DE REFERÊNCIA DE ASSISTÊNCIA SOCIAL), CREAS (CENTRO DE REFERÊNCIA ESPECIALIZADO DE ASSISTÊNCIA SOCIAL), E CONSELHO TUTELAR | I60: PE 24/25 | J60: 849/2025 | K60: 1970/2025 | L60: 2025000000191 | M60: 14470 | N60: 45930 | O60: 46296 | P60: 01/10/2025 A 01/10/2026 | Q60: 46296
A61: =Q61-$A$1 -> 129 | B61: =IF(A61<60,"Vencendo","Em Vigência") -> Em Vigência | C61: 85/25 | D61: FORTALEZA REAL COMERCIAL DE MATERIAIS E MANUTENÇÃO EM GERAL LTDA - ME CNPJ/MF sob o nº. 20.661.647/0001-71 | E61: CIDADANIA | F61: Cibely Aparecida Miranda dos Santos | G61: Ilana Rodrigues Mariano | H61: REGISTRO DE PREÇO PARA EVENTUAL AQUISIÇÃO DE ALIMENTOS PERECÍVEIS PARA ATENDER AS NECESSIDADES DOS USUÁRIOS DO CRAS (CENTRO DE REFERÊNCIA DE ASSISTÊNCIA SOCIAL), CREAS (CENTRO DE REFERÊNCIA ESPECIALIZADO DE ASSISTÊNCIA SOCIAL), E CONSELHO TUTELAR | I61: PE 24/25 | J61: 849/2025 | K61: 1971/2025 | L61: 2025000000191 | M61: 115072.8 | N61: 45923 | O61: 46296 | P61: 01/10/2025 A 01/10/2026 | Q61: 46296
A62: =Q62-$A$1 -> 129 | B62: =IF(A62<60,"Vencendo","Em Vigência") -> Em Vigência | C62: 86/25 | D62: MR ALIMENTOS SAUDAVEIS LTDA CNPJ/MF sob o nº. 22.077.561/0001-21 | E62: CIDADANIA | F62: Cibely Aparecida Miranda dos Santos | G62: Ilana Rodrigues Mariano | H62: REGISTRO DE PREÇO PARA EVENTUAL AQUISIÇÃO DE ALIMENTOS PERECÍVEIS PARA ATENDER AS NECESSIDADES DOS USUÁRIOS DO CRAS (CENTRO DE REFERÊNCIA DE ASSISTÊNCIA SOCIAL), CREAS (CENTRO DE REFERÊNCIA ESPECIALIZADO DE ASSISTÊNCIA SOCIAL), E CONSELHO TUTELAR | I62: PE 24/25 | J62: 849/2025 | K62: 1969/2025 | L62: 2025000000191 | M62: 11380 | N62: 45918 | O62: 46296 | P62: 01/10/2025 A 01/10/2026 | Q62: 46296
A63: =Q63-$A$1 -> 127 | B63: =IF(A63<60,"Vencendo","Em Vigência") -> Em Vigência | C63: 87/25 | D63: E. S. ADMINISTRADORA LTDA CNPJ sob o nº 51.099.516/0001-76 | E63: ADMINISTRAÇÃO | F63: Eduardo da Silva Divino CPF: 297.110.268-80 | G63: Kauê Rafael Lima di Santi Pires CPF: 411.882.018-83 | H63: REGISTRO DE PREÇOS PARA FUTURA E EVENTUAL AQUISIÇÃO DE PÓ DE CAFÉ, AÇÚCAR REFINADO, FILTRO DE PAPEL (COADOR), ADOÇANTE SUCRALOSE E PALHETA MEXEDOR DE CAFÉ, PARA ATENDER AS NECESSIDADES DA PREFEITURA MUNICIPAL DE RIO GRANDE DA SERRA, PELO PERÍODO DE 12 (DOZE) MESES COM ENTREGA FRACIONADA | I63: PE 17/25 | J63: 403/2025 | K63: 1906/2025 | L63: 2025000000193 | M63: 4074 | N63: 45923 | O63: 45929 | P63: 29/09/2025 A 29/09/2026 | Q63: 46294
A64: =Q64-$A$1 -> 137 | B64: =IF(A64<60,"Vencendo","Em Vigência") -> Em Vigência | C64: 88/25 | D64: NOBRE DISTRIBUIDORA LTDA | E64: ADMINISTRAÇÃO | F64: Eduardo da Silva Divino CPF: 297.110.268-80 | G64: Kauê Rafael Lima di Santi Pires CPF: 411.882.018-83 | H64: REGISTRO DE PREÇOS PARA FUTURA E EVENTUAL AQUISIÇÃO DE PÓ DE CAFÉ, AÇÚCAR REFINADO, FILTRO DE PAPEL (COADOR), ADOÇANTE SUCRALOSE E PALHETA MEXEDOR DE CAFÉ, PARA ATENDER AS NECESSIDADES DA PREFEITURA MUNICIPAL DE RIO GRANDE DA SERRA, PELO PERÍODO DE 12 (DOZE) MESES COM ENTREGA FRACIONADA | I64: PE 17/25 | J64: 403/2025 | K64: 1907/2025 | L64: 2025000000193 | M64: 8325 | N64: 45936 | O64: 45939 | P64: 09/10/2025 A 09/10/2026 | Q64: 46304
... A66: =Q66-$A$1 -> 121 | B66: =IF(A66<60,"Vencendo","Em Vigência") -> Em Vigência | C66: 90/25 | D66: WAF COMÉRCIO E SERVIÇOS LTDA CNPJ sob o nº 15.065.776/0001-67 | E66: ADMINISTRAÇÃO | F66: Eduardo da Silva Divino CPF: 297.110.268-80 | G66: Kauê Rafael Lima di Santi Pires CPF: 411.882.018-83 | H66: REGISTRO DE PREÇOS PARA FUTURA E EVENTUAL AQUISIÇÃO DE PÓ DE CAFÉ, AÇÚCAR REFINADO, FILTRO DE PAPEL (COADOR), ADOÇANTE SUCRALOSE E PALHETA MEXEDOR DE CAFÉ, PARA ATENDER AS NECESSIDADES DA PREFEITURA MUNICIPAL DE RIO GRANDE DA SERRA, PELO PERÍODO DE 12 (DOZE) MESES COM ENTREGA FRACIONADA | I66: PE 17/25 | J66: 403/2025 | K66: 1909/2025 | L66: 2025000000193 | M66: 4210 | N66: 45922 | O66: 45923 | P66: 23/09/2025 A 23/09/2026 | Q66: 46288
A67: =Q67-$A$1 -> 138 | B67: =IF(A67<60,"Vencendo","Em Vigência") -> Em Vigência | C67: 40/24 | D67: CIRURGICA OLIMPIO LTDA CNPJ - 01.140.868/0001-50 | E67: SAÚDE | F67: Heloisa Pereira da Silva | G67: Sara de Melo Silva Fernandes | H67: REGISTRO DE PREÇO PARA FORNECIMENTO DE MEDICAMENTOS INJETÁVEIS, VISANDO O ABASTECIMENTO DAS UNIDADES BÁSICAS DE SAÚDE E UPA DO MUNICÍPIO DE RIO GRANDE DA SERRA | I67: PE - 21/24 | J67: 1028/2024 | K67: 1859/2024 | L67: 2024000000255 | M67: 90600 | N67: 07/10/2024 10/10/2025 | O67: 10/10/2024 03/11/2025 | P67: 10/10/2024 A 10/10/2025 10/10/2025 A 10/10/2026 | Q67: 46305 | R67: ADITIVO
A68: =Q68-$A$1 -> 138 | B68: =IF(A68<60,"Vencendo","Em Vigência") -> Em Vigência | C68: 51/24 | D68: NOVA OESTE DISTRIBUIDORA DE MEDICAMENTOS LTDA CNPJ - 34.772.843/0001-28 | E68: SAÚDE | F68: Heloisa Pereira da Silva | G68: Sara de Melo Silva Fernandes | H68: REGISTRO DE PREÇO PARA FORNECIMENTO DE MEDICAMENTOS INJETÁVEIS, VISANDO O ABASTECIMENTO DAS UNIDADES BÁSICAS DE SAÚDE E UPA DO MUNICÍPIO DE RIO GRANDE DA SERRA | I68: PE - 21/24 | J68: 1028/2024 | K68: 1865/2024 | L68: 2024000000255 | M68: 59256 | N68: 08/10/2024 10/10/2025 | O68: 10/10/2024 29/10/2025 | P68: 10/10/2024 A 10/10/2025 10/10/2025 A 10/10/2026 | Q68: 46305 | R68: ADITIVO
A69: =Q69-$A$1 -> 138 | B69: =IF(A69<60,"Vencendo","Em Vigência") -> Em Vigência | C69: 52/24 | D69: PONTAMED FARMACÊUTICA LTDA CNPJ - 02.816.696/0001-54 | E69: SAÚDE | F69: Heloisa Pereira da Silva | G69: Sara de Melo Silva Fernandes | H69: REGISTRO DE PREÇO PARA FORNECIMENTO DE MEDICAMENTOS INJETÁVEIS, VISANDO O ABASTECIMENTO DAS UNIDADES BÁSICAS DE SAÚDE E UPA DO MUNICÍPIO DE RIO GRANDE DA SERRA | I69: PE - 21/24 | J69: 1028/2024 | K69: 1847/2024 | L69: 2024000000255 | M69: 66720.12 | N69: 07/10/2024 10/10/2025 | O69: 10/10/2024 29/10/2025 | P69: 10/10/2024 A 10/10/2025 10/10/2025 A 10/10/2026 | Q69: 46305 | R69: ADITIVO
A70: =Q70-$A$1 -> 139 | B70: =IF(A70<60,"Vencendo","Em Vigência") -> Em Vigência | C70: 84/24 | D70: NUTRICIONALE COMÉRCIO DE ALIMENTOS LTDA CNPJ - 08.528.442/0001-17 | E70: CIDADANIA | F70: Fernanda Stachowshi Martins | G70: Cibely Aparecida Miranda dos Santos | H70: REGISTRO DE PREÇOS PARA EVENTUAL AQUISIÇÃO DE KITS DE ALIMENTAÇÃO (CESTAS BÁSICAS) PARA ATENDER A DEMANDA DO CRAS | I70: PE 27/2024 | J70: 1038/2024 | K70: 2109/2024 | L70: 2024000000266 | M70: 139998 | N70: 45939 | O70: 45945 | P70: 11/10/2025 A 11/10/2026 | Q70: 46306 | R70: ADITIVO
A71: =Q71-$A$1 -> 139 | B71: =IF(A71<60,"Vencendo","Em Vigência") -> Em Vigência | C71: 43/24 | D71: COMERCIAL CIRURGICA RIOCLARENSE LTDA CNPJ - 67.729.178/0004-91 | E71: SAÚDE | F71: Heloisa Pereira da Silva | G71: Sara de Melo Silva Fernandes | H71: REGISTRO DE PREÇO PARA FORNECIMENTO DE MEDICAMENTOS INJETÁVEIS, VISANDO O ABASTECIMENTO DAS UNIDADES BÁSICAS DE SAÚDE E UPA DO MUNICÍPIO DE RIO GRANDE DA SERRA | I71: PE - 21/24 | J71: 1028/2024 | K71: 1851/2024 | L71: 2024000000255 | M71: 4608 | N71: 09/10/2024 11/10/2025 | O71: 11/10/2024 29/10/2025 | P71: 11/10/2024 A 11/10/2025 11/10/2025 A 11/10/2026 | Q71: 46306 | R71: ADITIVO
A72: =Q72-$A$1 -> 139 | B72: =IF(A72<60,"Vencendo","Em Vigência") -> Em Vigência | C72: 47/24 | D72: DISTRIBUIDORA DE MEDICAMENTOS BACKES LTDA CNPJ - 25.279.552/0001-01 | E72: SAÚDE | F72: Heloisa Pereira da Silva | G72: Sara de Melo Silva Fernandes | H72: REGISTRO DE PREÇO PARA FORNECIMENTO DE MEDICAMENTOS INJETÁVEIS, VISANDO O ABASTECIMENTO DAS UNIDADES BÁSICAS DE SAÚDE E UPA DO MUNICÍPIO DE RIO GRANDE DA SERRA | I72: PE - 21/24 | J72: 1028/2024 | K72: 1855/2024 | L72: 2024000000255 | M72: 9935.76 | N72: 09/10/2024 11/10/2025 | O72: 11/10/2024 29/10/2025 | P72: 11/10/2024 A 11/10/2025 11/10/2025 A 11/10/2026 | Q72: 46306 | R72: ADITIVO
A73: =Q73-$A$1 -> 139 | B73: =IF(A73<60,"Vencendo","Em Vigência") -> Em Vigência | C73: 39/24 | D73: BRASIL FARMAON MEDICAMENTOS FARMACÊUTICOS LTDA CNPJ - 40.254.918/0001-81 | E73: SAÚDE | F73: Heloisa Pereira da Silva | G73: Sara de Melo Silva Fernandes | H73: REGISTRO DE PREÇO PARA FORNECIMENTO DE MEDICAMENTOS INJETÁVEIS, VISANDO O ABASTECIMENTO DAS UNIDADES BÁSICAS DE SAÚDE E UPA DO MUNICÍPIO DE RIO GRANDE DA SERRA | I73: PE - 21/24 | J73: 1028/2024 | K73: 1857/2024 | L73: 2024000000255 | M73: 43176 | N73: 14/10/2024 11/10/2025 | O73: 11/10/2024 29/10/2025 | P73: 11/10/2024 A 11/10/2025 11/10/2025 A 11/10/2026 | Q73: 46306 | R73: ADITIVO
A74: =Q74-$A$1 -> 139 | B74: =IF(A74<60,"Vencendo","Em Vigência") -> Em Vigência | C74: 46/24 | D74: DIMEBRAS COMERCIAL HOSPITALAR LTDA CNPJ - 56.081.482/0001-06 | E74: SAÚDE | F74: Heloisa Pereira da Silva | G74: Sara de Melo Silva Fernandes | H74: REGISTRO DE PREÇO PARA FORNECIMENTO DE MEDICAMENTOS INJETÁVEIS, VISANDO O ABASTECIMENTO DAS UNIDADES BÁSICAS DE SAÚDE E UPA DO MUNICÍPIO DE RIO GRANDE DA SERRA | I74: PE - 21/24 | J74: 1028/2024 | K74: 1848/2024 | L74: 2024000000255 | M74: 231624 | N74: 09/10/2024 11/10/2025 | O74: 11/10/2024 03/11/2025 | P74: 11/10/2024 A 11/10/2025 11/10/2025 A 11/10/2026 | Q74: 46306 | R74: ADITIVO
A75: =Q75-$A$1 -> 139 | B75: =IF(A75<60,"Vencendo","Em Vigência") -> Em Vigência | C75: 49/24 | D75: INOVAMED HOSPITALAR LTDA CNPJ - 12.889.035/0001-02 | E75: SAÚDE | F75: Heloisa Pereira da Silva | G75: Sara de Melo Silva Fernandes | H75: REGISTRO DE PREÇO PARA FORNECIMENTO DE MEDICAMENTOS INJETÁVEIS, VISANDO O ABASTECIMENTO DAS UNIDADES BÁSICAS DE SAÚDE E UPA DO MUNICÍPIO DE RIO GRANDE DA SERRA | I75: PE - 21/24 | J75: 1028/2024 | K75: 1862/2024 | L75: 2024000000255 | M75: 11481 | N75: 09/10/2024 11/10/2025 | O75: 11/10/2024 29/10/2025 | P75: 11/10/2024 A 11/10/2025 11/10/2025 A 11/10/2026 | Q75: 46306 | R75: ADITIVO
A76: =Q76-$A$1 -> 146 | B76: =IF(A76<60,"Vencendo","Em Vigência") -> Em Vigência | C76: 48/24 | D76: DROGAFONTE LTDA CNPJ - 08.778.201/0001-26 | E76: SAÚDE | F76: Sara de Melo Silva Fernandes | G76: Demóstenes Dias de Mendonça | H76: REGISTRO DE PREÇO PARA FORNECIMENTO DE MEDICAMENTOS INJETÁVEIS, VISANDO O ABASTECIMENTO DAS UNIDADES BÁSICAS DE SAÚDE E UPA DO MUNICÍPIO DE RIO GRANDE DA SERRA | I76: PE - 21/24 | J76: 1028/2024 | K76: 1858/2024 | L76: 2024000000255 | M76: 207361,26 168.496,62 | N76: 14/10/2024 18/10/2025 | O76: 45583 | P76: 18/10/2024 A 18/10/2025 18/10/2025 A 18/10/2026 | Q76: 46313 | R76: ADITIVO
A77: =Q77-$A$1 -> 146 | B77: =IF(A77<60,"Vencendo","Em Vigência") -> Em Vigência | C77: 44/24 | D77: COMERCIAL RIFARMA DE MEDICAMENTOS LTDA CNPJ - 39.906.592/0001-40 | E77: SAÚDE | F77: Heloisa Pereira da Silva | G77: Sara de Melo Silva Fernandes | H77: REGISTRO DE PREÇO PARA FORNECIMENTO DE MEDICAMENTOS INJETÁVEIS, VISANDO O ABASTECIMENTO DAS UNIDADES BÁSICAS DE SAÚDE E UPA DO MUNICÍPIO DE RIO GRANDE DA SERRA | I77: PE - 21/24 | J77: 1028/2024 | K77: 1850/2024 | L77: 2024000000255 | M77: 9648 | N77: 45948 | O77: 45959 | P77: 18/10/2025 A 18/10/2026 | Q77: 46313 | R77: ADITIVO
A78: =Q78-$A$1 -> 136 | B78: =IF(A78<60,"Vencendo","Em Vigência") -> Em Vigência | C78: 54/24 | D78: CENTERMED COMÉRCIO DE PRODUTOS HOSPITALARES LTDA CNPJ - 03.652.030/0001-70 | E78: SAÚDE | F78: Heloisa Pereira da Silva | G78: Sara de Melo Silva Fernandes | H78: REGISTRO DE PREÇO PARA FORNECIMENTO DE MEDICAMENTOS NA FORMA FARMACÊUTICA DE COMPRIMIDOS VISANDO O ABASTECIMENTO DAS UNIDADES BÁSICAS DE SAÚDE E UPA DO MUNICÍPIO DE RIO GRANDE DA SERRA | I78: PE 23/24 | J78: 1030/2024 | K78: 1926/2024 | L78: 2024000000259 | M78: 9001.2 | N78: 45938 | O78: 45964 | P78: 08/10/2025 A 08/10/2026 | Q78: 46303
A79: =Q79-$A$1 -> 136 | B79: =IF(A79<60,"Vencendo","Em Vigência") -> Em Vigência | C79: 55/24 | D79: CIRURGICA OLIMPIO LTDA CNPJ - 01.140.868/0001-50 | E79: SAÚDE | F79: Heloisa Pereira da Silva | G79: Sara de Melo Silva Fernandes | H79: REGISTRO DE PREÇO PARA FORNECIMENTO DE MEDICAMENTOS NA FORMA FARMACÊUTICA DE COMPRIMIDOS VISANDO O ABASTECIMENTO DAS UNIDADES BÁSICAS DE SAÚDE E UPA DO MUNICÍPIO DE RIO GRANDE DA SERRA | I79: PE 23/24 | J79: 1030/2024 | K79: 1927/2024 | L79: 2024000000259 | M79: 81801.6 | N79: 45938 | O79: 45980 | P79: 08/10/2025 A 08/10/2026 | Q79: 46303
A80: =Q80-$A$1 -> 138 | B80: =IF(A80<60,"Vencendo","Em Vigência") -> Em Vigência | C80: 56/24 | D80: CIRÚRGICA ASSIS DISTRIBUIDORA DE PRODUTOS PARA SAÚDE LTDA CNPJ - 39.610.184/0001-47 | E80: SAÚDE | F80: Heloisa Pereira da Silva | G80: Sara de Melo Silva Fernandes | H80: REGISTRO DE PREÇO PARA FORNECIMENTO DE MEDICAMENTOS NA FORMA FARMACÊUTICA DE COMPRIMIDOS VISANDO O ABASTECIMENTO DAS UNIDADES BÁSICAS DE SAÚDE E UPA DO MUNICÍPIO DE RIO GRANDE DA SERRA | I80: PE 23/24 | J80: 1030/2024 | K80: 1928/2024 | L80: 2024000000259 | M80: 27096 | N80: 45939 | O80: 45964 | P80: 10/10/2025 A 10/10/2026 | Q80: 46305
A81: =Q81-$A$1 -> 136 | B81: =IF(A81<60,"Vencendo","Em Vigência") -> Em Vigência | C81: 58/24 | D81: DIMASTER COMERCIO DE PRODUTOS HOSPITALARES LTDA CNPJ - 02.520.829/0004-93 | E81: SAÚDE | F81: Heloisa Pereira da Silva | G81: Sara de Melo Silva Fernandes | H81: REGISTRO DE PREÇO PARA FORNECIMENTO DE MEDICAMENTOS NA FORMA FARMACÊUTICA DE COMPRIMIDOS VISANDO O ABASTECIMENTO DAS UNIDADES BÁSICAS DE SAÚDE E UPA DO MUNICÍPIO DE RIO GRANDE DA SERRA | I81: PE 23/24 | J81: 1030/2024 | K81: 1930/2024 | L81: 2024000000259 | M81: 94068 | N81: 45938 | O81: 45964 | P81: 08/10/2025 A 08/10/2026 | Q81: 46303
A82: =Q82-$A$1 -> 138 | B82: =IF(A82<60,"Vencendo","Em Vigência") -> Em Vigência | C82: 61/24 | D82: INOVAMED HOSPITALAR LTDA CNPJ - 12.889.035/0001-02 | E82: SAÚDE | F82: Heloisa Pereira da Silva | G82: Sara de Melo Silva Fernandes | H82: REGISTRO DE PREÇO PARA FORNECIMENTO DE MEDICAMENTOS NA FORMA FARMACÊUTICA DE COMPRIMIDOS VISANDO O ABASTECIMENTO DAS UNIDADES BÁSICAS DE SAÚDE E UPA DO MUNICÍPIO DE RIO GRANDE DA SERRA | I82: PE 23/24 | J82: 1030/2024 | K82: 1933/2024 | L82: 2024000000259 | M82: 63375 | N82: 45940 | O82: 45964 | P82: 10/10/2025 A 10/10/2026 | Q82: 46305
A83: =Q83-$A$1 -> 136 | B83: =IF(A83<60,"Vencendo","Em Vigência") -> Em Vigência | C83: 63/24 | D83: JT MEDICAMENTOS LTDA CNPJ - 51.892.897/0001-46 | E83: SAÚDE | F83: Heloisa Pereira da Silva | G83: Sara de Melo Silva Fernandes | H83: REGISTRO DE PREÇO PARA FORNECIMENTO DE MEDICAMENTOS NA FORMA FARMACÊUTICA DE COMPRIMIDOS VISANDO O ABASTECIMENTO DAS UNIDADES BÁSICAS DE SAÚDE E UPA DO MUNICÍPIO DE RIO GRANDE DA SERRA | I83: PE 23/24 | J83: 1030/2024 | K83: 1935/2024 | L83: 2024000000259 | M83: 63375 | N83: 45938 | O83: 45964 | P83: 08/10/2025 A 08/10/2026 | Q83: 46303
A84: =Q84-$A$1 -> 139 | B84: =IF(A84<60,"Vencendo","Em Vigência") -> Em Vigência | C84: 65/24 | D84: MCW PRODUTOS MEDICOS E HOSPITALARES LTDA CNPJ - 94.389.400/0001-84 | E84: SAÚDE | F84: Heloisa Pereira da Silva | G84: Sara de Melo Silva Fernandes | H84: REGISTRO DE PREÇO PARA FORNECIMENTO DE MEDICAMENTOS NA FORMA FARMACÊUTICA DE COMPRIMIDOS VISANDO O ABASTECIMENTO DAS UNIDADES BÁSICAS DE SAÚDE E UPA DO MUNICÍPIO DE RIO GRANDE DA SERRA | I84: PE 23/24 | J84: 1030/2024 | K84: 1939/2024 | L84: 2024000000259 | M84: 60750.48 | N84: 45940 | O84: 45964 | P84: 11/10/2025 A 11/10/2026 | Q84: 46306
A85: =Q85-$A$1 -> 142 | B85: =IF(A85<60,"Vencendo","Em Vigência") -> Em Vigência | C85: 66/24 | D85: NATCOFARMA DO BRASIL LTDA CNPJ - 08.157.293/0001-27 | E85: SAÚDE | F85: Heloisa Pereira da Silva | G85: Sara de Melo Silva Fernandes | H85: REGISTRO DE PREÇO PARA FORNECIMENTO DE MEDICAMENTOS NA FORMA FARMACÊUTICA DE COMPRIMIDOS VISANDO O ABASTECIMENTO DAS UNIDADES BÁSICAS DE SAÚDE E UPA DO MUNICÍPIO DE RIO GRANDE DA SERRA | I85: PE 23/24 | J85: 1030/2024 | K85: 1940/2024 | L85: 2024000000259 | M85: 29760 | N85: 45944 | O85: 45964 | P85: 14/10/2025 A 14/10/2026 | Q85: 46309
A86: =Q86-$A$1 -> 138 | B86: =IF(A86<60,"Vencendo","Em Vigência") -> Em Vigência | C86: 68/24 | D86: PROMEFARMA REPRESENTACOES COMERCIAIS LTDA CNPJ - 14.595.725/0001-84 | E86: SAÚDE | F86: Heloisa Pereira da Silva | G86: Sara de Melo Silva Fernandes | H86: REGISTRO DE PREÇO PARA FORNECIMENTO DE MEDICAMENTOS NA FORMA FARMACÊUTICA DE COMPRIMIDOS VISANDO O ABASTECIMENTO DAS UNIDADES BÁSICAS DE SAÚDE E UPA DO MUNICÍPIO DE RIO GRANDE DA SERRA | I86: PE 23/24 | J86: 1030/2024 | K86: 1942/2024 | L86: 2024000000259 | M86: 67193.16 | N86: 45940 | O86: 45964 | P86: 10/10/2025 A 10/10/2026 | Q86: 46305
A87: =Q87-$A$1 -> 157 | B87: =IF(A87<60,"Vencendo","Em Vigência") -> Em Vigência | C87: 72/24 | D87: DIMEVA DISTRIBUIDORA E IMPORTADORA LTDA CNPJ - 76.386.283/0001-13 | E87: SAÚDE | F87: Heloisa Pereira da Silva CPF: 434.113.338 12 | G87: Sara de Melo Silva Fernandes CPF: 448.006.058 81 | H87: REGISTRO DE PREÇO PARA FORNECIMENTO DE MEDICAMENTOS PSICOTRÓPICOS DE CONTROLE ESPECIAL LISTADOS NA PORTARIA SVS/MS N° 344/98 POR MEIO DE ATA DE REGISTRO DE PREÇO, VISANDO O ABASTECIMENTO DO CAPS 1 (CENTRO DE ATENÇÃO PSICOSSOCIAL) | I87: PE 22/25 | J87: 1029/2025 | K87: 2068/2024 | L87: 2024000000268 | M87: 7188 | N87: 23/10/2024 29/10/2025 | O87: 29/10/2024 03/11/2025 | P87: 29/10/2024 A 29/10/2025 29/10/2025 A 29/10/2026 | Q87: 46324 | R87: ADITIVO
A88: =Q88-$A$1 -> 157 | B88: =IF(A88<60,"Vencendo","Em Vigência") -> Em Vigência | C88: 73/24 | D88: CENTERMED COMÉRCIO DE PRODUTOS HOSPITALARES LTDA CNPJ - 03.652.030/0001-70 | E88: SAÚDE | F88: Heloisa Pereira da Silva CPF: 434.113.338 12 | G88: Sara de Melo Silva Fernandes CPF: 448.006.058 81 | H88: REGISTRO DE PREÇO PARA FORNECIMENTO DE MEDICAMENTOS PSICOTRÓPICOS DE CONTROLE ESPECIAL LISTADOS NA PORTARIA SVS/MS N° 344/98 POR MEIO DE ATA DE REGISTRO DE PREÇO, VISANDO O ABASTECIMENTO DO CAPS 1 (CENTRO DE ATENÇÃO PSICOSSOCIAL) | I88: PE 22/25 | J88: 1029/2026 | K88: 2069/2024 | L88: 2024000000269 | M88: 5040 | N88: 23/10/2024 29/10/2025 | O88: 29/10/2024 10/11/2025 | P88: 29/10/2024 A 29/10/2025 29/10/2025 A 29/10/2026 | Q88: 46324 | R88: ADITIVO
A89: =Q89-$A$1 -> 157 | B89: =IF(A89<60,"Vencendo","Em Vigência") -> Em Vigência | C89: 83/24 | D89: PÉROLA IMPORTADORA E DISTRIBUIDORA HOSPITALAR LTDA CNPJ - 30.888.187/0001-72 | E89: SAÚDE | F89: Heloisa Pereira da Silva CPF: 434.113.338 12 | G89: Sara de Melo Silva Fernandes CPF: 448.006.058 81 | H89: REGISTRO DE PREÇO PARA FORNECIMENTO DE MEDICAMENTOS PSICOTRÓPICOS DE CONTROLE ESPECIAL LISTADOS NA PORTARIA SVS/MS N° 344/98 POR MEIO DE ATA DE REGISTRO DE PREÇO, VISANDO O ABASTECIMENTO DO CAPS 1 (CENTRO DE ATENÇÃO PSICOSSOCIAL) | I89: PE 22/25 | J89: 1029/2036 | K89: 2079/2024 | L89: 2024000000279 | M89: 24300 | N89: 45588 | O89: 29/10/2024 29/10/2025 | P89: 29/10/2024 A 29/10/2025 29/10/2025 A 29/10/2026 | Q89: 46324 | R89: ADITIVO
A90: =Q90-$A$1 -> 157 | B90: =IF(A90<60,"Vencendo","Em Vigência") -> Em Vigência | C90: 82/24 | D90: CONQUISTA DISTRIBUIDORA DE MEDICAMENTOS E PRODUTOS HOSPITALARES LTDA CNPJ - 12.418.191/0001-95 | E90: SAÚDE | F90: José Laércio de Lima | G90: Heloisa Pereira da Silva | H90: REGISTRO DE PREÇO PARA FORNECIMENTO DE MEDICAMENTOS PSICOTRÓPICOS DE CONTROLE ESPECIAL LISTADOS NA PORTARIA SVS/MS N° 344/98 POR MEIO DE ATA DE REGISTRO DE PREÇO, VISANDO O ABASTECIMENTO DO CAPS 1 (CENTRO DE ATENÇÃO PSICOSSOCIAL) | I90: PE 22/25 | J90: 1029/2035 | K90: 2078/2024 | L90: 2024000000278 | M90: 4620 | N90: 23/10/2024 29/10/2025 | O90: 29/10/2024 28/11/2025 | P90: 29/10/2024 A 29/10/2025 29/10/2025 A 29/10/2026 | Q90: 46324 | R90: ADITIVO
A91: =Q91-$A$1 -> 158 | B91: =IF(A91<60,"Vencendo","Em Vigência") -> Em Vigência | C91: 78/24 | D91: COMERCIAL CIRURGICA RIOCLARENSE LTDA CNPJ - 67.729.178/0004-91 | E91: SAÚDE | F91: Heloisa Pereira da Silva CPF: 434.113.338 12 | G91: Sara de Melo Silva Fernandes CPF: 448.006.058 81 | H91: REGISTRO DE PREÇO PARA FORNECIMENTO DE MEDICAMENTOS PSICOTRÓPICOS DE CONTROLE ESPECIAL LISTADOS NA PORTARIA SVS/MS N° 344/98 POR MEIO DE ATA DE REGISTRO DE PREÇO, VISANDO O ABASTECIMENTO DO CAPS 1 (CENTRO DE ATENÇÃO PSICOSSOCIAL) | I91: PE 22/25 | J91: 1029/2031 | K91: 2074/2024 | L91: 2024000000274 | M91: 23280 | N91: 24/10/2024 30/10/2025 | O91: 30/10/2024 10/11/2025 | P91: 30/10/2024 A 30/10/2025 30/10/2025 A 30/10/2026 | Q91: 46325 | R91: ADITIVO
A92: =Q92-$A$1 -> 158 | B92: =IF(A92<60,"Vencendo","Em Vigência") -> Em Vigência | C92: 81/24 | D92: DROGAFONTE LTDA CNPJ - 08.778.201/0001-26 | E92: SAÚDE | F92: Sara de Melo Silva Fernandes CPF: 448.006.058 81 | G92: Demóstenes Dias de Mendonça CPF 460.198.395-91 | H92: REGISTRO DE PREÇO PARA FORNECIMENTO DE MEDICAMENTOS PSICOTRÓPICOS DE CONTROLE ESPECIAL LISTADOS NA PORTARIA SVS/MS N° 344/98 POR MEIO DE ATA DE REGISTRO DE PREÇO, VISANDO O ABASTECIMENTO DO CAPS 1 (CENTRO DE ATENÇÃO PSICOSSOCIAL) | I92: PE 22/25 | J92: 1029/2034 | K92: 2077/2024 | L92: 2024000000277 | M92: 54420 | N92: 24/10/2024 30/10/2025 | O92: 30/10/2024 10/11/2025 | P92: 30/10/2024 A 30/10/2025 30/10/2025 A 30/10/2026 | Q92: 46325 | R92: ADITIVO
A93: =Q93-$A$1 -> 158 | B93: =IF(A93<60,"Vencendo","Em Vigência") -> Em Vigência | C93: 85/24 | D93: FORTALEZA REAL COMERCIAL DE MATERIAIS E MANUTENÇÃO EM GERAL LTDA - ME CNPJ/MF sob o nº. 20.661.647/0001-71 | E93: SAÚDE | F93: Heloisa Pereira da Silva CPF: 434.113.338 12 | G93: Sara de Melo Silva Fernandes CPF: 448.006.058 81 | H93: REGISTRO DE PREÇOS PARA AQUISIÇÃO DE PROTETORES SOLARES COM REPELENTE, PARA UTILIZAÇÃO PELO DEPARTAMENTO DE VIGILÂNCIA E ATENÇÃO PRIMÁRIA | I93: PE 32/2024 | J93: 277/2024 | K93: 2080/2024 | L93: 2024000000269 | M93: 19000 | N93: 24/10/2024 30/10/2025 | O93: 30/10/2024 10/11/2025 | P93: 30/10/2024 A 30/10/2025 30/10/2025 A 30/10/2026 | Q93: 46325 | R93: ADITIVO
A94: =Q94-$A$1 -> 170 | B94: =IF(A94<60,"Vencendo","Em Vigência") -> Em Vigência | C94: 87/24 | D94: TOP NORTE COMÉRCIO DE MATERIAIS MÉDICOS HOSPITALARES LTDA | E94: SAÚDE | F94: José Laércio de Lima | G94: Heloisa Pereira da Silva | H94: REGISTRO DE PREÇO PARA FORNECIMENTO DE MEDICAMENTOS PARA ATENDER AS UNIDADES BÁSICAS DE SAÚDE E UPA – UNIDADE DE PRONTO ATENDIMENTO E MEDICAMENTOS PSICOTRÓPICOS, COMPRIMIDOS E INJETÁVEIS DESTINADOS A SECRETARIA DE SAÚDE DE RIO GRANDE DA SERRA | I94: PE 18/2024 | J94: 734/2024 | K94: 2136/2024 | L94: 2024000000268 | M94: 16974 | N94: 45972 | O94: 45979 | P94: 11/11/2025 A 11/11/2026 | Q94: 46337 | R94: ADITIVO
A95: =Q95-$A$1 -> 170 | B95: =IF(A95<60,"Vencendo","Em Vigência") -> Em Vigência | C95: 88/24 | D95: CONQUISTA DISTRIBUIDORA DE MEDICAMENTOS E PRODUTOS HOSPITALARES LTDA | E95: SAÚDE | F95: Heloisa Pereira da Silva CPF: 434.113.338 12 | G95: Sara de Melo Silva Fernandes CPF: 448.006.058 81 | H95: REGISTRO DE PREÇO PARA FORNECIMENTO DE MEDICAMENTOS PARA ATENDER AS UNIDADES BÁSICAS DE SAÚDE E UPA – UNIDADE DE PRONTO ATENDIMENTO E MEDICAMENTOS PSICOTRÓPICOS, COMPRIMIDOS E INJETÁVEIS DESTINADOS A SECRETARIA DE SAÚDE DE RIO GRANDE DA SERRA | I95: PE 18/2024 | J95: 734/2024 | K95: 2137/2024 | L95: 2024000000268 | M95: 7080 | N95: 45968 | O95: 45979 | P95: 11/11/2025 A 11/11/2026 | Q95: 46337 | R95: ADITIVO
A96: =Q96-$A$1 -> 177 | B96: =IF(A96<60,"Vencendo","Em Vigência") -> Em Vigência | C96: 91/24 | D96: DROGAFONTE LTDA | E96: SAUDE | F96: Heloisa Pereira da Silva CPF: 434.113.338 12 | G96: Sara de Melo Silva Fernandes CPF: 448.006.058 81 | H96: REGISTRO DE PREÇO PARA FORNECIMENTO DE MEDICAMENTOS PARA ATENDER AS UNIDADES BÁSICAS DE SAÚDE E UPA – UNIDADE DE PRONTO ATENDIMENTO E MEDICAMENTOS PSICOTRÓPICOS, COMPRIMIDOS E INJETÁVEIS DESTINADOS A SECRETARIA DE SAÚDE DE RIO GRANDE DA SERRA | I96: PE 18/2024 | J96: 734/2024 | K96: 2140/2024 | L96: 2024000000268 | M96: 63748.56 | N96: 45979 | O96: 46003 | P96: 18/11/2025 A 18/11/2026 | Q96: 46344 | R96: ADITIVO
A97: =Q97-$A$1 -> 170 | B97: =IF(A97<60,"Vencendo","Em Vigência") -> Em Vigência | C97: 95/24 | D97: DIMASTER COMÉRCIO DE PRODUTOS HOSPITALARES LTDA | E97: SAUDE | F97: Sara de Melo Silva Fernandes | G97: Demóstenes Dias de Mendonça | H97: REGISTRO DE PREÇO PARA FORNECIMENTO DE MEDICAMENTOS PARA ATENDER AS UNIDADES BÁSICAS DE SAÚDE E UPA – UNIDADE DE PRONTO ATENDIMENTO E MEDICAMENTOS PSICOTRÓPICOS, COMPRIMIDOS E INJETÁVEIS DESTINADOS A SECRETARIA DE SAÚDE DE RIO GRANDE DA SERRA | I97: PE 18/2024 | J97: 734/2024 | K97: 2145/2024 | L97: 2024000000268 | M97: 111033.9 | N97: 45586 | O97: 45964 | P97: 11/11/2025 A 11/11/2026 | Q97: 46337 | R97: ADITIVO
A98: =Q98-$A$1 -> 170 | B98: =IF(A98<60,"Vencendo","Em Vigência") -> Em Vigência | C98: 96/24 | D98: SIRIO PHARMA LTDA | E98: SAUDE | F98: José Laércio de Lima | G98: Heloisa Pereira da Silva | H98: REGISTRO DE PREÇO PARA FORNECIMENTO DE MEDICAMENTOS PARA ATENDER AS UNIDADES BÁSICAS DE SAÚDE E UPA – UNIDADE DE PRONTO ATENDIMENTO E MEDICAMENTOS PSICOTRÓPICOS, COMPRIMIDOS E INJETÁVEIS DESTINADOS A SECRETARIA DE SAÚDE DE RIO GRANDE DA SERRA | I98: PE 18/2024 | J98: 734/2024 | K98: 2146/2024 | L98: 2024000000268 | M98: 35400 | N98: 45971 | O98: 45979 | P98: 11/11/2025 A 11/11/2026 | Q98: 46337 | R98: ADITIVO
A99: =Q99-$A$1 -> 170 | B99: =IF(A99<60,"Vencendo","Em Vigência") -> Em Vigência | C99: 97/24 | D99: JT MEDICAMENTOS LTDA | E99: SAUDE | F99: Heloisa Pereira da Silva CPF: 434.113.338 12 | G99: Sara de Melo Silva Fernandes CPF: 448.006.058 81 | H99: REGISTRO DE PREÇO PARA FORNECIMENTO DE MEDICAMENTOS PARA ATENDER AS UNIDADES BÁSICAS DE SAÚDE E UPA – UNIDADE DE PRONTO ATENDIMENTO E MEDICAMENTOS PSICOTRÓPICOS, COMPRIMIDOS E INJETÁVEIS DESTINADOS A SECRETARIA DE SAÚDE DE RIO GRANDE DA SERRA | I99: PE 18/2024 | J99: 734/2024 | K99: 2148/2024 | L99: 2024000000268 | M99: 14825.94 | N99: 45964 | O99: 45978 | P99: 11/11/2025 A 11/11/2026 | Q99: 46337 | R99: ADITIVO
A100: =Q100-$A$1 -> 170 | B100: =IF(A100<60,"Vencendo","Em Vigência") -> Em Vigência | C100: 98/24 | D100: GRAMS & GRAMS LTDA | E100: SAUDE | F100: Heloisa Pereira da Silva CPF: 434.113.338 12 | G100: Sara de Melo Silva Fernandes CPF: 448.006.058 81 | H100: REGISTRO DE PREÇO PARA FORNECIMENTO DE MEDICAMENTOS PARA ATENDER AS UNIDADES BÁSICAS DE SAÚDE E UPA – UNIDADE DE PRONTO ATENDIMENTO E MEDICAMENTOS PSICOTRÓPICOS, COMPRIMIDOS E INJETÁVEIS DESTINADOS A SECRETARIA DE SAÚDE DE RIO GRANDE DA SERRA | I100: PE 18/2024 | J100: 734/2024 | K100: 2149/2024 | L100: 2024000000268 | M100: 14255.82 | N100: 45968 | O100: 45979 | P100: 11/11/2025 A 11/11/2026 | Q100: 46337 | R100: ADITIVO
A101: =Q101-$A$1 -> 170 | B101: =IF(A101<60,"Vencendo","Em Vigência") -> Em Vigência | C101: 99/24 | D101: PEDRINA MUSTAFA ME CNPJ sob o nº 20.976.427/0001-37 | E101: CIDADANIA | F101: Fernanda Stachowski Martins | G101: Maria Aparecida da Costa | H101: REGISTRO DE PREÇO PARA EVENTUAL AQUISIÇÃO DE UNIDADES DE CARTEIRA DE IDENTIFICAÇÃO PARA TRANSPORTE DOS IDOSOS E CARTEIRA DE IDENTIFICAÇÃO DO AUTISTA – CIPTEA | I101: PE 35/24 | J101: 750/2024 | K101: 2163/2024 | L101: 2024000000277 | M101: 11994 | N101: 45972 | O101: 45986 | P101: 11/11/2025 a 11/11/2026 | Q101: 46337 | R101: ADITIVO
A102: =Q102-$A$1 -> 186 | B102: =IF(A102<60,"Vencendo","Em Vigência") -> Em Vigência | C102: 95/25 | D102: WAF COMERCIO E SERVIÇOS LTDA CNPJ sob o nº 15.065.776/0001-67 | E102: ADMINISTRAÇÃO | F102: Kauê Rafael Lima di Santi Pires CPF: 411.882.018 83 | G102: Eduardo da Silva Divino CPF: 297.110.268 80 | H102: REGISTRO DE PREÇOS PARA FUTURA E EVENTUAL AQUISIÇÃO DE MATERIAIS DE HIDRÁULICOS, PARA ATENDER ÀS NECESSIDADES DA PREFEITURA MUNICIPAL DE RIO GRANDE DA SERRA | I102: PE 18/25 | J102: 1060/2025 | K102: 2321/2025 | L102: 2025000000207 | M102: 78678.11 | N102: 45986 | O102: 45988 | P102: 27/11/2025 A 27/11/2026 | Q102: 46353
A103: =Q103-$A$1 -> 192 | B103: =IF(A103<60,"Vencendo","Em Vigência") -> Em Vigência | C103: 104/24 | D103: FLEX NEGÓCIOS E SERVIÇOS LTDA CNPJ sob o nº 21.559.378/0001-08 | E103: ADMINISTRAÇÃO | F103: Eduardo da Silva Divino CPF: 297.110.268-80 | G103: Kauê Rafael Lima Di Santi Pires | H103: REGISTRO DE PREÇOS PARA A REALIZAÇÃO DE SERVIÇOS DE IMPRESSÃO DE MATERIAIS GRÁFICOS PARA USO NAS DIVERSAS SECRETARIAS DO MUNICÍPIO DE RIO GRANDE DA SERRA | I103: PE 37/24 | J103: 1153/2024 | K103: 2279/2024 | L103: 2024000000290 | M103: 702000 | N103: 45994 | O103: 46044 | P103: 03/12/2025 a 03/12/2026 | Q103: 46359 | R103: ADITIVO
A104: =Q104-$A$1 -> 197 | B104: =IF(A104<60,"Vencendo","Em Vigência") -> Em Vigência | C104: 96/25 | D104: COMERCIAL VANGUARDEIRA LTDA CNPJ sob o nº 10.942.831/0001 36 | E104: ADMINISTRAÇÃO | F104: Kauê Rafael Lima di Santi Pires CPF: 411.882.018 83 | G104: Eduardo da Silva Divino CPF: 297.110.268 80 | H104: REGISTRO DE PREÇOS PARA FUTURA E EVENTUAL AQUISIÇÃO DE MATERIAIS DE HIDRÁULICOS, PARA ATENDER ÀS NECESSIDADES DA PREFEITURA MUNICIPAL DE RIO GRANDE DA SERRA | I104: PE 18/25 | J104: 1060/2025 | K104: 2322/2025 | L104: 2025000000207 | M104: 588460.38 | N104: 45988 | O104: 45999 | P104: 08/12/2025 A 8/12/2026 | Q104: 46364
A105: =Q105-$A$1 -> 201 | B105: =IF(A105<60,"Vencendo","Em Vigência") -> Em Vigência | C105: 97/25 | D105: POUSO FARMA HOSPITALAR LTDA CNPJ sob o nº 18.519.219/0001-67 | E105: SAÚDE | F105: Heloisa Pereira da Silva | G105: Sara de Melo Silva Fernandes | H105: REGISTRO DE PREÇO PARA CONTRATAÇÃO DE EMPRESA PARA O FORNECIMENTO DE INSUMOS PARA O TRANSPORTE DE MEDICAMENTOS TERMOLÁBEIS E VACINAS | I105: PE - 37/25 | J105: 1584/2025 | K105: 2468/2025 | L105: 2025000000217 | M105: 4737.25 | N105: 45995 | O105: 46003 | P105: 12/12/2025 A 12/12/2026 | Q105: 46368
A106: =Q106-$A$1 -> 223 | B106: =IF(A106<60,"Vencendo","Em Vigência") -> Em Vigência | C106: 98/25 | D106: FORTALEZA REAL COMERCIO DE MATERIAIS E MANUTENÇÃO EM GERAL LTDA CNPJ sob o nº 20.661.647/0001-71 | E106: SAÚDE | F106: Silvana Moraes Branco Conceição | G106: Telma Moraes Pires | H106: REGISTRO DE PREÇO PARA FORNECIMENTO DE KIT DE MATERNIDADE PARA AS MULHERES EM SITUAÇÃO DE VULNERABILIDADE, INSCRITAS NO CRAS, NO SISTEMA DE SAÚDE PARA AS GESTANTES E OU OUTROS PROJETOS SOCIAIS DO MUNICÍPIO DE RIO GRANDE DA SERRA | I106: PE - 33/25 | J106: 1510/2025 | K106: 13/2026 | L106: 2025000000220 | M106: 150000 | N106: 46009 | O106: 46028 | P106: 06/01/2026 A 06/01/2027 | Q106: 46390
A107: =Q107-$A$1 -> 232 | B107: =IF(A107<60,"Vencendo","Em Vigência") -> Em Vigência | C107: 13/26 | D107: BELLAMED PRODUTOS HOSPITALARES LTDA CNPJ sob o nº 31.498.120/0001-94 | E107: SAÚDE | F107: Heloisa Pereira da Silva | G107: Sara de Melo Silva Fernandes | H107: REGISTRO DE PREÇOS PARA AQUISIÇÃO DE MATERIAIS E INSUMOS MEDICO-HOSPITALARES PARA ATENDER AS NECESSIDADES DA SECRETARIA DE SAÚDE DA PREFEITURA MUNICIPAL DE RIO GRANDE DA SERRA | I107: PE 27/25 | J107: 478/2025 | K107: 42/2026 | L107: 2025000000221 | M107: 1388628.6 | N107: 46031 | O107: 46034 | P107: 12/01/2026 a 12/01/2027 | Q107: 46399
A108: =Q108-$A$1 -> 250 | B108: =IF(A108<60,"Vencendo","Em Vigência") -> Em Vigência | C108: 14/26 | D108: PLANETA DOS DESCARTÁVEIS LTDA CNPJ sob o nº 45.645.750/0001-59 | E108: ADMINISTRAÇÃO | F108: Eduardo da Silva Divino CPF: 297.110.268-80 | G108: Kauê Rafael Lima Di Santi Pires | H108: REGISTRO DE PREÇO PARA FUTURA E EVENTUAL AQUISIÇÃO DE MATERIAL DE LIMPEZA, COM ENTREGA PARCELADA, DESTINADO ÀS SECRETARIAS MUNICIPAIS DA PREFEITURA DE RIO GRANDE DA SERRA | I108: PE 30/25 | J108: 664/2025 | K108: 170/2026 | L108: 2026000000002 | M108: 407012.95 | N108: 46052 | O108: 46052 | P108: 30/01/2026 a 30/01/2027 | Q108: 46417
A109: =Q109-'ATAS VIGENTES'!$A$1 -> 272 | B109: =IF(A109<60,"Vencendo","Em Vigência") -> Em Vigência | C109: 18/25 | D109: TRIUNFO ILUMINAÇÃO LTDA | E109: ADMINISTRAÇÃO | F109: Eduardo da Silva Divino | G109: Kauê Rafael Lima Di Santi Pires | H109: REGISTO DE PREÇOS PARA AQUISIÇÃO DE LÂMPADAS DE LED PARA USO NAS DIVERSAS SECRETARIAS DO MUNICÍPIO DE RIO GRANDE DA SERRA | I109: PE 39/24 | J109: 1236/2024 | K109: 298/2025 | L109: 2024000000302 | M109: 9078.84 | N109: 46073 | O109: 46148 | P109: 21/02/2026 a 21/02/2027 | Q109: 46439 | R109: ADITIVO
A110: =Q110-$A$1 -> 276 | B110: =IF(A110<60,"Vencendo","Em Vigência") -> Em Vigência | C110: 01/26 | D110: CIRURGICA UNIÃO LTDA CNPJ sob o nº 04.063.331/0001-21 | E110: SAÚDE | F110: Heloisa Pereira da Silva | G110: Sara de Melo Silva Fernandes | H110: REGISTRO DE PREÇOS PARA AQUISIÇÃO DE MATERIAIS E INSUMOS MEDICO-HOSPITALARES PARA ATENDER AS NECESSIDADES DA SECRETARIA DE SAÚDE DA PREFEITURA MUNICIPAL DE RIO GRANDE DA SERRA | I110: PE 27/25 | J110: 478/2025 | K110: 300/2026 | L110: 2025000000221 | M110: 1002717 | N110: 46038 | O110: 46078 | P110: 25/02/2026 a 25/02/2027 | Q110: 46443
A111: =Q111-$A$1 -> 276 | B111: =IF(A111<60,"Vencendo","Em Vigência") -> Em Vigência | C111: 02/26 | D111: CIRURGICA OLIMPIO - EIRELI CNPJ sob o nº 01.140.868/0001-50 | E111: SAÚDE | F111: Heloisa Pereira da Silva | G111: Sara de Melo Silva Fernandes | H111: REGISTRO DE PREÇOS PARA AQUISIÇÃO DE MATERIAIS E INSUMOS MEDICO-HOSPITALARES PARA ATENDER AS NECESSIDADES DA SECRETARIA DE SAÚDE DA PREFEITURA MUNICIPAL DE RIO GRANDE DA SERRA | I111: PE 27/25 | J111: 478/2025 | K111: 301/2026 | L111: 2025000000221 | M111: 770000 | N111: 46038 | O111: 46078 | P111: 25/02/2026 a 25/02/2027 | Q111: 46443
...

Sheet ATAS ENCERRADAS
A1: =TODAY() -> 46167 | B1: ATAS ENCERRADAS
B2: ATA | C2: Detentor | D2: Secretaria | E2: Gestor | F2: Fiscal | G2: Objeto | H2: Modalidade | I2: PC | J2: Processo Execução | K2: Audesp | L2: Valor Total Ata | M2: Assinatura | N2: Data da Publicação | O2: Vigência
A3: =P3-'ATAS VIGENTES'!$A$1 -> -31 | B3: 06/25 | C3: VILA BARCELONA COMERCIO DE SUPRIMENTOS E EQUIPAMENTOS EIRELI CNPJ sob o nº 22.719.411/0001-74 | D3: ADMINISTRAÇÃO | E3: Lucas Pereira Marques | F3: Kauê Rafael Lima Di Santi Pires | G3: REGISTRO DE PREÇO PARA FORNECIMENTO DE MATERIAL DE LIMPEZA PARA SUPRIR AS NECESSIDADES EVENTUAIS DAS SECRETARIAS PERTENCENTES À PREFEITURA MUNICIPAL DE RIO GRANDE DA SERRA | H3: PE 17/24 | I3: 961/2023 | J3: 757/2025 | K3: 2024000000304 | L3: 40300 | M3: 45764 | N3: 45771 | O3: 24/04/2025 a 24/04/2026 | P3: 46136
A4: =P4-'ATAS VIGENTES'!$A$1 -> -39 | B4: 21/25 | C4: INTERLAB FARMACÊUTICA LTDA | D4: SAÚDE | E4: Heloísa Pereira da Silva | F4: Sara de Melo Silva Fernandes | G4: REGISTRO DE PREÇOS DE MEDICAMENTOS PARA ATENDIMENTO DAS DEMANDAS JUDICIAIS DO MUNICÍPIO DE RIO GRANDE DA SERRA | H4: PE 21/25 | I4: 1887/2024 | J4: 624/2025 | K4: 2025000000133 | L4: R$ 3682,80 | M4: 45754 | N4: 45763 | O4: 16/04/2025 a 16/04/2026 | P4: 46128
A5: =P5-'ATAS VIGENTES'!$A$1 -> -45 | B5: 22/25 | C5: PHOENIX DISTRIBUIDORA E IMPORTADORA DE PRODUTOS FARMACÊUTICOS E CORRELATOS LTDA | D5: SAÚDE | E5: Heloísa Pereira da Silva | F5: Sara de Melo Silva Fernandes | G5: REGISTRO DE PREÇOS DE MEDICAMENTOS PARA ATENDIMENTO DAS DEMANDAS JUDICIAIS DO MUNICÍPIO DE RIO GRANDE DA SERRA | H5: PE 21/25 | I5: 1887/2024 | J5: 625/2025 | K5: 2025000000133 | L5: 594 | M5: 45750 | N5: 45757 | O5: 10/04/2025 A 10/04/2026 | P5: 46122
A6: =P6-'ATAS VIGENTES'!$A$1 -> -45 | B6: 23/25 | C6: PONTOMEDI DISTRIBUIDORA DE MEDICAMENTOS LTDA | D6: SAÚDE | E6: Heloísa Pereira da Silva | F6: Sara de Melo Silva Fernandes | G6: REGISTRO DE PREÇOS DE MEDICAMENTOS PARA ATENDIMENTO DAS DEMANDAS JUDICIAIS DO MUNICÍPIO DE RIO GRANDE DA SERRA | H6: PE 21/25 | I6: 1887/2024 | J6: 626/2025 | K6: 2025000000133 | L6: 2952 | M6: 45750 | N6: 45757 | O6: 10/04/2025 A 10/04/2026 | P6: 46122
A7: =P7-'ATAS VIGENTES'!$A$1 -> -45 | B7: 24/25 | C7: SULMEDIC COMÉRCIO DE MEDICAMENTOS LTDA | D7: SAÚDE | E7: Heloísa Pereira da Silva | F7: Sara de Melo Silva Fernandes | G7: REGISTRO DE PREÇOS DE MEDICAMENTOS PARA ATENDIMENTO DAS DEMANDAS JUDICIAIS DO MUNICÍPIO DE RIO GRANDE DA SERRA | H7: PE 21/25 | I7: 1887/2024 | J7: 627/2025 | K7: 2025000000133 | L7: 2620.8 | M7: 45750 | N7: 45757 | O7: 10/04/2025 A 10/04/2026 | P7: 46122
A8: =P8-'ATAS VIGENTES'!$A$1 -> -219 | B8: 50/24 | C8: MCW PRODUTOS MEDICOS E HOSPITALARES LTDA CNPJ - 94.389.400/0001-84 | D8: SAÚDE | E8: José Laércio de Lima | F8: Heloisa Pereira da Silva | G8: REGISTRO DE PREÇO PARA FORNECIMENTO DE MEDICAMENTOS INJETÁVEIS, VISANDO O ABASTECIMENTO DAS UNIDADES BÁSICAS DE SAÚDE E UPA DO MUNICÍPIO DE RIO GRANDE DA SERRA | H8: PE - 21/24 | I8: 1028/2024 | J8: 1863/2024 | K8: 2024000000255 | L8: 7378.26 | M8: 45580 | N8: 45583 | O8: 18/10/2024 A 18/10/2025 | P8: 45948
A9: =P9-'ATAS VIGENTES'!$A$1 -> -80 | B9: 08/25 | C9: YNEMED PRODUTOS MEDICOS E HOSPITALARES LTDA CNPJ sob o nº 51.740.794/0001-60 | D9: ADMINISTRAÇÃO | E9: Lucas Pereira Marques | F9: Kauê Rafael Lima Di Santi Pires | G9: REGISTRO DE PREÇO PARA FORNECIMENTO DE MATERIAL DE LIMPEZA PARA SUPRIR AS NECESSIDADES EVENTUAIS DAS SECRETARIAS PERTENCENTES À PREFEITURA MUNICIPAL DE RIO GRANDE DA SERRA | H9: PE 17/24 | I9: 961/2023 | J9: 335/2025 | K9: 2024000000304 | L9: 3488 | M9: 45706 | N9: 45722 | O9: 06/03/2025 a 06/03/2026 | P9: 46087
A10: =P10-'ATAS VIGENTES'!$A$1 -> -80 | B10: 04/25 | C10: NILSON DOS SANTOS UTILIDADES DO LAR EIRELLI CNPJ sob o nº 27.857.822/0001-40 | D10: ADMINISTRAÇÃO | E10: Lucas Pereira Marques | F10: Kauê Rafael Lima Di Santi Pires | G10: REGISTRO DE PREÇO PARA FORNECIMENTO DE MATERIAL DE LIMPEZA PARA SUPRIR AS NECESSIDADES EVENTUAIS DAS SECRETARIAS PERTENCENTES À PREFEITURA MUNICIPAL DE RIO GRANDE DA SERRA | H10: PE 17/24 | I10: 961/2023 | J10: 333/2025 | K10: 2024000000304 | L10: 32805 | M10: 45705 | N10: 45722 | O10: 06/03/2025 a 06/03/2026 | P10: 46087
A11: =P11-'ATAS VIGENTES'!$A$1 -> -87 | B11: 14/25 | C11: CITRUS INDUSTRIA E COMERCIO DE PRODUTOS DE LIMPEZA LTDA CNPJ sob o nº 53.279.738/0001-04 | D11: ADMINISTRAÇÃO | E11: Lucas Pereira Marques | F11: Kauê Rafael Lima Di Santi Pires | G11: REGISTRO DE PREÇO PARA FORNECIMENTO DE MATERIAL DE LIMPEZA PARA SUPRIR AS NECESSIDADES EVENTUAIS DAS SECRETARIAS PERTENCENTES À PREFEITURA MUNICIPAL DE RIO GRANDE DA SERRA | H11: PE 17/24 | I11: 961/2023 | J11: 415/2025 | K11: 2024000000304 | L11: 10175.5 | M11: 45715 | N11: 45715 | O11: 27/02/2025 a 27/02/2026 | P11: 46080
A12: =P12-'ATAS VIGENTES'!$A$1 -> -93 | B12: 20/25 | C12: GCM COMERCIAL LTDA | D12: ADMINISTRAÇÃO | E12: Kauê Rafael Lima Di Santi Pires | F12: Lucas Pereira Marques | G12: REGISTO DE PREÇOS PARA AQUISIÇÃO DE LÂMPADAS DE LED PARA USO NAS DIVERSAS SECRETARIAS DO MUNICÍPIO DE RIO GRANDE DA SERRA | H12: PE 39/24 | I12: 1236/2024 | J12: 300/2025 | K12: 2024000000302 | L12: 12565.6 | M12: 45706 | N12: 45709 | O12: 21/02/2025 a 21/02/2026 | P12: 46074
A13: =P13-'ATAS VIGENTES'!$A$1 -> -101 | B13: 19/25 | C13: WAF COMÉRCIO E SERVIÇOS LTDA | D13: ADMINISTRAÇÃO | E13: Kauê Rafael Lima Di Santi Pires | F13: Lucas Pereira Marques | G13: REGISTO DE PREÇOS PARA AQUISIÇÃO DE LÂMPADAS DE LED PARA USO NAS DIVERSAS SECRETARIAS DO MUNICÍPIO DE RIO GRANDE DA SERRA | H13: PE 39/24 | I13: 1236/2024 | J13: 299/2025 | K13: 2024000000302 | L13: 16967.5 | M13: 45699 | N13: 45701 | O13: 13/02/2025 a 13/02/2026 | P13: 46066
A15: =P15-'ATAS VIGENTES'!$A$1 -> -101 | B15: 17/25 | C15: MORK TELECON PRODUTOS E SERVIÇOS TELECOMUNICAÇÕES LTDA | D15: ADMINISTRAÇÃO | E15: Kauê Rafael Lima Di Santi Pires | F15: Lucas Pereira Marques | G15: REGISTO DE PREÇOS PARA AQUISIÇÃO DE LÂMPADAS DE LED PARA USO NAS DIVERSAS SECRETARIAS DO MUNICÍPIO DE RIO GRANDE DA SERRA | H15: PE 39/24 | I15: 1236/2024 | J15: 297/2025 | K15: 2024000000302 | L15: 349.7 | M15: 45700 | N15: 45702 | O15: 12/02/2025 a 13/02/2026 | P15: 46066
A16: =P16-'ATAS VIGENTES'!$A$1 -> -101 | B16: 16/25 | C16: IVANETE APARECIDA MIRANDA | D16: ADMINISTRAÇÃO | E16: Kauê Rafael Lima Di Santi Pires | F16: Lucas Pereira Marques | G16: REGISTO DE PREÇOS PARA AQUISIÇÃO DE LÂMPADAS DE LED PARA USO NAS DIVERSAS SECRETARIAS DO MUNICÍPIO DE RIO GRANDE DA SERRA | H16: PE 39/24 | I16: 1236/2024 | J16: 296/2025 | K16: 2024000000302 | L16: 2640 | M16: 45699 | N16: 45701 | O16: 13/02/2025 a 13/02/2026 | P16: 46066
A17: =P17-'ATAS VIGENTES'!$A$1 -> -101 | B17: 15/25 | C17: BA LUZ INDÚSTRIA E COMÉRCIO DE MATERIAIS ELÉTRICOS LTDA | D17: ADMINISTRAÇÃO | E17: Kauê Rafael Lima Di Santi Pires | F17: Lucas Pereira Marques | G17: REGISTO DE PREÇOS PARA AQUISIÇÃO DE LÂMPADAS DE LED PARA USO NAS DIVERSAS SECRETARIAS DO MUNICÍPIO DE RIO GRANDE DA SERRA | H17: PE 39/24 | I17: 1236/2024 | J17: 295/2025 | K17: 202400000302 | L17: 27553.04 | M17: 45699 | N17: 45701 | O17: 13/02/2025 a 13/02/2026 | P17: 46066
... A62: =P62-'ATAS VIGENTES'!$A$1 -> -227 | B62: 38/24 | C62: ACÁCIA COMÉRCIO DE MEDICAMENTOS LTDA CNPJ - 03.945.035/0001-91 | D62: SAÚDE | E62: José Laércio de Lima | F62: Heloisa Pereira da Silva | G62: REGISTRO DE PREÇO PARA FORNECIMENTO DE MEDICAMENTOS INJETÁVEIS, VISANDO O ABASTECIMENTO DAS UNIDADES BÁSICAS DE SAÚDE E UPA DO MUNICÍPIO DE RIO GRANDE DA SERRA | H62: PE - 21/24 | I62: 1028/2024 | J62: 1856/2024 | K62: 2024000000255 | L62: 891.6 | M62: 45572 | N62: 45575 | O62: 10/10/2024 A 10/10/2025 | P62: 45940
A63: =P63-'ATAS VIGENTES'!$A$1 -> -228 | B63: 37/24 | C63: DV COMÉRCIO E REPRESENTAÇÃO COMERCIAL LTDA CNPJ - 08.170.178/0001-92 | D63: ADMINISTRAÇÃO | E63: Lucas Pereira Marques | F63: Kauê Rafael Lima di Santis Pires | G63: REGISTRO DE PREÇOS REGISTRO DE PREÇOS PARA FUTURA AQUISIÇÃO DE PAPEL SULFITE PARA ATENDER AS NECESSIDADES DA PREFEITURA NO MUNICÍPIO DE RIO GRANDE DA SERRA | H63: PE - 26/24 | I63: 1269/2024 | J63: 1838/2024 | K63: 2024000000253 | L63: R$ 3000,00 | M63: 45569 | N63: 45574 | O63: 09/10/2024 A 09/10/2025 | P63: 45939
A64: =P64-$A$1 -> -234 | B64: 36/24 | C64: MULTPAPER DISTRIBUIDORA DE PAPÉIS LTDA CNPJ - 26.976.381/0005-66 | D64: ADMINISTRAÇÃO | E64: Lucas Pereira Marques | F64: Kauê Rafael Lima di Santis Pires | G64: REGISTRO DE PREÇOS REGISTRO DE PREÇOS PARA FUTURA AQUISIÇÃO DE PAPEL SULFITE PARA ATENDER AS NECESSIDADES DA PREFEITURA NO MUNICÍPIO DE RIO GRANDE DA SERRA | H64: PE - 26/24 | I64: 1269/2024 | J64: 1837/2024 | K64: 2024000000253 | L64: 295500 | M64: 45559 | N64: 45568 | O64: 03/10/2024 A 03/10/2025 | P64: 45933
A65: =P65-'ATAS VIGENTES'!$A$1 -> -236 | B65: 35/24 | C65: SOMAR INDÚSTRIA E COMÉRCIO LTDA CNPJ - 32.237.610/0001-08 | D65: SAÚDE | E65: Heloisa Pereira da Silva | F65: José Laercio de Lima | G65: REGISTRO DE PREÇOS PARA FUTURA E EVENTUAL AQUISIÇÃO DE FRALDAS PEDIÁTRICAS E GERIÁTRICAS, COM ENTREGA FRACIONADA, DESTINADAS AO ATENDIMENTO DE PACIENTES CADASTRADOS NAS UNIDADES BÁSICAS DE SAÚDE, PARA ATENDER AS NECESSIDADES DA SECRETARIA MUNICIPAL DE SAÚDE DO MUNICÍPIO DE RIO GRANDE DA SERRA | H65: PE - 14/24 | I65: 2412/2023 | J65: 1843/2024 | K65: 2024000000249 | L65: 22080 | M65: 45586 | N65: 45566 | O65: 01/10/2024 A 01/10/2025 | P65: 45931
A66: =P66-'ATAS VIGENTES'!$A$1 -> -236 | B66: 34/24 | C66: BELLAMED PRODUTOS HOSPITALARES LTDA CNPJ - 31.498.120/0001-94 | D66: SAÚDE | E66: Heloisa Pereira da Silva | F66: José Laercio de Lima | G66: REGISTRO DE PREÇOS PARA FUTURA E EVENTUAL AQUISIÇÃO DE FRALDAS PEDIÁTRICAS E GERIÁTRICAS, COM ENTREGA FRACIONADA, DESTINADAS AO ATENDIMENTO DE PACIENTES CADASTRADOS NAS UNIDADES BÁSICAS DE SAÚDE, PARA ATENDER AS NECESSIDADES DA SECRETARIA MUNICIPAL DE SAÚDE DO MUNICÍPIO DE RIO GRANDE DA SERRA | H66: PE - 14/24 | I66: 2412/2023 | J66: 1844/2024 | K66: 2024000000249 | L66: 555828 | M66: 45585 | N66: 45566 | O66: 01/10/2024 A 01/10/2025 | P66: 45931
A67: =P67-'ATAS VIGENTES'!$A$1 -> -263 | B67: 33/24 | C67: ARCAPES SERVIÇOS ESPECIALIZADOS LTDA CNPJ - 14.200.757/0001-33 | D67: OBRAS | E67: Leila Andreassi de Castro | F67: João Victor Silva | G67: CONTRATAÇÃO DE EMPRESA PARA PRESTAÇÃO DE SERVIÇOS DE MANUTENÇÃO PREVENTIVA E CORRETIVA NOS PRÓPRIOS MUNICIPAIS | H67: CO - 02/24 | I67: 619/2024 | J67: 1710/2024 | K67: 2024000000245 | L67: 8979278.7 | M67: 45539 | N67: 45545 | O67: 04/09/2024 A 04/09/2025 | P67: 45904
A68: =P68-'ATAS VIGENTES'!$A$1 -> -263 | B68: 32/24 | C68: VRM COMÉRCIO E SERVIÇOS LTDA CNPJ - 31.868.626/0001-48 | D68: ADMINISTRAÇÃO | E68: Lucas Pereira Marques | F68: Kauê Rafael Lima di Santis Pires | G68: REGISTRO DE PREÇOS PARA FORNECIMENTO DE MATERIAL DE ESCRITÓRIO/EXPEDIENTE PARA SUPRIR AS NECESSIDADES EVENTUAIS DAS SECRETARIAS PERTENCENTES À PREFEITURA MUNICIPAL DE RIO GRANDE DA SERRA | H68: PE - 15/24 | I68: 962/2023 | J68: 1621/2024 | K68: 2024000000226 | L68: 2378.15 | M68: 45533 | N68: 45539 | O68: 04/09/2024 A 04/09/2025 | P68: 45904
A69: =P69-'ATAS VIGENTES'!$A$1 -> -271 | B69: 31/24 | C69: LICITASHOP COMÉRCIO E SERVIÇOS LTDA CNPJ - 50.958.011/0001-57 | D69: ADMINISTRAÇÃO | E69: Lucas Pereira Marques | F69: Kauê Rafael Lima di Santis Pires | G69: REGISTRO DE PREÇOS PARA FORNECIMENTO DE MATERIAL DE ESCRITÓRIO/EXPEDIENTE PARA SUPRIR AS NECESSIDADES EVENTUAIS DAS SECRETARIAS PERTENCENTES À PREFEITURA MUNICIPAL DE RIO GRANDE DA SERRA | H69: PE - 15/24 | I69: 962/2023 | J69: 1620/2024 | K69: 2024000000226 | L69: 6441.85 | M69: 45531 | N69: 45531 | O69: 27/08/2024 A 27/08/2025 | P69: 45896
A70: =P70-'ATAS VIGENTES'!$A$1 -> -257 | B70: 30/24 | C70: CANAÃ DISTRIBUIDORA E COMÉRCIO EIRELI EPP CNPJ - 21.278.096/0001-24 | D70: ADMINISTRAÇÃO | E70: Lucas Pereira MarqueS | F70: Kauê Rafael Lima di Santis Pires | G70: REGISTRO DE PREÇOS PARA FORNECIMENTO DE MATERIAL DE ESCRITÓRIO/EXPEDIENTE PARA SUPRIR AS NECESSIDADES EVENTUAIS DAS SECRETARIAS PERTENCENTES À PREFEITURA MUNICIPAL DE RIO GRANDE DA SERRA | H70: PE - 15/24 | I70: 962/2023 | J70: 1619/2024 | K70: 2024000000226 | L70: 9134.6 | M70: 45544 | N70: 45545 | O70: 10/09/2024 A 10/09/2025 | P70: 45910
A71: =P71-'ATAS VIGENTES'!$A$1 -> -271 | B71: 29/24 | C71: ANGELIQUE ORLANDINA CORREA CNPJ - 15.508.827/0001-88 | D71: ADMINISTRAÇÃO | E71: Lucas Pereira MarqueS | F71: Kauê Rafael Lima di Santis Pires | G71: REGISTRO DE PREÇOS PARA FORNECIMENTO DE MATERIAL DE ESCRITÓRIO/EXPEDIENTE PARA SUPRIR AS NECESSIDADES EVENTUAIS DAS SECRETARIAS PERTENCENTES À PREFEITURA MUNICIPAL DE RIO GRANDE DA SERRA | H71: PE - 15/24 | I71: 962/2023 | J71: 1618/2024 | K71: 2024000000226 | L71: 90158.57 | M71: 45531 | N71: 45531 | O71: 27/08/2024 A 27/08/2025 | P71: 45896
A72: =P72-'ATAS VIGENTES'!$A$1 -> -263 | B72: 28/24 | C72: ALIANÇA COMÉRCIO E DISTRIBUIÇÃO LTDA CNPJ - 31.486.195/0001-55 | D72: ADMINISTRAÇÃO | E72: Lucas Pereira MarqueS | F72: Kauê Rafael Lima di Santis Pires | G72: REGISTRO DE PREÇOS PARA FORNECIMENTO DE MATERIAL DE ESCRITÓRIO/EXPEDIENTE PARA SUPRIR AS NECESSIDADES EVENTUAIS DAS SECRETARIAS PERTENCENTES À PREFEITURA MUNICIPAL DE RIO GRANDE DA SERRA | H72: PE - 15/24 | I72: 962/2023 | J72: 1623/2024 | K72: 2024000000226 | L72: 126822.35 | M72: 45532 | N72: 45539 | O72: 04/09/2024 A 04/09/2025 | P72: 45904
A73: =P73-'ATAS VIGENTES'!$A$1 -> -305 | B73: 26/24 | C73: DANIEL LOPES TOLAINE ME CNPJ - 12.870.090/0001-50 | D73: ADMINISTRAÇÃO | E73: Lucas Pereira Marques | F73: Kauê Rafael Lima di Santis Pires | G73: REGISTRO DE PREÇO PARA EVENTUAIS AQUISIÇÕES DE MOBILIÁRIO EM GERAL, DESTINADOS AS SECRETARIAS MUNICIPAIS DA PREFEITURA DE RIO GRANDE DA SERRA | H73: PE - 6/2024 | I73: 2466/2023 | J73: 1416/2024 | K73: 2024000000221 | L73: 48800 | M73: 45496 | N73: 45497 | O73: 24/07/2024 A 24/07/2025 | P73: 45862
A74: =P74-'ATAS VIGENTES'!$A$1 -> -299 | B74: 25/24 | C74: ZIRICO MOVEIS LTDA CNPJ - 26.656.774/0001-69 | D74: ADMINISTRAÇÃO | E74: Lucas Pereira Marques | F74: Kauê Rafael Lima di Santis Pires | G74: REGISTRO DE PREÇO PARA EVENTUAIS AQUISIÇÕES DE MOBILIÁRIO EM GERAL, DESTINADOS AS SECRETARIAS MUNICIPAIS DA PREFEITURA DE RIO GRANDE DA SERRA | H74: PE - 6/2024 | I74: 2466/2023 | K74: 2024000000221 | L74: 6500 | M74: 45502 | N74: 45503 | O74: 30/07/2024 A 30/07/2025 | P74: 45868
A75: =P75-'ATAS VIGENTES'!$A$1 -> -305 | B75: 24/24 | C75: ORTHOVIDA INDUSTRIA E NEGOCIOS DIGITAIS LTDA CNPJ - 14.323.297/0001-30 | D75: ADMINISTRAÇÃO | E75: Lucas Pereira Marques | F75: Kauê Rafael Lima di Santis Pires | G75: REGISTRO DE PREÇO PARA EVENTUAIS AQUISIÇÕES DE MOBILIÁRIO EM GERAL, DESTINADOS AS SECRETARIAS MUNICIPAIS DA PREFEITURA DE RIO GRANDE DA SERRA | H75: PE - 6/2024 | I75: 2466/2023 | J75: 1415/2024 | K75: 2024000000221 | L75: 27882.79 | M75: 45496 | N75: 45497 | O75: 24/07/2024 A 24/07/2025 | P75: 45862
A76: =P76-'ATAS VIGENTES'!$A$1 -> -305 | B76: 23/24 | C76: SOLDDINOX DISTRIBUIDORA DE EQUIPAMENTOS LTDA CNPJ - 50.125.548/0001-36 | D76: ADMINISTRAÇÃO | E76: Lucas Pereira Marques | F76: Kauê Rafael Lima di Santis Pires | G76: REGISTRO DE PREÇO PARA EVENTUAIS AQUISIÇÕES DE MOBILIÁRIO EM GERAL, DESTINADOS AS SECRETARIAS MUNICIPAIS DA PREFEITURA DE RIO GRANDE DA SERRA | H76: PE - 6/2024 | I76: 2466/2023 | J76: 1412/2024 | K76: 2024000000221 | L76: 32300 | M76: 45497 | N76: 45497 | O76: 24/07/2024 A 24/07/2025 | P76: 45862
A77: =P77-'ATAS VIGENTES'!$A$1 -> -305 | B77: 22/24 | C77: ARICANDUVA COMERCIO DE ARTIGOS DE PLÁSTICO EIRELI CNPJ - 41.770.193/0001-47 | D77: ADMINISTRAÇÃO | E77: Lucas Pereira Marques | F77: Kauê Rafael Lima di Santis Pires | G77: REGISTRO DE PREÇO PARA EVENTUAIS AQUISIÇÕES DE MOBILIÁRIO EM GERAL, DESTINADOS AS SECRETARIAS MUNICIPAIS DA PREFEITURA DE RIO GRANDE DA SERRA | H77: PE - 6/2024 | I77: 2466/2023 | J77: 1414/2024 | K77: 2024000000221 | L77: 11267.5 | M77: 45496 | N77: 45497 | O77: 24/07/2024 A 24/07/2025 | P77: 45862
A78: =P78-'ATAS VIGENTES'!$A$1 -> -305 | B78: 21/24 | C78: M&M BOMBONATO MOVEIS LTDA CNPJ - 36.316.683/0001-38 | D78: ADMINISTRAÇÃO | E78: Lucas Pereira Marques | F78: Kauê Rafael Lima di Santis Pires | G78: REGISTRO DE PREÇO PARA EVENTUAIS AQUISIÇÕES DE MOBILIÁRIO EM GERAL, DESTINADOS AS SECRETARIAS MUNICIPAIS DA PREFEITURA DE RIO GRANDE DA SERRA | H78: PE - 6/2024 | I78: 2466/2023 | J78: 1413/2024 | K78: 2024000000221 | L78: 40250 | M78: 45496 | N78: 45497 | O78: 24/07/2024 A 24/07/2025 | P78: 45862
A79: =P79-'ATAS VIGENTES'!$A$1 -> -305 | B79: 20/24 | C79: WOOD STEEL COMERCIO DE MOVEIS LTDA CNPJ - 47.863.106/0001-82 | D79: ADMINISTRAÇÃO | E79: Lucas Pereira Marques | F79: Kauê Rafael Lima di Santis Pires | G79: REGISTRO DE PREÇO PARA EVENTUAIS AQUISIÇÕES DE MOBILIÁRIO EM GERAL, DESTINADOS AS SECRETARIAS MUNICIPAIS DA PREFEITURA DE RIO GRANDE DA SERRA | H79: PE - 6/2024 | I79: 2466/2023 | J79: 1412/2024 | K79: 2024000000221 | L79: 22945.2 | M79: 45496 | N79: 45497 | O79: 24/07/2024 A 24/07/2025 | P79: 45862
A80: =P80-'ATAS VIGENTES'!$A$1 -> -305 | B80: 19/24 | C80: FOX INDUSTRIA METALURGICA LTDA CNPJ - 29.178.797/00001-01 | D80: ADMINISTRAÇÃO | E80: Lucas Pereira Marques | F80: Kauê Rafael Lima di Santis Pires | G80: REGISTRO DE PREÇO PARA EVENTUAIS AQUISIÇÕES DE MOBILIÁRIO EM GERAL, DESTINADOS AS SECRETARIAS MUNICIPAIS DA PREFEITURA DE RIO GRANDE DA SERRA | H80: PE - 6/2024 | I80: 2466/2023 | J80: 1411/2024 | K80: 2024000000221 | L80: 56290 | M80: 45496 | N80: 45497 | O80: 24/07/2024 A 24/07/2025 | P80: 45862
A81: =P81-'ATAS VIGENTES'!$A$1 -> -305 | B81: 18/24 | C81: ESPAÇO A MOVEIS PLANEJADOS LTDA CNPJ - 09.066.243/0001-05 | D81: ADMINISTRAÇÃO | E81: Lucas Pereira Marques | F81: Kauê Rafael Lima di Santis Pires | G81: REGISTRO DE PREÇO PARA EVENTUAIS AQUISIÇÕES DE MOBILIÁRIO EM GERAL, DESTINADOS AS SECRETARIAS MUNICIPAIS DA PREFEITURA DE RIO GRANDE DA SERRA | H81: PE - 6/2024 | I81: 2466/2023 | J81: 1410/2024 | K81: 2024000000221 | L81: 71110 | M81: 45496 | N81: 45497 | O81: 24/07/2024 A 24/07/2025 | P81: 45862
A82: =P82-'ATAS VIGENTES'!$A$1 -> -306 | B82: 17/24 | C82: BEL MICRO TECNOLOGIA S/A CNPJ - 71.052.559/0001-03 | D82: ADMINISTRAÇÃO | E82: Lucas Pereira Marques | F82: Kauê Rafael Lima di Santis Pires | G82: REGISTRO DE PREÇOS PARA FUTURA E EVENTUAL AQUISIÇÃO DE VENTILADORES, APARELHOS DE AR CONDICIONADO E AQUECEDORES DE AMBIENTE, COM ENTREGA FRACIONADA, PARA ATENDER AS NECESSIDADES DAS SECRETARIAS MUNICIPAIS DO MUNICÍPIO DE RIO GRANDE DA SERRA | H82: PE - 16/2024 | I82: 2228/2023 | J82: 1409/2024 | K82: 2024000000216 | L82: 300000 | M82: 45496 | N82: 45497 | O82: 23/07/2024 A 23/07/2025 | P82: 45861
A83: =P83-'ATAS VIGENTES'!$A$1 -> -310 | B83: 16/24 | C83: ESPAÇO 2 TECNOLOGIA E INFORMÁTICA LTDA - EPP CNPJ - 09.066.243/0001-05 | D83: ADMINISTRAÇÃO | E83: Lucas Pereira Marques | F83: Kauê Rafael Lima di Santis Pires | G83: REGISTRO DE PREÇOS PARA FUTURA E EVENTUAL AQUISIÇÃO DE VENTILADORES, APARELHOS DE AR CONDICIONADO E AQUECEDORES DE AMBIENTE, COM ENTREGA FRACIONADA, PARA ATENDER AS NECESSIDADES DAS SECRETARIAS MUNICIPAIS DO MUNICÍPIO DE RIO GRANDE DA SERRA | H83: PE - 16/2024 | I83: 2228/2023 | J83: 1408/2024 | K83: 2024000000216 | L83: 25982.88 | M83: 45492 | N83: 45497 | O83: 19/07/2024 A 19/07/2025 | P83: 45857
A84: =P84-'ATAS VIGENTES'!$A$1 -> -279 | B84: 15/24 | C84: FERRINI COMERCIO E CONSULTORIA LTDA ME CNPJ - 13.642.211/0001-70 | D84: ADMINISTRAÇÃO | E84: Lucas Pereira Marques | F84: Kauê Rafael Lima di Santis Pires | G84: REGISTRO DE PREÇOS PARA FUTURA E EVENTUAL AQUISIÇÃO DE VENTILADORES, APARELHOS DE AR CONDICIONADO E AQUECEDORES DE AMBIENTE, COM ENTREGA FRACIONADA, PARA ATENDER AS NECESSIDADES DAS SECRETARIAS MUNICIPAIS DO MUNICÍPIO DE RIO GRANDE DA SERRA | H84: PE - 16/2024 | I84: 2228/2023 | J84: 1436/2024 | K84: 2024000000216 | L84: 73124.5 | M84: 45523 | N84: 45525 | O84: 19/08/2024 A 19/08/2025 | P84: 45888
A85: =P85-'ATAS VIGENTES'!$A$1 -> -381 | B85: 11/24 | C85: RIO PRETO DISTRIBUIÇÃO DE EQUIPAMENTOS DE INFORMÁTICA E TECNOLOGIA LTDA CNPJ - 33.937.002/0001-60 | D85: ADMINISTRAÇÃO | E85: Elias Rodrigues de Prado | F85: Guilherme Rodrigues | G85: REGISTRO DE PREÇOS PARA FORNECIMENTO DE COMPUTADORES, PARA ATENDER AS NECESSIDADES DAS SECRETARIAS PERTENCENTES À PREFEITURA MUNICIPAL DE RIO GRANDE DA SERRA | H85: PP - 49/2023 | I85: 1355/2023 | J85: 883/2024 | K85: 2024000000167 | L85: 79400 | M85: 45419 | N85: 45421 | O85: 09/05/2024 A 09/05/2025 | P85: 45786
A86: =P86-'ATAS VIGENTES'!$A$1 -> -381 | B86: 10/24 | C86: SHANX LTDA CNPJ - 51.014.023/0001-96 | D86: ADMINISTRAÇÃO | E86: Elias Rodrigues de Prado | F86: Guilherme Rodrigues | G86: REGISTRO DE PREÇOS PARA FORNECIMENTO DE COMPUTADORES, PARA ATENDER AS NECESSIDADES DAS SECRETARIAS PERTENCENTES À PREFEITURA MUNICIPAL DE RIO GRANDE DA SERRA | H86: PP - 49/2023 | I86: 1355/2023 | J86: 882/2024 | K86: 2024000000167 | L86: 160000 | M86: 45421 | N86: 45421 | O86: 09/05/2024 A 09/05/2025 | P86: 45786
A87: =P87-'ATAS VIGENTES'!$A$1 -> -381 | B87: 09/24 | C87: ESPAÇO 2 TECNOLOGIA E INFORMÁTICA LTDA - EPP CNPJ - 09.066.243/0001-05 | D87: ADMINISTRAÇÃO | E87: Elias Rodrigues de Prado | F87: Guilherme Rodrigues | G87: REGISTRO DE PREÇOS PARA FORNECIMENTO DE COMPUTADORES, PARA ATENDER AS NECESSIDADES DAS SECRETARIAS PERTENCENTES À PREFEITURA MUNICIPAL DE RIO GRANDE DA SERRA | H87: PP - 49/2023 | I87: 1355/2023 | J87: 881/2024 | K87: 2024000000167 | L87: 148000 | M87: 45419 | N87: 45421 | O87: 09/05/2024 A 09/05/2025 | P87: 45786
A88: =P88-$A$1 -> -380 | B88: 08/24 | C88: GENESIS NEGÓCIOS E SERVIÇOS LTDA CNPJ - 53.274.781/0001-79 | D88: ADMINISTRAÇÃO | E88: Elias Rodrigues de Prado | F88: Guilherme Rodrigues | G88: REGISTRO DE PREÇOS PARA FORNECIMENTO DE COMPUTADORES, PARA ATENDER AS NECESSIDADES DAS SECRETARIAS PERTENCENTES À PREFEITURA MUNICIPAL DE RIO GRANDE DA SERRA | H88: PP - 49/2023 | I88: 1355/2023 | J88: 880/2024 | K88: 2024000000167 | L88: 530000 | M88: 45422 | N88: 45422 | O88: 10/05/2024 A 10/05/2025 | P88: 45787
A89: =P89-'ATAS VIGENTES'!$A$1 -> -424 | B89: 07/24 | C89: ESPAÇO 2 TECNOLOGIA E INFORMÁTICA LTDA - EPP CNPJ - 09.066.243/0001-05 | D89: ADMINISTRAÇÃO | E89: Josiani Cristina de Araújo Macedo | F89: Elias Rodrigues de Prado | G89: REGISTRO DE PREÇO PARA FORNECIMENTO DE TONNER E CARTUCHO DE TINTAS PARA AS IMPRESSORAS PERTENCENTES A PREFEITURA MUNICIPAL DE RIO GRANDE DA SERRA. | H89: PP - 58/2023 | I89: 2137/2023 | J89: 595/2024 | K89: 2024000000124 | L89: 303730 | M89: 45373 | N89: 45378 | O89: 27/03/2024 A 27/03/2025 | P89: 45743
A90: =P90-'ATAS VIGENTES'!$A$1 -> -424 | B90: 06/24 | C90: GARLOC TRANSPORTES, LOGISTICA E LOCAÇÕES LTDA CNPJ - 69.205.789/0001-13 | D90: EDUCAÇÃO | E90: Lamartine Dourado Cavalcante | F90: Ari Inácio de Souza | G90: CONTRATAÇÃO DE EMPRESA ESPECIALIZADA PARA TERCEIRIZAÇÃO DE FROTAS MEDIANTE FORNECIMENTO DE VEÍCULOS DO TIPO VAN E MICRO ÔNIBUS PARA TRANSPORTES ESCOLARES DO MUNICÍPIO, COM FORNECIMENTO DE COMBUSTÍVEL, PNEUS, MANUTENÇÕES, MOTORISTAS E TRIPULANTES, PARA ATENDER AS ATIVIDADES DA SECRETARIA DE EDUCAÇÃO E CULTURA DO MUNICÍPIO. REFERIDO TRANSPORTE ESTÁ INCLUÍDO AS ATIVIDADES CULTURAIS E DE LAZER REALIZADAS FORA DA UNIDADE ESCOLAR | H90: PP - 54/2023 | I90: 2413/2023 | J90: 596/2024 | K90: 2024000000140 | L90: 11454000 | M90: 45376 | N90: 45378 | O90: 27/03/2024 A 27/03/2025 | P90: 45743
A91: =P91-'ATAS VIGENTES'!$A$1 -> -430 | B91: 05/24 | C91: DC INFINITY COMERCIALIZADORA E DISTRIBUIDORA LTDA CNPJ - 32.727.217/0001-94 | D91: ADMINISTRAÇÃO | E91: Mariana Aparecida Aricó Donaire | F91: Mariana Aparecida Aricó Donaire | G91: REGISTRO DE PREÇOS PARA EVENTUAL FORNECIMENTO DE ÁGUA MINERAL, BEBEDOURO E SUPORTE, PARA ATENDER ÀS NECESSIDADES DAS SECRETARIAS E UNIDADES DA PREFEITURA MUNICIPAL DE RIO GRANDE DA SERRA | H91: PP - 55/2023 | I91: 2371/2023 | J91: 540/2024 | K91: 2024000000139 | L91: 99930 | M91: 45370 | N91: 45372 | O91: 21/03/2024 A 21/03/2025 | P91: 45737
A92: =P92-'ATAS VIGENTES'!$A$1 -> -430 | B92: 04/24 | C92: RGSE PROJETOS E ENGENHARIA LTDA CNPJ - 38.880.696/0001-60 | D92: OBRAS | E92: Kléber Avelino de Oliveira | F92: Adriano de Sousa Pereira | G92: REGISTRO DE PREÇOS PARA CONTRATAÇÃO DE EMPRESA ESPECIALIZADA PARA A PRESTAÇÃO DE SERVIÇOS DE ASSESSORIA TÉCNICA E APOIO OPERACIONAL PARA IMPLANTAÇÃO, ELABORAÇÃO, ACOMPANHAMENTO TÉCNICO, GERENCIAMENTO E FISCALIZAÇÃO DE PROJETOS E/OU OBRAS DO MUNICÍPIO DE RIO GRANDE DA SERRA – SP | H92: CO - 14/2023 | I92: 2028/2022 | J92: 547/2024 | K92: 2024000000137 | L92: 4283761.1 | M92: 45371 | N92: 45372 | O92: 21/03/2024 A 21/03/2025 | P92: 45737
A93: =P93-'ATAS VIGENTES'!$A$1 -> -447 | B93: 03/24 | C93: FORTALEZA REAL COMERCIAL DE MATERIAIS E MANUTENÇÃO EM GERAL LTDA ME CNPJ: 20.661.647/0001-71 | D93: SAÚDE | E93: Silvana Moraes Branco Conceição CPF: 140.431.098-30 | F93: Patrícia Aparecida Santiago CPF: 268.187.788-10 | G93: REGISTRO DE PREÇOS PARA FORNECIMENTO DE MATERIAL DE USO ODONTOLÓGICO NAS UNIDADES DA SECRETARIA DE SAÚDE NO MUNICÍPIO DE RIO GRANDE DA SERRA | H93: PP - 57/2023 | I93: 935/2023 | J93: 445/2024 | K93: 2024000000125 | L93: 11250 | M93: 45342 | N93: 45355 | O93: 04/03/2024 A 04/03/2025 | P93: 45720
A94: =P94-'ATAS VIGENTES'!$A$1 -> -447 | B94: 02/24 | C94: CIRURGICA UNIÃO LTDA CNPJ - 04.063.331/0001-21 | D94: SAÚDE | E94: Silvana Moraes Branco Conceição CPF: 140.431.098-30 | F94: Patrícia Aparecida Santiago CPF: 268.187.788-10 | G94: REGISTRO DE PREÇOS PARA FORNECIMENTO DE MATERIAL DE USO ODONTOLÓGICO NAS UNIDADES DA SECRETARIA DE SAÚDE NO MUNICÍPIO DE RIO GRANDE DA SERRA | H94: PP - 57/2023 | I94: 935/2023 | J94: 444/2024 | K94: 2024000000125 | L94: 80049.9 | M94: 45342 | N94: 45355 | O94: 04/03/2024 A 04/03/2025 | P94: 45720
